Workbook
Name _1B.05.M.010.0010: #REF!
Name _1B.05.M.010.0010: #REF!
Name _1B.05.M.010.0010: #REF!
Name _1B.05.M.010.0050: #REF!
Name _1B.05.M.010.0050: #REF!
Name _1B.05.M.0100.0010: #REF!
Name _1B.05.M.0100.0010: #REF!
Name _1B.05.M.020.0010: #REF!
Name _1B.05.M.020.0010: #REF!
Name _1B.05.M.020.0020: #REF!
Name _1B.05.M.020.0020: #REF!
Name _1B.05.M.020.0030: #REF!
Name _1B.05.M.020.0030: #REF!
Name _1B.05.M.020.0040: #REF!
Name _1B.05.M.020.0040: #REF!
Name _1B.05.M.030.0010: #REF!
Name _1B.05.M.030.0010: #REF!
Name _1B.05.M.030.0020: #REF!
Name _1B.05.M.030.0020: #REF!
Name _1B.05.M.040.0010: #REF!
Name _1B.05.M.040.0010: #REF!
Name _1B.05.M.050.0010: #REF!
Name _1B.05.M.050.0010: #REF!
Name _1B.05.M.050.0020: #REF!
Name _1B.05.M.050.0020: #REF!
Name _1B.05.M.050.0030: #REF!
Name _1B.05.M.050.0030: #REF!
Name _1B.05.M.060.0020: #REF!
Name _1B.05.M.060.0020: #REF!
Name _1B.05.M.060.0100: #REF!
Name _1B.05.M.060.0100: #REF!
Name _1B.05.M.070.0010: #REF!
Name _1B.05.M.070.0010: #REF!
Name _1B.05.M.070.0020: #REF!
Name _1B.05.M.070.0020: #REF!
Name _1B.05.M.070.0030: #REF!
Name _1B.05.M.070.0030: #REF!
Name _1B.05.M.070.0040: #REF!
Name _1B.05.M.070.0040: #REF!
Name _1B.05.M.070.0050: #REF!
Name _1B.05.M.070.0050: #REF!
Name _1B.05.M.080.0010: #REF!
Name _1B.05.M.080.0010: #REF!
Name _1B.05.M.090.0010: #REF!
Name _1B.05.M.090.0010: #REF!
Name _1B.09.P.010.0010: #REF!
Name _1B.09.P.010.0010: #REF!
Name _1B.09.P.010.0020: #REF!
Name _1B.09.P.010.0020: #REF!
Name _1B.09.P.010.0030: #REF!
Name _1B.09.P.010.0030: #REF!
Name _1B.09.P.010.0040: #REF!
Name _1B.09.P.010.0040: #REF!
Name _1B.09.P.010.0050: #REF!
Name _1B.09.P.010.0050: #REF!
Name _1B.09.P.010.0060: #REF!
Name _1B.09.P.010.0060: #REF!
Name _1B.09.P.010.0070: #REF!
Name _1B.09.P.010.0070: #REF!
Name _1B.09.P.020.0010: #REF!

Sheet Weekly Progress Report
A1: MODON - Weekly Progress Report - Construction Projects | AF1: Data Date | AG1: ='General Information'!L1 -> 46314
A2: Contract General Information | G2: Key Dates | M2: Cost Summary (SR) | U2: Performance Summary | AA2: Project Scope
A3: Project Name | B3: ='General Information'!C3 -> Construction of Passenger Station for SAR Railway Sudair Industrial City | G3: Contract Award | H3: ='General Information'!C12 -> 46112 | I3: Contract Award (Hijri) | J3: ='General Information'!C16 -> 10/12/1447 | K3: Revised Completion | L3: ='General Information'!C20 -> 46119 | M3: Original Contract Value | O3: ='Invoice Log'!F3 -> 33090825 | Q3: O&M Value | S3: ='Invoice Log'!J3 -> 0 | T3: EAC | U3: Plan Value | V3: =K44 -> 0.19043972 | W3: Phys. Plan Value | X3: =W44 -> 0.38056579 | Y3: Quality Score | Z3: =Quality.!AC10 -> 0.88724138 | AA3: Civil Work , Storm Water Drainage , Sewer , Portable , Electrical , CCTV
A4: Project ID | B4: ='General Information'!C4 -> SUD1-05-018 | D4: Stage | E4: ='General Information'!C7 -> Construction | G4: Contract Sign | H4: ='General Information'!C13 -> 46112 | I4: Contract Sign (Hijri) | J4: ='General Information'!C17 -> 10/12/1447 | K4: Committed Completion | L4: ='General Information'!C21 -> 46605 | M4: Revised Contract Value | O4: ='Invoice Log'!F4 -> 0 | P4: EAC | Q4: Revised O&M Value | S4: ='Invoice Log'!J4 -> 0 | T4: =+#REF!+#REF!+S4 -> #REF! | U4: Earn Value | V4: =L44 -> 0.21442627 | W4: Phys. Earn Value | X4: =X44 -> 0.2607931 | Z4: =REPT("¢",IF(INT(+Z3*10)>5,5,INT(+Z3*10)))&REPT("£",IF(INT(+Z3*10)>5,0,5-INT(+Z3*10)))&CHAR(10)&REPT("¢",+IF(INT(+Z3*10)>5,-5+INT(+Z3*10),0))&REPT("£",IF(INT(+Z3*10)>5,10-INT(+Z3*10),5)) -> ¢¢¢¢¢ ¢¢¢££
A5: Contractor | B5: ='General Information'!C5 -> Technical Dvelopment Co. "TDC" | D5: Status | E5: ='General Information'!C8 -> Active | G5: Site Handover | H5: ='General Information'!C14 -> 46119 | I5: Site Handover (Hijri) | J5: ='General Information'!C18 -> 11/19/1447 | K5: Forecast Completion | L5: ='General Information'!C22 -> 46605 | M5: Estimate At Completion Value | O5: ='Invoice Log'!F5 -> 33090825 | P5: =+#REF!+#REF!+O5 -> #REF! | Q5: Submitted Invoices (Gross Value) | S5: ='Invoice Log'!J5 -> 3048399.3 | U5: Variance | V5: =V4-V3 -> 0.023986546 | W5: Variance | X5: =X4-X3 -> -0.11977268 | Y5: Safety Score | Z5: =HSE.!AE6 -> 0.83333333
A6: Consultant | B6: ='General Information'!C6 -> Saudi Arabia Consulting Engineering Company "EGIS" | D6: Modon PM | E6: ='General Information'!C9 -> Engr.Zyad Al Shabat | G6: Original Completion | H6: ='General Information'!C15 -> 46605 | I6: Original Completion (Hijri) | J6: ='General Information'!C19 -> 03/03/1449 | K6: Variance | L6: ='General Information'!C23 -> 0 | M6: Potential Changes | O6: ='Invoice Log'!F6 -> 0 | Q6: Total Deduction | S6: ='Invoice Log'!J6 -> -2000 | U6: SPI | V6: =N44 -> 1.1259535 | W6: SPI | X6: =Z44 -> 0.68527733 | Z6: =REPT("¢",IF(INT(+Z5*10)>5,5,INT(+Z5*10)))&REPT("£",IF(INT(+Z5*10)>5,0,5-INT(+Z5*10)))&CHAR(10)&REPT("¢",+IF(INT(+Z5*10)>5,-5+INT(+Z5*10),0))&REPT("£",IF(INT(+Z5*10)>5,10-INT(+Z5*10),5)) -> ¢¢¢¢¢ ¢¢¢££
A8: Progress Overview
A9: Earned Value Progress (SAR) | O9: Physical Progress (Effort) | AA9: Earned Value Progress (%)
A10: WBS | C10: BOQ Value (SAR) | D10: % Wt. | E10: Weekly (SAR) | G10: To Date (SAR) | O10: Budgeted | P10: % Wt. | Q10: Weekly Physical Progress | U10: To Date Physical Progress
E11: Planned | F11: Earned | G11: Original Plan | H11: Cum. Planned | I11: Cum.Earned | J11: Original Plan % | K11: Cum. Planned % | L11: Cum.Earned % | M11: Variance | N11: SPI | O11: (Manhours) | Q11: Planned | R11: Earned | S11: Plan % | T11: Earned % | U11: Planned | V11: Earned | W11: Plan % | X11: Earned % | Y11: Variance | Z11: SPI
C12: =Progress!C7 -> 0 | D12: =Progress!D7 -> 0 | E12: =Progress!E39 -> 0 | F12: =Progress!F39 -> 0 | G12: =Progress!G39 -> 0 | H12: =Progress!H39 -> 22585.02 | I12: =Progress!I39 -> 0 | J12: =IFERROR(IF(ISBLANK(G12),"",G12/C12),0) -> 0 | K12: =IFERROR(IF(ISBLANK(H12),"",H12/C12),0) -> 0 | L12: =IFERROR(IF(ISBLANK(I12),"",I12/C12),0) -> 0 | M12: =IFERROR(L12-K12,"") -> 0 | N12: =IFERROR(L12/K12,"") | O12: =Progress!K7 -> 0 | P12: =IF(ISBLANK(O12),"",O12/$O$44) -> 0 | Q12: =Progress!M7 -> 0 | R12: =Progress!N7 -> 0 | S12: =IFERROR(IF(ISBLANK(Q12),"",Q12/O12),0) -> 0 | T12: =IFERROR(IF(ISBLANK(R12),"",R12/O12),0) -> 0 | U12: =Progress!O7 -> 0 | V12: =Progress!P7 -> 0 | W12: =IFERROR(IF(ISBLANK(U12),"",U12/O12),0) -> 0 | X12: =IFERROR(IF(ISBLANK(V12),"",V12/O12),0) -> 0 | Y12: =IFERROR(X12-W12,"") -> 0 | Z12: =IFERROR(X12/W12,"")
A13: =Progress!A7 -> Milestones | C13: =Progress!C8 -> 0 | D13: =Progress!D8 -> 0 | E13: =Progress!E40 -> 0 | F13: =Progress!F8 -> 0 | G13: =Progress!G8 -> 0 | H13: =Progress!H8 -> 0 | I13: =Progress!I8 -> 0 | J13: =IFERROR(IF(ISBLANK(G13),"",G13/C13),0) -> 0 | K13: =IFERROR(IF(ISBLANK(H13),"",H13/C13),0) -> 0 | L13: =IFERROR(IF(ISBLANK(I13),"",I13/C13),0) -> 0 | M13: =IFERROR(L13-K13,"") -> 0 | N13: =IFERROR(L13/K13,"") | O13: =Progress!K7 -> 0 | P13: =IF(ISBLANK(O13),"",O13/$O$44) -> 0 | Q13: =Progress!M8 -> 0 | R13: =Progress!N8 -> 0 | S13: =IFERROR(IF(ISBLANK(Q13),"",Q13/O13),0) -> 0 | T13: =IFERROR(IF(ISBLANK(R13),"",R13/O13),0) -> 0 | U13: =Progress!O8 -> 19793 | V13: =Progress!P8 -> 19793 | W13: =IFERROR(IF(ISBLANK(U13),"",U13/O13),0) -> 0 | X13: =IFERROR(IF(ISBLANK(V13),"",V13/O13),0) -> 0 | Y13: =IFERROR(X13-W13,"") -> 0 | Z13: =IFERROR(X13/W13,"")
A14: =Progress!A8 -> Mobilization | C14: =Progress!C8 -> 0 | D14: =Progress!D8 -> 0 | E14: =Progress!E9 -> 0 | F14: =Progress!F8 -> 0 | G14: =Progress!G9 -> 0 | H14: =Progress!H8 -> 0 | I14: =Progress!I8 -> 0 | J14: =IFERROR(IF(ISBLANK(G14),"",G14/C14),0) -> 0 | K14: =IFERROR(IF(ISBLANK(H14),"",H14/C14),0) -> 0 | L14: =IFERROR(IF(ISBLANK(I14),"",I14/C14),0) -> 0 | M14: =Progress!M8 -> 0 | N14: =IFERROR(L14/K14,"") | O14: =Progress!K8 -> 19154 | P14: =Progress!L8 -> 0.029999947 | Q14: =Progress!Q8 -> 0 | R14: =Progress!R8 -> 0 | S14: =Progress!S8 -> 0 | T14: =Progress!T8 -> 0 | U14: =Progress!U8 -> 0 | V14: =Progress!V8 -> 0 | W14: =Progress!W8 -> 0 | X14: =Progress!X8 -> 0 | Y14: =Progress!Y8 -> 0 | Z14: =IFERROR(X14/W14,"")
A15: =Progress!A9 -> Engineering | C15: =Progress!C9 -> 0 | D15: =Progress!D9 -> 0 | E15: =Progress!E9 -> 0 | F15: =Progress!F9 -> 0 | G15: =Progress!G9 -> 0 | H15: =Progress!H9 -> 0 | I15: =Progress!I9 -> 0 | J15: =IFERROR(IF(ISBLANK(G15),"",G15/C15),0) -> 0 | K15: =IFERROR(IF(ISBLANK(H15),"",H15/C15),0) -> 0 | L15: =IFERROR(IF(ISBLANK(I15),"",I15/C15),0) -> 0 | M15: =IFERROR(L15-K15,"") -> 0 | N15: =IFERROR(L15/K15,"") | O15: =Progress!K9 -> 31923.4 | P15: =IF(ISBLANK(O15),"",O15/$O$44) -> 0.050000016 | Q15: =Progress!M9 -> 0 | R15: =Progress!N9 -> 0 | S15: =IFERROR(IF(ISBLANK(Q15),"",Q15/O15),0) -> 0 | T15: =IFERROR(IF(ISBLANK(R15),"",R15/O15),0) -> 0 | U15: =Progress!O9 -> 32988 | V15: =Progress!P9 -> 31339 | W15: =IFERROR(IF(ISBLANK(U15),"",U15/O15),0) -> 1.0333486 | X15: =IFERROR(IF(ISBLANK(V15),"",V15/O15),0) -> 0.98169368 | Y15: =IFERROR(X15-W15,"") -> -0.051654899 | Z15: =IFERROR(X15/W15,"") -> 0.95001213
A16: =Progress!A10 -> Procurement | C16: =Progress!C10 -> 0 | D16: =Progress!D10 -> 0 | E16: =Progress!E10 -> 0 | F16: =Progress!F10 -> 0 | G16: =Progress!G10 -> 0 | H16: =Progress!H10 -> 0 | I16: =Progress!I10 -> 0 | J16: =IFERROR(IF(ISBLANK(G16),"",G16/C16),0) -> 0 | K16: =IFERROR(IF(ISBLANK(H16),"",H16/C16),0) -> 0 | L16: =IFERROR(IF(ISBLANK(I16),"",I16/C16),0) -> 0 | M16: =IFERROR(L16-K16,"") -> 0 | N16: =IFERROR(L16/K16,"") | O16: =Progress!K10 -> 89385.5 | P16: =IF(ISBLANK(O16),"",O16/$O$44) -> 0.14000001 | Q16: =Progress!M10 -> 3134 | R16: =Progress!N10 -> 4642 | S16: =IFERROR(IF(ISBLANK(Q16),"",Q16/O16),0) -> 0.035061615 | T16: =IFERROR(IF(ISBLANK(R16),"",R16/O16),0) -> 0.05193236 | U16: =Progress!O10 -> 68347 | V16: =Progress!P10 -> 17130 | W16: =IFERROR(IF(ISBLANK(U16),"",U16/O16),0) -> 0.76463185 | X16: =IFERROR(IF(ISBLANK(V16),"",V16/O16),0) -> 0.19164182 | Y16: =IFERROR(X16-W16,"") -> -0.57299003 | Z16: =IFERROR(X16/W16,"") -> 0.2506328
A17: =Progress!A11 -> Construction | C17: =Progress!C11 -> 33090852 | D17: =Progress!D11 -> 1 | E17: =Progress!E11 -> 710697.41 | F17: =Progress!F11 -> 214091.03 | G17: =Progress!G11 -> 0 | H17: =Progress!H11 -> 6301807.5 | I17: =Progress!I11 -> 7095542 | J17: =IFERROR(IF(ISBLANK(G17),"",G17/C17),0) -> 0 | K17: =IFERROR(IF(ISBLANK(H17),"",H17/C17),0) -> 0.19043956 | L17: =IFERROR(IF(ISBLANK(I17),"",I17/C17),0) -> 0.21442609 | M17: =IFERROR(L17-K17,"") -> 0.023986526 | N17: =IFERROR(L17/K17,"") -> 1.1259535 | O17: =Progress!K11 -> 478850.8 | P17: =IF(ISBLANK(O17),"",O17/$O$44) -> 0.74999992 | Q17: =Progress!M11 -> 8552 | R17: =Progress!N11 -> 3430 | S17: =IFERROR(IF(ISBLANK(Q17),"",Q17/O17),0) -> 0.017859425 | T17: =IFERROR(IF(ISBLANK(R17),"",R17/O17),0) -> 0.0071629827 | U17: =Progress!O11 -> 121851 | V17: =Progress!P11 -> 98246 | W17: =IFERROR(IF(ISBLANK(U17),"",U17/O17),0) -> 0.25446548 | X17: =IFERROR(IF(ISBLANK(V17),"",V17/O17),0) -> 0.20517038 | Y17: =IFERROR(X17-W17,"") -> -0.049295104 | Z17: =IFERROR(X17/W17,"") -> 0.8062798
A18: =Progress!A12 -> Package-1 | C18: =Progress!C12 -> 22502032 | D18: =Progress!D12 -> 0.68000763 | E18: =Progress!E12 -> 613731.64 | F18: =Progress!F12 -> 214091.03 | G18: =Progress!G12 -> 0 | H18: =Progress!H12 -> 5886632.1 | I18: =Progress!I12 -> 7095542 | J18: =IFERROR(IF(ISBLANK(G18),"",G18/C18),0) -> 0 | K18: =IFERROR(IF(ISBLANK(H18),"",H18/C18),0) -> 0.26160447 | L18: =IFERROR(IF(ISBLANK(I18),"",I18/C18),0) -> 0.31532895 | M18: =IFERROR(L18-K18,"") -> 0.053724478 | N18: =IFERROR(L18/K18,"") -> 1.2053653 | O18: =Progress!K12 -> 345775.5 | P18: =IF(ISBLANK(O18),"",O18/$O$44) -> 0.54157077 | Q18: =Progress!M12 -> 8143 | R18: =Progress!N12 -> 3430 | S18: =IFERROR(IF(ISBLANK(Q18),"",Q18/O18),0) -> 0.023549962 | T18: =IFERROR(IF(ISBLANK(R18),"",R18/O18),0) -> 0.0099197312 | U18: =Progress!O12 -> 109662 | V18: =Progress!P12 -> 98246 | W18: =IFERROR(IF(ISBLANK(U18),"",U18/O18),0) -> 0.31714798 | X18: =IFERROR(IF(ISBLANK(V18),"",V18/O18),0) -> 0.28413233 | Y18: =IFERROR(X18-W18,"") -> -0.033015642 | Z18: =IFERROR(X18/W18,"") -> 0.89589831
A19: =Progress!A13 -> ROAD WORKS 1 | C19: =Progress!C13 -> 17704263 | D19: =Progress!D13 -> 0.53501986 | E19: =Progress!E13 -> 514154.16 | F19: =Progress!F13 -> 111822.59 | G19: =Progress!G13 -> 0 | H19: =Progress!H13 -> 5366361.2 | I19: =Progress!I13 -> 6500573.5 | J19: =IFERROR(IF(ISBLANK(G19),"",G19/C19),0) -> 0 | K19: =IFERROR(IF(ISBLANK(H19),"",H19/C19),0) -> 0.30311124 | L19: =IFERROR(IF(ISBLANK(I19),"",I19/C19),0) -> 0.36717561 | M19: =IFERROR(L19-K19,"") -> 0.064064363 | N19: =IFERROR(L19/K19,"") -> 1.2113559 | O19: =Progress!K13 -> 168659.6 | P19: =IF(ISBLANK(O19),"",O19/$O$44) -> 0.26416305 | Q19: =Progress!M13 -> 15867 | R19: =Progress!N13 -> 557 | S19: =IFERROR(IF(ISBLANK(Q19),"",Q19/O19),0) -> 0.094077064 | T19: =IFERROR(IF(ISBLANK(R19),"",R19/O19),0) -> 0.0033025099 | U19: =Progress!O13 -> 73549 | V19: =Progress!P13 -> 78905 | W19: =IFERROR(IF(ISBLANK(U19),"",U19/O19),0) -> 0.43607954 | X19: =IFERROR(IF(ISBLANK(V19),"",V19/O19),0) -> 0.46783581 | Y19: =IFERROR(X19-W19,"") -> 0.031756271 | Z19: =IFERROR(X19/W19,"") -> 1.0728222
A20: =Progress!A14 -> ROAD - 01 | C20: =Progress!C14 -> 10400905 | D20: =Progress!D14 -> 0.31431361 | E20: =Progress!E14 -> 275854.68 | F20: =Progress!F14 -> 111822.59 | G20: =Progress!G14 -> 0 | H20: =Progress!H14 -> 3150987.4 | I20: =Progress!I14 -> 4140066.2 | J20: =IFERROR(IF(ISBLANK(G20),"",G20/C20),0) -> 0 | K20: =IFERROR(IF(ISBLANK(I20),"",I20/C20),0) -> 0.39804865 | L20: =IFERROR(IF(ISBLANK(I20),"",I20/C20),0) -> 0.39804865 | M20: =IFERROR(L20-K20,"") -> 0 | N20: =IFERROR(L20/K20,"") -> 1 | O20: =Progress!K14 -> 96629.6 | P20: =IF(ISBLANK(O20),"",O20/$O$44) -> 0.15134608 | Q20: =Progress!M14 -> 1058 | R20: =Progress!N14 -> 557 | S20: =IFERROR(IF(ISBLANK(Q20),"",Q20/O20),0) -> 0.010949026 | T20: =IFERROR(IF(ISBLANK(R20),"",R20/O20),0) -> 0.0057642793 | U20: =Progress!O14 -> 58740 | V20: =Progress!P14 -> 62660 | W20: =IFERROR(IF(ISBLANK(U20),"",U20/O20),0) -> 0.60788827 | X20: =IFERROR(IF(ISBLANK(V20),"",V20/O20),0) -> 0.64845555 | Y20: =IFERROR(X20-W20,"") -> 0.04056728 | Z20: =IFERROR(X20/W20,"") -> 1.0667348
A21: =Progress!A15 -> ROAD - 02 | C21: =Progress!C15 -> 7303358 | D21: =Progress!D15 -> 0.22070625 | E21: =Progress!E15 -> 238299.48 | F21: =Progress!F15 -> 0 | H21: =Progress!H15 -> 2215373.7 | I21: =Progress!I15 -> 2360507.3 | O21: =Progress!K15 -> 72030.1 | P21: =IF(ISBLANK(O21),"",O21/$O$44) -> 0.11281712 | Q21: =Progress!M15 -> 1164 | R21: =Progress!N15 -> 0 | S21: =IFERROR(IF(ISBLANK(Q21),"",Q21/O21),0) -> 0.016159911 | T21: =IFERROR(IF(ISBLANK(R21),"",R21/O21),0) -> 0 | U21: =Progress!O15 -> 14810 | V21: =Progress!P15 -> 16245 | W21: =IFERROR(IF(ISBLANK(U21),"",U21/O21),0) -> 0.20560849 | X21: =IFERROR(IF(ISBLANK(V21),"",V21/O21),0) -> 0.22553072 | Y21: =IFERROR(X21-W21,"") -> 0.019922227 | Z21: =IFERROR(X21/W21,"") -> 1.096894
A22: =Progress!A16 -> ELECTRICAL WORKS | C22: =Progress!C16 -> 3415753 | D22: =Progress!D16 -> 0.10322348 | E22: =Progress!E16 -> 62394.6 | F22: =Progress!F16 -> 43659.79 | H22: =Progress!H16 -> 246971.83 | I22: =Progress!I16 -> 62629.37 | O22: =Progress!K16 -> 103222.1 | P22: =IF(ISBLANK(O22),"",O22/$O$44) -> 0.16167158 | Q22: =Progress!M16 -> 0 | R22: =Progress!N16 -> 0 | S22: =IFERROR(IF(ISBLANK(Q22),"",Q22/O22),0) -> 0 | T22: =IFERROR(IF(ISBLANK(R22),"",R22/O22),0) -> 0 | U22: =Progress!O16 -> 18369 | V22: =Progress!P16 -> 3751 | W22: =IFERROR(IF(ISBLANK(U22),"",U22/O22),0) -> 0.17795608 | X22: =IFERROR(IF(ISBLANK(V22),"",V22/O22),0) -> 0.036339117 | Y22: =IFERROR(X22-W22,"") -> -0.14161696 | Z22: =IFERROR(X22/W22,"") -> 0.20420273
A23: =Progress!A17 -> MV Network | C23: =Progress!C17 -> 1577890 | D23: =Progress!D17 -> 0.047683571 | E23: =Progress!E17 -> 17205.13 | F23: =Progress!F17 -> 0 | H23: =Progress!H17 -> 35478.52 | I23: =Progress!I17 -> 0 | O23: =Progress!K17 -> 37659 | P23: =IF(ISBLANK(O23),"",O23/$O$44) -> 0.058983397 | Q23: =Progress!M17 -> 1036 | R23: =Progress!N17 -> 0 | S23: =IFERROR(IF(ISBLANK(Q23),"",Q23/O23),0) -> 0.027510024 | T23: =IFERROR(IF(ISBLANK(R23),"",R23/O23),0) -> 0 | U23: =Progress!O17 -> 1036 | V23: =Progress!P17 -> 0 | W23: =IFERROR(IF(ISBLANK(U23),"",U23/O23),0) -> 0.027510024 | X23: =IFERROR(IF(ISBLANK(V23),"",V23/O23),0) -> 0 | Y23: =IFERROR(X23-W23,"") -> -0.027510024 | Z23: =IFERROR(X23/W23,"") -> 0
A24: =Progress!A18 -> Earthing System | C24: =Progress!C18 -> 4795 | D24: =Progress!D18 -> 0.0001449041 | E24: =Progress!E57 -> 0 | F24: =Progress!F18 -> 0 | H24: =Progress!H18 -> 0 | I24: =Progress!I18 -> 0 | O24: =Progress!K18 -> 172.8 | P24: =IF(ISBLANK(O24),"",O24/$O$44) -> 0.00027064795 | Q24: =Progress!M18 -> 0 | R24: =Progress!N18 -> 0 | S24: =IFERROR(IF(ISBLANK(Q24),"",Q24/O24),0) -> 0 | T24: =IFERROR(IF(ISBLANK(R24),"",R24/O24),0) -> 0 | U24: =Progress!O18 -> 0 | V24: =Progress!P18 -> 0 | W24: =IFERROR(IF(ISBLANK(U24),"",U24/O24),0) -> 0 | X24: =IFERROR(IF(ISBLANK(V24),"",V24/O24),0) -> 0 | Y24: =IFERROR(X24-W24,"") -> 0 | Z24: =IFERROR(X24/W24,"")
A25: =Progress!A19 -> Street Lighting Network | C25: =Progress!C19 -> 1454545 | D25: =Progress!D19 -> 0.043956106 | F25: =Progress!F19 -> 0 | H25: =Progress!H19 -> 146450.34 | I25: =Progress!I19 -> 6382.5 | O25: =Progress!K19 -> 51050.8 | P25: =IF(ISBLANK(O25),"",O25/$O$44) -> 0.0799583 | Q25: =Progress!M19 -> 9986 | R25: =Progress!N19 -> 0 | S25: =IFERROR(IF(ISBLANK(Q25),"",Q25/O25),0) -> 0.19560908 | T25: =IFERROR(IF(ISBLANK(R25),"",R25/O25),0) -> 0 | U25: =Progress!O19 -> 13326 | V25: =Progress!P19 -> 515 | W25: =IFERROR(IF(ISBLANK(U25),"",U25/O25),0) -> 0.26103411 | X25: =IFERROR(IF(ISBLANK(V25),"",V25/O25),0) -> 0.010087991 | Y25: =IFERROR(X25-W25,"") -> -0.25094612 | Z25: =IFERROR(X25/W25,"") -> 0.038646255
A26: =Progress!A20 -> TELECOMMUNICATIONS WORKS | C26: =Progress!C20 -> 378522 | D26: =Progress!D20 -> 0.011438871 | F26: =Progress!F20 -> 43659.79 | H26: =Progress!H20 -> 65042.96 | I26: =Progress!I20 -> 56246.87 | O26: =Progress!K20 -> 14339.6 | P26: =IF(ISBLANK(O26),"",O26/$O$44) -> 0.022459394 | Q26: =Progress!M20 -> 4008 | R26: =Progress!N20 -> 2429 | S26: =IFERROR(IF(ISBLANK(Q26),"",Q26/O26),0) -> 0.2795057 | T26: =IFERROR(IF(ISBLANK(R26),"",R26/O26),0) -> 0.16939106 | U26: =Progress!O20 -> 4008 | V26: =Progress!P20 -> 3237 | W26: =IFERROR(IF(ISBLANK(U26),"",U26/O26),0) -> 0.2795057 | X26: =IFERROR(IF(ISBLANK(V26),"",V26/O26),0) -> 0.22573851 | Y26: =IFERROR(X26-W26,"") -> -0.05376719 | Z26: =IFERROR(X26/W26,"") -> 0.80763473
A27: =Progress!A21 -> LOW VOLTAGE | C27: =Progress!C21 -> 86942 | D27: =Progress!D21 -> 0.0026273727 | F27: =Progress!F21 -> 0 | I27: =Progress!I21 -> 4926.72 | O27: =Progress!K21 -> 6638.4 | P27: =IF(ISBLANK(O27),"",O27/$O$44) -> 0.010397392 | Q27: =Progress!M21 -> 0 | R27: =Progress!N21 -> 329 | S27: =IFERROR(IF(ISBLANK(Q27),"",Q27/O27),0) -> 0 | T27: =IFERROR(IF(ISBLANK(R27),"",R27/O27),0) -> 0.049560135 | U27: =Progress!O21 -> 0 | V27: =Progress!P21 -> 651 | W27: =IFERROR(IF(ISBLANK(U27),"",U27/O27),0) -> 0 | X27: =IFERROR(IF(ISBLANK(V27),"",V27/O27),0) -> 0.098065799 | Y27: =IFERROR(X27-W27,"") -> 0.098065799 | Z27: =IFERROR(X27/W27,"")
A28: =Progress!A22 -> ROAD - 01 | C28: =Progress!C22 -> 28981 | D28: =Progress!D22 -> 0.00087580096 | E28: =Progress!E43 -> 0 | F28: =Progress!F22 -> 0 | G28: =Progress!G35 -> 0 | H28: =Progress!H35 -> 371500.3 | I28: =Progress!I22 -> 2028.65 | J28: =IFERROR(IF(ISBLANK(G28),"",G28/C28),0) -> 0 | K28: =IFERROR(IF(ISBLANK(I28),"",I28/C28),0) -> 0.06999931 | L28: =IFERROR(IF(ISBLANK(I28),"",I28/C28),0) -> 0.06999931 | M28: =IFERROR(L28-K28,"") -> 0 | N28: =IFERROR(L28/K28,"") -> 1 | O28: =Progress!K22 -> 2072.2 | P28: =IF(ISBLANK(O28),"",O28/$O$44) -> 0.0032455826 | Q28: =Progress!M22 -> 0 | R28: =Progress!N43 -> 0 | S28: =IFERROR(IF(ISBLANK(Q28),"",Q28/O28),0) -> 0 | T28: =IFERROR(IF(ISBLANK(R28),"",R28/O28),0) -> 0 | U28: =Progress!O35 -> 2336 | V28: =Progress!P22 -> 322 | W28: =IFERROR(IF(ISBLANK(U28),"",U28/O28),0) -> 1.1273043 | X28: =IFERROR(IF(ISBLANK(V28),"",V28/O28),0) -> 0.15539041 | Y28: =IFERROR(X28-W28,"") -> -0.97191391 | Z28: =IFERROR(X28/W28,"") -> 0.13784247
A29: =Progress!A23 -> ROAD - 02 | C29: =Progress!C23 -> 57961 | D29: =Progress!D23 -> 0.0017515717 | F29: =Progress!F23 -> 869.42 | O29: =Progress!K23 -> 4566.2 | P29: =IF(ISBLANK(O29),"",O29/$O$44) -> 0.0071518094 | V29: =Progress!P23 -> 328
A30: =Progress!A24 -> PORTABLE WATER | C30: =Progress!C24 -> 379700 | D30: =Progress!D24 -> 0.01147447 | F30: =Progress!F24 -> 210420.04 | O30: =Progress!K24 -> 46755 | P30: =IF(ISBLANK(O30),"",O30/$O$44) -> 0.073230005
A31: =Progress!A25 -> ROAD - 01 | C31: =Progress!C25 -> 189850 | D31: =Progress!D25 -> 0.0057372352 | F31: =Progress!F25 -> -87612.8 | O31: =Progress!K25 -> 20132.1 | P31: =IF(ISBLANK(O31),"",O31/$O$44) -> 0.031531896
A32: =Progress!A26 -> ROAD - 02 | C32: =Progress!C26 -> 189850 | D32: =Progress!D26 -> 0.0057372352 | F32: =Progress!F26 -> 3809.25 | O32: =Progress!K26 -> 26622.9 | P32: =IF(ISBLANK(O32),"",O32/$O$44) -> 0.041698109
A33: =Progress!A27 -> SEWARAGE NETWORK | C33: =Progress!C27 -> 621335 | D33: =Progress!D27 -> 0.01877664 | F33: =Progress!F27 -> 20653.36 | O33: =Progress!K27 -> 19751.7 | P33: =IF(ISBLANK(O33),"",O33/$O$44) -> 0.030936094
A34: =Progress!A28 -> ROAD - 01 | C34: =Progress!C28 -> 372801 | D34: =Progress!D28 -> 0.011265984 | O34: =Progress!K28 -> 12694.5 | P34: =IF(ISBLANK(O34),"",O34/$O$44) -> 0.019882757
A35: =Progress!A29 -> ROAD - 02 | C35: =Progress!C29 -> 248534 | D35: =Progress!D29 -> 0.0075106558 | O35: =Progress!K29 -> 7057.2 | P35: =IF(ISBLANK(O35),"",O35/$O$44) -> 0.011053337
A36: =Progress!A30 -> STORM WATER | C36: =Progress!C30 -> 294040 | D36: =Progress!D30 -> 0.0088858395 | O36: =Progress!K30 -> 748.6 | P36: =IF(ISBLANK(O36),"",O36/$O$44) -> 0.0011724945
A37: =Progress!A31 -> ROAD N... | C37: =Progress!C31 -> 294040 | D37: =Progress!D31 -> 0.0088858395 | O37: =Progress!K31 -> 748.6 | P37: =IF(ISBLANK(O37),"",O37/$O$44) -> 0.0011724945
A38: =Progress!A32 -> Package-3 | C38: =Progress!C32 -> 10588820 | D38: =Progress!D32 -> 0.31999237 | O38: =Progress!K32 -> 133075.3 | P38: =IF(ISBLANK(O38),"",O38/$O$44) -> 0.20842915
A39: =Progress!A33 -> Site Works | C39: =Progress!C33 -> 21090 | D39: =Progress!D33 -> 0.00063733626 | O39: =Progress!K33 -> 1835.5 | P39: =IF(ISBLANK(O39),"",O39/$O$44) -> 0.0028748513
A40: =Progress!A34 -> Earthworks | C40: =Progress!C34 -> 21090 | D40: =Progress!D34 -> 0.00063733626 | O40: =Progress!K34 -> 1835.5 | P40: =IF(ISBLANK(O40),"",O40/$O$44) -> 0.0028748513
A41: =Progress!A35 -> Platform Works | C41: =Progress!C35 -> 6003782 | D41: =Progress!D35 -> 0.18143329 | O41: =Progress!K35 -> 68964.6 | P41: =IF(ISBLANK(O41),"",O41/$O$44) -> 0.10801578
A42: =Progress!A36 -> Platform Substructure | C42: =Progress!C36 -> 5037344 | D42: =Progress!D36 -> 0.15222769 | E42: =Progress!E44 -> 0 | F42: =Progress!F44 -> 0 | G42: =Progress!G36 -> 0 | H42: =Progress!H36 -> 371500.3 | I42: =Progress!I36 -> 0 | J42: =IFERROR(IF(ISBLANK(G42),"",G42/C42),0) -> 0 | K42: =IFERROR(IF(ISBLANK(I42),"",I42/C42),0) -> 0 | L42: =IFERROR(IF(ISBLANK(I42),"",I42/C42),0) -> 0 | M42: =IFERROR(L42-K42,"") -> 0 | N42: =IFERROR(L42/K42,"") | O42: =Progress!K36 -> 47410.5 | P42: =IF(ISBLANK(O42),"",O42/$O$44) -> 0.074256681 | Q42: =Progress!M44 -> 0 | R42: =Progress!N44 -> 0 | S42: =IFERROR(IF(ISBLANK(Q42),"",Q42/O42),0) -> 0 | T42: =IFERROR(IF(ISBLANK(R42),"",R42/O42),0) -> 0 | U42: =Progress!O36 -> 2336 | V42: =Progress!P36 -> 0 | W42: =IFERROR(IF(ISBLANK(U42),"",U42/O42),0) -> 0.049271786 | X42: =IFERROR(IF(ISBLANK(V42),"",V42/O42),0) -> 0 | Y42: =IFERROR(X42-W42,"") -> -0.049271786 | Z42: =IFERROR(X42/W42,"") -> 0
A43: =Progress!A37 -> Finishes & Architectural Works | C43: =Progress!C37 -> 966437 | D43: =Progress!D37 -> 0.029205564 | E43: =Progress!E45 -> 0 | F43: =Progress!F45 -> 0 | G43: =Progress!G37 -> 0 | H43: =Progress!H37 -> 0 | I43: =Progress!I37 -> 0 | J43: =IFERROR(IF(ISBLANK(G43),"",G43/C43),0) -> 0 | K43: =IFERROR(IF(ISBLANK(I43),"",I43/C43),0) -> 0 | L43: =IFERROR(IF(ISBLANK(I43),"",I43/C43),0) -> 0 | M43: =IFERROR(L43-K43,"") -> 0 | N43: =IFERROR(L43/K43,"") | O43: =Progress!K37 -> 21151.7 | P43: =IF(ISBLANK(O43),"",O43/$O$44) -> 0.033128844 | Q43: =Progress!M45 -> 0 | R43: =Progress!N45 -> 0 | S43: =IFERROR(IF(ISBLANK(Q43),"",Q43/O43),0) -> 0 | T43: =IFERROR(IF(ISBLANK(R43),"",R43/O43),0) -> 0 | U43: =Progress!O37 -> 0 | V43: =Progress!P37 -> 0 | W43: =IFERROR(IF(ISBLANK(U43),"",U43/O43),0) -> 0 | X43: =IFERROR(IF(ISBLANK(V43),"",V43/O43),0) -> 0 | Y43: =IFERROR(X43-W43,"") -> 0 | Z43: =IFERROR(X43/W43,"")
B44: Total | C44: =Progress!C52 -> 33090825 | D44: =Progress!D52 -> 1 | E44: =Progress!E52 -> 795259.98 | F44: =Progress!F52 -> 214091.03 | G44: =Progress!G52 -> 0 | H44: =Progress!H52 -> 6301807.5 | I44: =Progress!I52 -> 7095542 | J44: =IFERROR(IF(ISBLANK(G44),"",G44/C44),0) -> 0 | K44: =IFERROR(IF(ISBLANK(H44),"",H44/C44),0) -> 0.19043972 | L44: =IFERROR(IF(ISBLANK(I44),"",I44/C44),0) -> 0.21442627 | M44: =+L44-K44 -> 0.023986546 | N44: =L44/K44 -> 1.1259535 | O44: =Progress!K52 -> 638467.8 | P44: =Progress!L52 -> 1 | Q44: =Progress!M52 -> 11686 | R44: =Progress!N52 -> 8072 | S44: =IFERROR(IF(ISBLANK(Q44),"",Q44/O44),0) -> 0.018303194 | T44: =IFERROR(IF(ISBLANK(R44),"",R44/O44),0) -> 0.012642768 | U44: =Progress!O52 -> 242979 | V44: =Progress!P52 -> 166508 | W44: =IFERROR(IF(ISBLANK(U44),"",U44/O44),0) -> 0.38056579 | X44: =IFERROR(IF(ISBLANK(V44),"",V44/O44),0) -> 0.2607931 | Y44: =+X44-W44 -> -0.11977268 | Z44: =X44/W44 -> 0.68527733
AA45: Construction Milestones
AA46: Item No. | AB46: Milestones | AD46: Original (Baseline) | AE46: Latest Plan | AF46: Forecast | AG46: Status | AH46: Days Change
AA47: =+Milestones!A4 -> 1 | AB47: =+Milestones!B4 -> Project Start Milstone | AD47: =+Milestones!D4 -> 46119 | AE47: =+Milestones!E4 -> 46119 | AF47: =+Milestones!E4 -> 46119 | AG47: =Milestones!F4 -> Finish | AH47: =+Milestones!G4 -> 0
Z48: =+Milestones!#REF! -> #REF! | AA48: =+Milestones!A5 -> 2 | AB48: =+Milestones!B5 -> Mobilization Finish Milestone | AD48: =+Milestones!D5 -> 46148 | AE48: =+Milestones!E5 -> 46148 | AF48: =+Milestones!E5 -> 46148 | AG48: =Milestones!F5 -> Finish | AH48: =+Milestones!G5 -> 0
Z49: =+Milestones!#REF! -> #REF! | AA49: =+Milestones!A6 -> 3 | AB49: =+Milestones!B6 -> Work Plan and Timeline Milestone | AD49: =+Milestones!D6 -> 46148 | AE49: =+Milestones!E6 -> 46250 | AF49: =+Milestones!E6 -> 46250 | AG49: =+Milestones!F6 -> UP | AH49: =+Milestones!G6 -> -102
Z50: =+Milestones!#REF! -> #REF! | AA50: =+Milestones!A7 -> 4 | AB50: =+Milestones!B7 -> Completion of MV Work | AD50: =+Milestones!D7 -> 46529 | AE50: =+Milestones!E7 -> 46512 | AF50: =+Milestones!E7 -> 46512 | AG50: =+Milestones!F7 -> UP | AH50: =+Milestones!G7 -> 17
Z51: =+Milestones!#REF! -> #REF! | AA51: =+Milestones!A8 -> 5 | AB51: =+Milestones!B8 -> Completion of road and paving works Milestone | AD51: =+Milestones!D8 -> 46362 | AE51: =+Milestones!E8 -> 46387 | AF51: =+Milestones!E8 -> 46387 | AG51: =+Milestones!F8 -> UP | AH51: =+Milestones!G8 -> -25
Z52: =+Milestones!#REF! -> #REF! | AA52: =+Milestones!A9 -> 6 | AB52: =+Milestones!B9 -> Completion of site and platform work Milestone | AD52: =+Milestones!D9 -> 46588 | AE52: =+Milestones!E9 -> 46604 | AF52: =+Milestones!E9 -> 46604 | AG52: =+Milestones!F9 -> UP | AH52: =+Milestones!G9 -> -16
G53: 20000000 | Z53: =+Milestones!#REF! -> #REF! | AA53: =+Milestones!A10 -> 7 | AB53: =+Milestones!B10 -> Completion of finishing works and general site works | AD53: =+Milestones!D10 -> 46588 | AE53: =+Milestones!E10 -> 46605 | AF53: =+Milestones!E10 -> 46605 | AG53: =+Milestones!F10 -> UP | AH53: =+Milestones!G10 -> -17
Z54: =+Milestones!#REF! -> #REF! | AA54: =+Milestones!A11 -> 8 | AB54: =+Milestones!B11 -> Engineering Phase Finish Milestone | AD54: =+Milestones!D11 -> 46148 | AE54: =+Milestones!E11 -> 46286 | AF54: =+Milestones!E11 -> 46286 | AG54: =+Milestones!F11 -> UP | AH54: =+Milestones!G11 -> -138
Z55: =+Milestones!#REF! -> #REF! | AA55: =+Milestones!A12 -> 9 | AB55: =+Milestones!B12 -> Procurment Phase Finish Milestone | AD55: =+Milestones!D12 -> 46492 | AE55: =+Milestones!E12 -> 46547 | AF55: =+Milestones!E12 -> 46547 | AG55: =+Milestones!F12 -> UP | AH55: =+Milestones!G12 -> -55
A71: Performance overview
A72: Submittals Status | L72: Quality | W72: Safety
A73: Shop Drawings | L73: Quality Reports | W73: Safety Statistics | AE73: Proactive Vs Reactive Actions Taken
A74: Item Per WBS | C74: Total | D74: Total Submitted Drawings | I74: Remaining | J74: Pending | K74: Total Submittals | L74: Quality Reports | N74: Issued | O74: Closed | P74: Pending | Q74: Avg. Closing (Days) | R74: Pending | W74: Category | X74: Item | Z74: This Week | AB74: This Month | AC74: Year to Date | AD74: Cumulative
D75: A | E75: B | F75: C | G75: D | H75: Processed | R75: 0-10 Days | S75: 11-20 Days | T75: 21-30 Days | U75: 31-60 Days | V75: > 60 Days
A76: Roadwork | C76: =+'Quality-Stat'!D14 -> 90 | D76: =+'Quality-Stat'!E14 -> 80 | E76: =+'Quality-Stat'!F14 -> 10 | F76: =+'Quality-Stat'!G14 -> 0 | G76: =+'Quality-Stat'!H14 -> 0 | H76: =+'Quality-Stat'!I14 -> 90 | I76: =+'Quality-Stat'!J14 -> 0 | J76: =+'Quality-Stat'!K14 -> 0 | K76: =+'Quality-Stat'!L14 -> 90 | W76: General | X76: ='HSE-Stat'!B4 -> Total Hours Worked | Z76: ='HSE-Stat'!D4 -> 4280 | AB76: ='HSE-Stat'!E4 -> 9540 | AC76: ='HSE-Stat'!F4 -> 77050 | AD76: ='HSE-Stat'!G4 -> 77050 | AG76: Proactive | AH76: =+SUM(AD87:AD91) -> 42
A77: wet network(sewer,,potable) | C77: =+'Quality-Stat'!D15 -> 47 | D77: =+'Quality-Stat'!E15 -> 13 | E77: =+'Quality-Stat'!F15 -> 34 | F77: =+'Quality-Stat'!G15 -> 0 | G77: =+'Quality-Stat'!H15 -> 0 | H77: =+'Quality-Stat'!I15 -> 47 | I77: =+'Quality-Stat'!J15 -> 0 | J77: =+'Quality-Stat'!K15 -> 0 | K77: =+'Quality-Stat'!L15 -> 47 | L77: Non Conformance (NCR) | N77: =+'Quality-Stat'!C6 -> 4 | O77: =+'Quality-Stat'!D6 -> 4 | P77: =+'Quality-Stat'!E6 -> 0 | Q77: =+'Quality-Stat'!F6 -> 0 | R77: =+'Quality-Stat'!G6 -> 0 | S77: =+'Quality-Stat'!H6 -> - | T77: =+'Quality-Stat'!I6 -> - | U77: =+'Quality-Stat'!J6 -> - | V77: =+'Quality-Stat'!K6 -> - | X77: ='HSE-Stat'!B5 -> Safe Hours Worked | Z77: ='HSE-Stat'!D5 -> 4280 | AB77: ='HSE-Stat'!E5 -> 9540 | AC77: ='HSE-Stat'!F5 -> 77050 | AD77: ='HSE-Stat'!G5 -> 77050 | AG77: Reactive | AH77: =SUM(AD78:AD86) -> 0
A78: Telecom | C78: =+'Quality-Stat'!D16 -> 15 | D78: =+'Quality-Stat'!E16 -> 8 | E78: =+'Quality-Stat'!F16 -> 7 | F78: =+'Quality-Stat'!G16 -> 0 | G78: =+'Quality-Stat'!H16 -> 0 | H78: =+'Quality-Stat'!I16 -> 15 | I78: =+'Quality-Stat'!J16 -> 0 | J78: =+'Quality-Stat'!K16 -> 0 | K78: =+'Quality-Stat'!L16 -> 15 | L78: Site Instruction (SIR) | N78: =+'Quality-Stat'!C7 -> 0 | O78: =+'Quality-Stat'!D7 -> 0 | P78: =+'Quality-Stat'!E7 -> 0 | Q78: =+'Quality-Stat'!F7 -> 0 | R78: =+'Quality-Stat'!G7 -> - | S78: =+'Quality-Stat'!H7 -> 0 | T78: =+'Quality-Stat'!I7 -> 0 | U78: =+'Quality-Stat'!J7 -> 0 | V78: =+'Quality-Stat'!K7 -> 0 | W78: Reactive | X78: 0 | Z78: 0 | AB78: 0 | AC78: ='HSE-Stat'!F6 -> 22 | AD78: 0
A79: Lighting | C79: =+'Quality-Stat'!D17 -> 28 | D79: =+'Quality-Stat'!E17 -> 8 | E79: =+'Quality-Stat'!F17 -> 20 | F79: =+'Quality-Stat'!G17 -> 0 | G79: =+'Quality-Stat'!H17 -> 0 | H79: =+'Quality-Stat'!I17 -> 28 | I79: =+'Quality-Stat'!J17 -> 0 | J79: =+'Quality-Stat'!K17 -> 0 | K79: =+'Quality-Stat'!L17 -> 28 | L79: Material Inspection (MIR) | N79: =+'Quality-Stat'!C8 -> 15 | O79: =+'Quality-Stat'!D8 -> 15 | P79: =+'Quality-Stat'!E8 -> 0 | Q79: =+'Quality-Stat'!F8 -> 0 | R79: =+'Quality-Stat'!G8 -> 0 | S79: =+'Quality-Stat'!H8 -> 0 | T79: =+'Quality-Stat'!I8 -> 0 | U79: =+'Quality-Stat'!J8 -> 0 | V79: =+'Quality-Stat'!K8 -> 0 | X79: 0 | Z79: 0 | AB79: 0 | AC79: ='HSE-Stat'!F7 -> 0 | AD79: 0
A80: Electrical | C80: =+'Quality-Stat'!D18 -> 24 | D80: =+'Quality-Stat'!E18 -> 5 | E80: =+'Quality-Stat'!F18 -> 19 | F80: =+'Quality-Stat'!G18 -> 0 | G80: =+'Quality-Stat'!H18 -> 0 | H80: =+'Quality-Stat'!I18 -> 24 | I80: =+'Quality-Stat'!J18 -> 0 | J80: =+'Quality-Stat'!K18 -> 0 | K80: =+'Quality-Stat'!L18 -> 24 | L80: Field Inspection (FIR) | N80: =+'Quality-Stat'!C9 -> 152 | O80: =+'Quality-Stat'!D9 -> 143 | P80: =+'Quality-Stat'!E9 -> 9 | Q80: =+'Quality-Stat'!F9 -> 0 | R80: =+'Quality-Stat'!G9 -> 9 | S80: =+'Quality-Stat'!H9 -> 0 | T80: =+'Quality-Stat'!I9 -> 0 | U80: =+'Quality-Stat'!J9 -> 0 | V80: =+'Quality-Stat'!K9 -> 0 | X80: 0 | Z80: 0 | AB80: 0 | AC80: ='HSE-Stat'!F8 -> 20 | AD80: 0
A81: TOTAL | C81: =+'Quality-Stat'!D19 -> 204 | D81: =+'Quality-Stat'!E19 -> 114 | E81: =+'Quality-Stat'!F19 -> 90 | F81: =+'Quality-Stat'!G19 -> 0 | G81: =+'Quality-Stat'!H19 -> 0 | H81: =+'Quality-Stat'!I19 -> 204 | I81: =+'Quality-Stat'!J19 -> 0 | J81: =+'Quality-Stat'!K19 -> 0 | K81: =+'Quality-Stat'!L19 -> 204 | L81: Key Submittals Approval Status | X81: 0 | Z81: 0 | AB81: 0 | AC81: ='HSE-Stat'!F9 -> 0 | AD81: 0
A82: Material Approval | L82: 1 Quality Plan Approval | O82: ='General Information'!C27 -> 46153 | Q82: 6 Baseline Approval | U82: ='General Information'!C39 -> 46236 | X82: 0 | Z82: 0 | AB82: 0 | AC82: ='HSE-Stat'!F10 -> 0 | AD82: 0 | AE82: Total Hours Worked Vs Safe Hours Worked
A83: Item Per WBS | C83: Total | D83: Total Submitted Material | I83: Remaining to approve | J83: Pending | K83: Total Submittals | L83: 2 Quality Plan Last Up | O83: ='General Information'!C28 -> 46153 | Q83: 7 No of Approved Version of Schedule | U83: ='General Information'!C40 -> - | X83: 0 | Z83: 0 | AB83: 0 | AC83: ='HSE-Stat'!F11 -> 0 | AD83: 0
D84: A | E84: B | F84: C | G84: D | H84: Processed | I84: with Designer | L84: 3 Safety Plan Approval | O84: ='General Information'!C31 -> 46148 | Q84: 8 Last Approved Schedule | U84: ='General Information'!C41 -> - | X84: 0 | Z84: 0 | AB84: 0 | AC84: ='HSE-Stat'!F12 -> 0 | AD84: 0
A85: Civil /Structural /Architectural | C85: =+'Quality-Stat'!D25 -> 20 | D85: =+'Quality-Stat'!E25 -> 0 | E85: =+'Quality-Stat'!F25 -> 18 | F85: =+'Quality-Stat'!G25 -> 1 | G85: =+'Quality-Stat'!H25 -> 0 | H85: =+'Quality-Stat'!I25 -> 19 | I85: =+'Quality-Stat'!J25 -> 0 | J85: =+'Quality-Stat'!K25 -> 1 | K85: =+'Quality-Stat'!L25 -> 20 | L85: 4 Safety Plan Last Up | O85: ='General Information'!C32 -> 46142 | Q85: 9 BOQ Approval Date | U85: ='General Information'!C44 -> - | X85: 0 | Z85: 0 | AB85: 0 | AC85: 0 | AD85: 0
A86: Electrical | C86: =+'Quality-Stat'!D26 -> 16 | D86: =+'Quality-Stat'!E26 -> 1 | E86: =+'Quality-Stat'!F26 -> 13 | F86: =+'Quality-Stat'!G26 -> 2 | G86: =+'Quality-Stat'!H26 -> 0 | H86: =+'Quality-Stat'!I26 -> 16 | I86: =+'Quality-Stat'!J26 -> 0 | J86: =+'Quality-Stat'!K26 -> 0 | K86: =+'Quality-Stat'!L26 -> 16 | L86: 5 Construction Plan Approval | O86: ='General Information'!C48 -> - | Q86: 10 No of Approved Version of BOQ | U86: ='General Information'!C45 -> - | X86: 0 | Z86: 0 | AB86: 0 | AC86: ='HSE-Stat'!F14 -> 0 | AD86: 0
A87: Mechanical | C87: =+'Quality-Stat'!D27 -> 7 | D87: =+'Quality-Stat'!E27 -> 0 | E87: =+'Quality-Stat'!F27 -> 7 | F87: =+'Quality-Stat'!G27 -> 0 | G87: =+'Quality-Stat'!H27 -> 0 | H87: =+'Quality-Stat'!I27 -> 7 | I87: =+'Quality-Stat'!J27 -> 0 | J87: =+'Quality-Stat'!K27 -> 0 | K87: =+'Quality-Stat'!L27 -> 7 | L87: Invoices Summary | W87: Proactive | X87: 0 | Z87: 0 | AB87: 0 | AC87: ='HSE-Stat'!F15 -> 0 | AD87: 0
L88: Total Submitted Invoices | N88: ='Invoice Log'!V3 -> 2 | O88: Submitted Invoices (SAR) | R88: ='Invoice Log'!Z3 -> 3048399.3 | T88: Contract Value (SR) | U88: =O4 -> 0 | X88: ='HSE-Stat'!B6 -> No.of Internal Training | Z88: ='HSE-Stat'!D6 -> 1 | AB88: ='HSE-Stat'!E6 -> 3 | AC88: ='HSE-Stat'!F6 -> 22 | AD88: ='HSE-Stat'!G6 -> 22
L89: PM Approved Invoices | N89: ='Invoice Log'!V5 -> 0 | O89: PM Approved Invoices (SAR) | R89: ='Invoice Log'!Z5 -> 0 | T89: Planned Value (SR) | U89: =H44 -> 6301807.5 | X89: ='HSE-Stat'!B7 -> No.of Internal Audit | Z89: ='HSE-Stat'!D7 -> 0 | AB89: ='HSE-Stat'!E7 -> 0 | AC89: ='HSE-Stat'!F7 -> 0 | AD89: ='HSE-Stat'!G7 -> 0
A90: TOTAL | C90: =+'Quality-Stat'!D28 -> 43 | D90: =SUM(D85:D89) -> 1 | E90: =SUM(E85:E89) -> 38 | F90: =SUM(F85:F89) -> 3 | G90: =SUM(G85:G89) -> 0 | H90: =SUM(H85:H89) -> 42 | I90: =SUM(I85:I89) -> 0 | J90: =SUM(J85:J89) -> 1 | K90: =SUM(K85:K89) -> 43 | L90: No of Paid Invoices | N90: ='Invoice Log'!V6 -> 0 | O90: Paid Invoices (SAR) | R90: ='Invoice Log'!Z6 -> 0 | T90: Earned Value (SR) | U90: =I44 -> 7095542 | X90: ='HSE-Stat'!B8 -> No. of Toolbox Talks | Z90: ='HSE-Stat'!D8 -> 1 | AB90: ='HSE-Stat'!E8 -> 3 | AC90: ='HSE-Stat'!F8 -> 20 | AD90: ='HSE-Stat'!G8 -> 20
A91: Procurement Summary | L91: No of Pending Invoices | N91: =+N88-N90 -> 2 | O91: Last Submitted Period | R91: ='Invoice Log'!AC3 -> 0 | T91: Submitted (SAR) | U91: =R88 -> 3048399.3 | X91: ='HSE-Stat'!B9 -> Safety Awards/Incentives | Z91: ='HSE-Stat'!D9 -> 0 | AB91: ='HSE-Stat'!E9 -> 0 | AC91: ='HSE-Stat'!F9 -> 0 | AD91: ='HSE-Stat'!G9 -> 0
A92: Item Per WBS | C92: Total Materials | D92: Total Number of P.O. | E92: Actual P.O. To Date | F92: Remaining P.O | G92: Material on Site | H92: Remaining Materials | I92: Material Delivery Completion (Date) | L92: Advance Payment % | N92: ='Invoice Log'!N3 -> 0 | O92: Advance Payment (SAR) | R92: ='Invoice Log'!R3 -> 0 | T92: PM Approved (SAR) | U92: =R89 -> 0 | W92: Latest Contract Change Order Log
D93: A | E93: B | F93: C | G93: D | H93: Processed | L93: Retention % | N93: ='Invoice Log'!N4 -> 0 | O93: Retention (SAR) | R93: ='Invoice Log'!R4 -> 0 | T93: Total Paid (SAR) | U93: =R90 -> 0
A94: Civil /Structural /Architectural | C94: =+'Quality-Stat'!D33 -> 3 | D94: =+'Quality-Stat'!E33 -> 2 | E94: =+'Quality-Stat'!F33 -> 2 | F94: =+'Quality-Stat'!G33 -> 1 | G94: =+'Quality-Stat'!H33 -> 0 | H94: =IF('Quality-Stat'!I33="","",'Quality-Stat'!I33) -> 3 | I94: {=+'Quality-Stat'!J33:L33} -> - | J94: 0 | K94: 0 | L94: Deduction / Penalties % | N94: ='Invoice Log'!N5 -> -6.0439714e-05 | O94: Deduction / Penalties (SAR) | R94: ='Invoice Log'!N6 -> -2000 | W94: CCO No. | X94: Date Added | Y94: Description of Change | AD94: Status | AE94: Cost | AF94: Sch Impact (Months) | AG94: Date Approved | AH94: Duration
A95: Electrical | C95: =IF('Quality-Stat'!D34="","",'Quality-Stat'!D34) -> 18 | D95: =IF('Quality-Stat'!E34="","",'Quality-Stat'!E34) -> 15 | E95: =IF('Quality-Stat'!F34="","",'Quality-Stat'!F34) -> 15 | F95: =IF('Quality-Stat'!G34="","",'Quality-Stat'!G34) -> 3 | G95: =IF('Quality-Stat'!H34="","",'Quality-Stat'!H34) -> 6 | H95: =IF('Quality-Stat'!I34="","",'Quality-Stat'!I34) -> 6 | I95: {=+'Quality-Stat'!J34:L34} -> - | J95: 0 | K95: 0 | L95: Resources at Site
A96: Mechanical | C96: =IF('Quality-Stat'!D35="","",'Quality-Stat'!D35) -> 6 | D96: =IF('Quality-Stat'!E35="","",'Quality-Stat'!E35) -> 5 | E96: =IF('Quality-Stat'!F35="","",'Quality-Stat'!F35) -> 5 | F96: =IF('Quality-Stat'!G35="","",'Quality-Stat'!G35) -> 1 | G96: =IF('Quality-Stat'!H35="","",'Quality-Stat'!H35) -> 3 | H96: =IF('Quality-Stat'!I35="","",'Quality-Stat'!I35) -> 3 | I96: {=+'Quality-Stat'!J35:L35} -> - | J96: 0 | K96: 0 | L96: Head Count - Manual | P96: Head Count - Non Manual | T96: Total Head Count | W96: =CCO!A3 -> - | X96: =CCO!B3 -> - | Y96: =CCO!C3 -> - | AD96: =CCO!D3 -> - | AE96: =CCO!E3 -> - | AF96: =CCO!F3 -> - | AG96: =CCO!G3 -> - | AH96: =CCO!H3 -> -
L97: Planned | M97: Actual | N97: Next Month Forecast | O97: Saudi Staff | P97: Planned | Q97: Actual | R97: Next Month Forecast | S97: Saudi Staff | T97: Total Plan | U97: Total Actual | V97: Variance
L98: =Manpower!A24 -> 40 | M98: =Manpower!B24 -> 65 | N98: =Manpower!F24 -> 0 | O98: =Manpower!H24 -> 0 | P98: =Manpower!A20 -> 20 | Q98: =Manpower!B20 -> 22 | R98: =Manpower!F20 -> 0 | S98: =Manpower!H20 -> 3 | T98: =L98+P98 -> 60 | U98: =M98+Q98 -> 87 | V98: =+U98-T98 -> 27
A99: TOTAL | C99: =IF('Quality-Stat'!D36="","",'Quality-Stat'!D36) -> 27 | D99: =IF('Quality-Stat'!E36="","",'Quality-Stat'!E36) -> 22 | E99: =IF('Quality-Stat'!F36="","",'Quality-Stat'!F36) -> 22 | F99: =IF('Quality-Stat'!G36="","",'Quality-Stat'!G36) -> 5 | G99: =IF('Quality-Stat'!H36="","",'Quality-Stat'!H36) -> 9 | H99: =IF('Quality-Stat'!I36="","",'Quality-Stat'!I36) -> 12 | I99: =MAX('Quality-Stat'!J33:L35) -> 0 | L99: Manpower Breakdown by Trade | S99: Major Equipment
A100: =Schedule!A1 -> Primavera P6 Schedule Status | L100: Key Trade | M100: Planned | N100: Actual | S100: Type | T100: Planned | U100: Actual | V100: Idle
A101: =Schedule!A2 -> Project Activities Overview | L101: =+Manpower!N23 -> Engineer | M101: =Manpower!N24 -> 2 | N101: =Manpower!N25 -> 10 | S101: =+Manpower!$B$49 -> Pick Up/Car | T101: =+Manpower!B50 -> 1 | U101: =+Manpower!B51 -> 2 | V101: =+Manpower!B52 -> 0
A102: =Schedule!A3 -> Schedule Statistics | F102: =Schedule!F3 -> Active Schedule Activities | L102: =+Manpower!P23 -> Doc. Controller | M102: =Manpower!P24 -> 1 | N102: =Manpower!P25 -> 1 | S102: =+Manpower!$D$49 -> Bus | T102: =+Manpower!D50 -> 1 | U102: 2 | V102: =+Manpower!D52 -> 0 | W102: Major Quantity Trackers
A103: =Schedule!A4 -> Total Act. | B103: =Schedule!B4 -> Not Started | C103: =Schedule!C4 -> In Progress | D103: =Schedule!D4 -> Completed | E103: =Schedule!E4 -> % | F103: =Schedule!F4 -> Active | G103: =Schedule!G4 -> Ahead | H103: =Schedule!H4 -> On | ... K103: =Schedule!K4 -> 0 | L103: =+Manpower!R23 -> Proc. Team | M103: =+Manpower!R24 -> 1 | N103: =Manpower!R25 -> 1 | S103: =+Manpower!$F$49 -> Dump Truck | T103: =+Manpower!F50 -> 10 | U103: 12 | V103: =+Manpower!F52 -> 0 | W103: BOQ N0. | X103: Item Description | AC103: Total Qty | AD103: Measu Unit | AE103: Plan to Date | AF103: Act to Date | AG103: Remaining | AH103: Variance
A104: =Schedule!A5 -> 855 | B104: =Schedule!B5 -> 586 | C104: =Schedule!C5 -> 46 | D104: =Schedule!D5 -> 223 | E104: =Schedule!E5 -> 0.26081871 | F104: =Schedule!F5 -> 10 | G104: =Schedule!G5 -> 15 | H104: =Schedule!H5 -> 0 | ... J104: =Schedule!J5 -> -7 | L104: =+Manpower!T23 -> Foreman | M104: =Manpower!T24 -> 2 | N104: =Manpower!T25 -> 3 | S104: =+Manpower!$H$49 -> Boom Truck | T104: =+Manpower!H50 -> 0 | U104: 2 | V104: =+Manpower!H52 -> 0 | W104: ='Major Quantities'!A3 -> B1.32 11 13.01 | X104: ='Major Quantities'!B3 -> Subgrade | AC104: ='Major Quantities'!C3 -> 20530 | AD104: ='Major Quantities'!D3 -> m3 | AE104: ='Major Quantities'!E3 -> 0 | AF104: ='Major Quantities'!F3 -> 15000 | AG104: ='Major Quantities'!H3 -> 5530 | AH104: ='Major Quantities'!I3 -> 0
A105: =Schedule!A6 -> Critical Path Activities | D105: =Schedule!D6 -> Free Float Management (Total) | H105: =Schedule!H6 -> Failed Start Activities | L105: =+Manpower!V23 -> Draftman | M105: =+Manpower!V24 -> 1 | N105: =+Manpower!V25 -> 1 | S105: =+Manpower!$J$49 -> Generator | T105: =+Manpower!J50 -> 1 | U105: 1 | V105: =+Manpower!J52 -> 0 | W105: ='Major Quantities'!A4 -> B1.32 11 23.01 | X105: ='Major Quantities'!B4 -> Aggregate base course | AC105: ='Major Quantities'!C4 -> 16375.94 | AD105: ='Major Quantities'!D4 -> m3 | AE105: ='Major Quantities'!E4 -> 0 | AF105: ='Major Quantities'!F4 -> 9875.94 | AG105: ='Major Quantities'!H4 -> 6500 | AH105: ='Major Quantities'!I4 -> 0
D106: =Schedule!D7 -> Greater Than 14 Days | F106: =Schedule!F7 -> Less Than 14 Days | L106: =+Manpower!X23 -> Driver | M106: =+Manpower!X24 -> 5 | N106: =+Manpower!X25 -> 31 | S106: =+Manpower!$L$49 -> CRANE | T106: =+Manpower!L50 -> 0 | U106: =+Manpower!L51 -> 1 | V106: =+Manpower!L52 -> 0 | W106: ='Major Quantities'!A6 -> B1.32 12 16.01 | X106: ='Major Quantities'!B6 -> Asphalt | AC106: ='Major Quantities'!C6 -> 13360 | AD106: ='Major Quantities'!D6 -> m3 | AE106: ='Major Quantities'!E6 -> 0 | AF106: ='Major Quantities'!F6 -> 573 | AG106: ='Major Quantities'!H6 -> 12787 | AH106: ='Major Quantities'!I6 -> 0
A107: =Schedule!A8 -> Last Week | B107: =Schedule!B8 -> This Week | C107: =Schedule!C8 -> Diff | D107: =Schedule!D8 -> Last Week | E107: =Schedule!E8 -> This Week | F107: =Schedule!F8 -> Last Week | G107: =Schedule!G8 -> This Week | H107: =Schedule!H8 -> Last Week | ... K107: =Schedule!K8 -> 0 | L107: =Manpower!Z23 -> UnSkilled Labor | M107: =Manpower!Z24 -> 15 | N107: =Manpower!Z25 -> 20 | S107: =+Manpower!$N$49 -> Showel | T107: =+Manpower!N50 -> 0 | U107: =+Manpower!N51 -> 1 | V107: =+Manpower!N52 -> 0 | W107: ='Major Quantities'!A7 -> B1.32 14 13.13.01 | X107: ='Major Quantities'!B7 -> Interlock | AC107: ='Major Quantities'!C7 -> 27900 | AD107: ='Major Quantities'!D7 -> m2 | AE107: ='Major Quantities'!E7 -> 0 | AF107: ='Major Quantities'!F7 -> 0 | AG107: ='Major Quantities'!H7 -> 27900 | AH107: ='Major Quantities'!I7 -> 0
A108: =Schedule!A9 -> 0 | B108: =Schedule!B9 -> 0 | C108: =Schedule!C9 -> 0 | D108: =Schedule!D9 -> 53 | E108: =Schedule!E9 -> 172 | F108: =Schedule!F9 -> 598 | G108: =Schedule!G9 -> 570 | H108: =Schedule!H9 -> 0 | ... J108: =Schedule!J9 -> -2 | L108: Total | M108: =Manpower!AF24 -> 40 | N108: =Manpower!AF25 -> 87 | S108: Total | T108: =SUM(T101:T107) -> 13 | U108: =SUM(U101:U107) -> 21 | V108: =SUM(V101:V107) -> 0 | W108: ='Major Quantities'!A8 -> B1.32 16 13.23.01 | X108: ='Major Quantities'!B8 -> Curbstone | AC108: ='Major Quantities'!C8 -> 20555 | AD108: ='Major Quantities'!D8 -> m2 | AE108: ='Major Quantities'!E8 -> 0 | AF108: ='Major Quantities'!F8 -> 0 | AG108: ='Major Quantities'!H8 -> 20555 | AH108: ='Major Quantities'!I8 -> 0
A109: Testing And Commissioning | Q109: Top Issues and Risks
Q110: Top 5 Issues
A111: Item | B111: Planned Start Date | D111: Planned Finish Date | F111: Forecast Start Date | H111: Forecast Finish Date | J111: Actual Start Date | L111: Actual Finish Date | N111: % Completed | O111: Open Comments | P111: Closed Comments | Q111: Issue No | R111: Date Identified | S111: Issue Description | W111: Responsible | X111: Action Taken | AA111: Mitigation | AF111: Current Status | AG111: Expected/Actual Closure | AH111: Duration Elapsed
A112: =Testing!A5 -> Civil Works | B112: =Testing!B13 -> 46516 | D112: =Testing!C13 -> 46538 | F112: =Testing!D13 -> 46544 | H112: =Testing!E13 -> 46561 | J112: =IF(Testing!F3=""," ",Testing!F3) | L112: =IF(Testing!G3=""," ",Testing!G3) | N112: 0 | O112: 0 | P112: 0 | Q112: =Issues!$A$23 -> 3120-11 | R112: =Issues!$V$23 -> 46298 | S112: =Issues!$O$23 -> Equipment operator found working zone with Non-compalince to site mandatory PPE. | W112: =Issues!$T$19 -> Contractor/HSE Team | X112: =Issues!$U$23 -> it was ensure to wear the mandatory PPE all the time when present on site | AF112: =Issues!K13 -> Close | AG112: =Issues!Y13 -> 2 | AH112: =Issues!X13 -> 1
A113: =Testing!A6 -> Storm Water Drainage Network | B113: =Testing!B14 -> 46406 | D113: =Testing!C14 -> 46424 | F113: =Testing!D14 -> 46464 | H113: =Testing!E14 -> 46482 | J113: =IF(Testing!F5=""," ",Testing!F5) | L113: =IF(Testing!G5=""," ",Testing!G5) | N113: =IF(Testing!H5=""," ",Testing!H5) -> 0 | O113: =IF(Testing!I5=""," ",Testing!I5) -> 0 | P113: =IF(Testing!J5=""," ",Testing!J5) -> 0 | Q113: =Issues!$A$24 -> 3120-12 | R113: =Issues!$V$24 -> 46305 | S113: =Issues!$O$24 -> Observe Hot Work activity without proper control measure Fire safety | W113: =Issues!$T$19 -> Contractor/HSE Team | X113: =Issues!$U$24 -> Provide Fire Extinguisher and other requirements as per Hot work requirements. | AF113: =Issues!K14 -> Close | AG113: =Issues!Y14 -> 2 | AH113: =Issues!X14 -> 1
A114: =Testing!A7 -> Sewerage Network | B114: =Testing!B15 -> 46460 | D114: =Testing!C15 -> 46477 | F114: =Testing!D15 -> 46412 | H114: =Testing!E15 -> 46431 | J114: =IF(Testing!F6=""," ",Testing!F6) | L114: =IF(Testing!G6=""," ",Testing!G6) | N114: =IF(Testing!H6=""," ",Testing!H6) -> 0 | O114: =IF(Testing!I6=""," ",Testing!I6) -> 0 | P114: =IF(Testing!J6=""," ",Testing!J6) -> 0 | Q114: =Issues!$A$25 -> 3120-13 | R114: =Issues!$V$25 -> 46306 | S114: =Issues!$O$25 -> Observe site without mandatory PPE complaince | W114: =Issues!$T$19 -> Contractor/HSE Team | X114: =Issues!$U$25 -> Wear the mandatory PPE all the time when present on site | AF114: =Issues!K15 -> Close | AG114: =Issues!Y15 -> 2 | AH114: =Issues!X15 -> 1
A115: =Testing!A8 -> Portable Water | B115: =Testing!B16 -> 46468 | D115: =Testing!C16 -> 46485 | F115: =Testing!D16 -> 46474 | H115: =Testing!E16 -> 46491 | L115: =IF(Testing!G7=""," ",Testing!G7) | N115: =IF(Testing!H7=""," ",Testing!H7) -> 0 | O115: =IF(Testing!I7=""," ",Testing!I7) -> 0 | P115: =IF(Testing!J7=""," ",Testing!J7) -> 0 | Q115: =Issues!$A$26 -> 3120-14 | R115: =Issues!$V$26 -> 46313 | S115: =Issues!$O$26 -> Observe dust created at temporary vehicles roads due insuffient dust control measures. | W115: =Issues!$T$19 -> Contractor/HSE Team | X115: =Issues!$U$26 -> Ensure dust control by regular spraying of water on vehicles routes | AF115: =Issues!K16 -> Close | AG115: =Issues!Y16 -> 2 | AH115: =Issues!X16 -> 1
A116: =Testing!A9 -> Electrical Works | B116: =Testing!B17 -> 46586 | D116: =Testing!C17 -> 46602 | F116: =Testing!D17 -> 46576 | H116: =Testing!E17 -> 46594 | L116: =IF(Testing!G8=""," ",Testing!G8) | N116: =IF(Testing!H8=""," ",Testing!H8) -> 0 | O116: =IF(Testing!I8=""," ",Testing!I8) -> 0 | P116: =IF(Testing!J8=""," ",Testing!J8) -> 0 | Q116: =Issues!$A$27 -> 3120-15 | R116: =Issues!$V$27 -> 46312 | S116: =Issues!$O$27 -> Observe non complaince of mandatory PPE by equipment operators | W116: =Issues!$T$19 -> Contractor/HSE Team | X116: =Issues!$U$27 -> Wear the mandatory PPE all the time by equipment operators when present on site | AF116: =Issues!K17 -> Close | AG116: =Issues!Y17 -> 2 | AH116: =Issues!X17 -> 1
...

Sheet General Information
A1: Weekly Progress Report - Construction Projects | K1: Data Date | L1: 46314
A2: Contract General Information
A3: Project Name | C3: Construction of Passenger Station for SAR Railway Sudair Industrial City
A4: Project ID | C4: SUD1-05-018
A5: Contractor | C5: Technical Dvelopment Co. "TDC"
A6: Consultant | C6: Saudi Arabia Consulting Engineering Company "EGIS"
A7: Stage | C7: Construction
A8: Status | C8: Active
A9: Modon PM | C9: Engr.Zyad Al Shabat
A11: Key Dates
A12: Contract Award Date | C12: 46112
A13: Contract Sign Date | C13: 46112
A14: Site Handover Date | C14: 46119
A15: Original Completion | C15: 46605
A16: Contract Award Date (Hijri) | C16: 10/12/1447
A17: Contract Sign Date (Hijri) | C17: 10/12/1447
A18: Site Handover Date (Hijri) | C18: 11/19/1447
A19: Original Completion (Hijri) | C19: 03/03/1449
A20: Revised Completion Date | C20: 46119
A21: Committed Completion Date | C21: 46605
A22: Forecast Completion | C22: 46605
A23: Variance | C23: =C22-C15 -> 0
A25: Key Project Submittals | C25: Submission Date | D25: Days taken to approve orginal plan from site handover date
A26: Quality Plan submission | C26: 46142 | D26: =C26-C14 -> 23
A27: Quality Plan approval | C27: 46153
A28: Quality Plan Last Update | C28: 46153
A30: Safety Plan submission | C30: 46142 | D30: =C30-C14 -> 23
A31: Safety Plan approval | C31: 46148
A32: Safety Plan Last Update | C32: =C30 -> 46142
A34: Risk Management Plan submission | C34: 46132 | D34: =C34-C14 -> 13
A35: Risk Management Plan approval | C35: 46142
A36: Risk Management Plan Last Update | C36: 46142
A38: Baseline Schedule submission | C38: 46149 | D38: =C38-C14 -> 30
A39: Baseline Schedule approval | C39: 46236
A40: No of Schedule Versions | C40: -
A41: Last Revised Schedule Approval Date | C41: -
A43: BOQ submission | C43: - | D43: -
A44: BOQ approval | C44: -
A45: No of Approved Version of BOQ | C45: -
A47: Execution Plan submission | C47: 46142 | D47: =C47-C14 -> 23
A48: Execution Plan Approval | C48: -

Sheet Progress
A1: Project Scope Statement | B1: Construction of Passenger Station for SAR Railway Sudair Industrial City
A4: Earned Value Progress (SAR) | K4: Physical Progress (Effort)
A5: WBS | C5: BOQ Value (SAR) | D5: % Wt. | E5: Weekly (SAR) | H5: To Date (SAR) | K5: Budgeted | L5: % Wt. | M5: Weekly Physical Progress | O5: To Date Physical Progress
E6: Planned | F6: Earned | G6: Original Plan | H6: Planned | I6: Earned | K6: (Manhours) | M6: Planned | N6: Earned | O6: Planned | P6: Earned
A7: Milestones | H7: 0 | I7: 0 | K7: 0 | L7: 0 | O7: 0 | P7: 0
A8: Mobilization | C8: 0 | H8: 0 | I8: 0 | K8: 19154 | L8: 0.029999947 | M8: =O8-O58 -> 0 | N8: =P8-P58 -> 0 | O8: 19793 | P8: 19793
A9: Engineering | C9: 0 | D9: 0 | E9: =H9-H59 -> 0 | F9: =I9-I59 -> 0 | G9: 0 | H9: 0 | I9: 0 | K9: 31923.4 | L9: 0.050000016 | M9: =O9-O59 -> 0 | N9: =P9-P59 -> 0 | O9: 32988 | P9: 31339
A10: Procurement | C10: 0 | D10: 0 | E10: =H10-H60 -> 0 | F10: =I10-I60 -> 0 | G10: 0 | H10: 0 | I10: 0 | K10: 89385.5 | L10: 0.14000001 | M10: =O10-O60 -> 3134 | N10: =P10-P60 -> 4642 | O10: 68347 | P10: 17130
A11: Construction | C11: 33090852 | D11: 1 | E11: =H11-H61 -> 710697.41 | F11: =I11-I61 -> 214091.03 | G11: 0 | H11: 6301807.5 | I11: 7095542 | K11: 478850.8 | L11: 0.74999992 | M11: =O11-O61 -> 8552 | N11: =P11-P61 -> 3430 | O11: 121851 | P11: 98246
A12: Package-1 | C12: 22502032 | D12: 0.68000763 | E12: =H12-H62 -> 613731.64 | F12: =I12-I62 -> 214091.03 | G12: 0 | H12: 5886632.1 | I12: 7095542 | K12: 345775.5 | L12: 0.54157077 | M12: =O12-O62 -> 8143 | N12: =P12-P62 -> 3430 | O12: 109662 | P12: 98246
A13: ROAD WORKS 1 | C13: 17704263 | D13: 0.53501986 | E13: =H13-H63 -> 514154.16 | F13: =I13-I63 -> 111822.59 | G13: 0 | H13: 5366361.2 | I13: 6500573.5 | K13: 168659.6 | L13: 0.26416305 | M13: =O13-O64 -> 15867 | N13: =P13-P63 -> 557 | O13: 73549 | P13: 78905
A14: ROAD - 01 | C14: 10400905 | D14: 0.31431361 | E14: =H14-H64 -> 275854.68 | F14: =I14-I64 -> 111822.59 | G14: 0 | H14: 3150987.4 | I14: 4140066.2 | K14: 96629.6 | L14: 0.15134608 | M14: =O14-O64 -> 1058 | N14: =P14-P64 -> 557 | O14: 58740 | P14: 62660
A15: ROAD - 02 | C15: 7303358 | D15: 0.22070625 | E15: =H15-H65 -> 238299.48 | F15: =I15-I65 -> 0 | H15: 2215373.7 | I15: 2360507.3 | K15: 72030.1 | L15: 0.11281712 | M15: =O15-O65 -> 1164 | N15: =P15-P65 -> 0 | O15: 14810 | P15: 16245
A16: ELECTRICAL WORKS | C16: 3415753 | D16: 0.10322348 | E16: =H16-H66 -> 62394.6 | F16: =I16-I66 -> 43659.79 | H16: 246971.83 | I16: 62629.37 | K16: 103222.1 | L16: 0.16167158 | N16: =Q16-Q65 -> 0 | O16: 18369 | P16: 3751
A17: MV Network | C17: 1577890 | D17: 0.047683571 | E17: =H17-H67 -> 17205.13 | F17: =I17-I67 -> 0 | H17: 35478.52 | I17: 0 | K17: 37659 | L17: 0.058983397 | M17: =O17-O68 -> 1036 | N17: =P17-P68 -> 0 | O17: 1036 | P17: 0
A18: Earthing System | C18: 4795 | D18: 0.0001449041 | E18: =H18-H68 -> 0 | F18: =I18-I67 -> 0 | H18: 0 | I18: 0 | K18: 172.8 | L18: 0.00027064795 | M18: =O18-O68 -> 0 | N18: =P18-P68 -> 0 | O18: 0 | P18: 0
A19: Street Lighting Network | C19: 1454545 | D19: 0.043956106 | E19: =H19-H69 -> 30727.34 | F19: =I19-I69 -> 0 | H19: 146450.34 | I19: 6382.5 | K19: 51050.8 | L19: 0.0799583 | M19: =O19-O70 -> 9986 | N19: =P19-P69 -> 0 | O19: 13326 | P19: 515
A20: TELECOMMUNICATIONS WORKS | C20: 378522 | D20: 0.011438871 | E20: =H20-H70 -> 14462.12 | F20: =I20-I70 -> 43659.79 | H20: 65042.96 | I20: 56246.87 | K20: 14339.6 | L20: 0.022459394 | M20: =O20-O71 -> 4008 | N20: =P20-P70 -> 2429 | O20: 4008 | P20: 3237
A21: LOW VOLTAGE | C21: 86942 | D21: 0.0026273727 | E21: =H21-H71 -> 0 | F21: =I21-I71 -> 0 | H21: 0 | I21: 4926.72 | K21: 6638.4 | L21: 0.010397392 | M21: =O21-O72 -> 0 | N21: =P21-P72 -> 329 | O21: 0 | P21: 651
A22: ROAD - 01 | C22: 28981 | D22: 0.00087580096 | E22: =H22-H72 -> 0 | F22: =I22-I72 -> 0 | H22: 0 | I22: 2028.65 | K22: 2072.2 | L22: 0.0032455826 | M22: =O22-O73 -> 0 | N22: =P22-P72 -> 0 | O22: 0 | P22: 322
A23: ROAD - 02 | C23: 57961 | D23: 0.0017515717 | E23: =H23-H73 -> 0 | F23: =I23-I72 -> 869.42 | H23: 0 | I23: 2898.07 | K23: 4566.2 | L23: 0.0071518094 | M23: =O23-O74 -> -9146 | N23: =P23-P73 -> 0 | O23: 0 | P23: 328
A24: PORTABLE WATER | C24: 379700 | D24: 0.01147447 | E24: =H24-H74 -> 11904.6 | F24: =I24-I73 -> 210420.04 | H24: 66242.45 | I24: 213318.11 | K24: 46755 | L24: 0.073230005 | M24: =O24-O75 -> 7499 | N24: =P24-P75 -> 4879 | O24: 11285 | P24: 12074
A25: ROAD - 01 | C25: 189850 | D25: 0.0057372352 | E25: =H25-H75 -> 5695.33 | F25: =I25-I74 -> -87612.8 | H25: 30835.92 | I25: 121896.06 | K25: 20132.1 | L25: 0.031531896 | M25: =O25-O76 -> -614 | N25: =P25-P76 -> 2412 | O25: 4746 | P25: 7195
A26: ROAD - 02 | C26: 189850 | D26: 0.0057372352 | E26: =H26-H76 -> 6209.26 | F26: =I26-I76 -> 3809.25 | H26: 35406.53 | I26: 91422.05 | K26: 26622.9 | L26: 0.041698109 | M26: =O26-O76 -> 1179 | N26: =P26-P76 -> 96 | O26: 6539 | P26: 4879
A27: SEWARAGE NETWORK | C27: 621335 | D27: 0.01877664 | E27: =H27-H76 -> 98048.47 | F27: =I27-I76 -> 20653.36 | H27: 127245.74 | I27: 108266.16 | K27: 19751.7 | L27: 0.030936094 | M27: =O27-O78 -> 2570 | N27: =P27-P77 -> 312 | O27: 6304 | P27: 2638
A28: ROAD - 01 | C28: 372801 | D28: 0.011265984 | E28: =H28-H77 -> -32403.53 | F28: =I28-I77 -> 0 | H28: 79365.26 | I28: 90221.8 | K28: 12694.5 | L28: 0.019882757 | M28: =O28-O79 -> 2872 | N28: =P28-P79 -> 1863 | O28: 4447 | P28: 2226
A29: ROAD - 02 | C29: 248534 | D29: 0.0075106558 | E29: =H29-H78 -> -23284.72 | F29: =I29-I79 -> 2122.86 | H29: 47880.48 | I29: 18044.36 | K29: 7057.2 | L29: 0.011053337 | M29: =O29-O80 -> 1723 | N29: =P29-P79 -> 49 | O29: 1857 | P29: 412
A30: STORM WATER | C30: 294040 | D30: 0.0088858395 | E30: =H30-H79 -> 39207.33 | F30: =I30-I79 -> 189906.67 | H30: 79810.92 | I30: 205828.17 | K30: 748.6 | L30: 0.0011724945 | M30: =O30-O81 -> 22 | N30: =P30-P80 -> 38 | O30: 156 | P30: 228
A31: ROAD N... | C31: 294040 | D31: 0.0088858395 | E31: =H31-H80 -> 9801.34 | F31: =I31-I80 -> 36755.03 | H31: 79810.92 | I31: 205828.17 | K31: 748.6 | L31: 0.0011724945 | M31: =O31-O81 -> 22 | N31: =P31-P82 -> 228 | O31: 156 | P31: 228
A32: Package-3 | C32: 10588820 | D32: 0.31999237 | E32: =H32-H82 -> 96965.76 | F32: =I32-I82 -> 0 | H32: 415175.34 | I32: 0 | K32: 133075.3 | L32: 0.20842915 | M32: =O32-O82 -> 410 | N32: =P32-P83 -> 0 | O32: 12190 | P32: 0
A33: Site Works | C33: 21090 | D33: 0.00063733626 | E33: =H33-H82 -> -297119.56 | F33: =I33-I82 -> 0 | H33: 21090.02 | I33: 0 | K33: 1835.5 | L33: 0.0028748513 | M33: =O33-O83 -> 0 | N33: =P33-P84 -> 0 | O33: 9506 | P33: 0
A34: Earthworks | C34: 21090 | D34: 0.00063733626 | E34: =H34-H83 -> 0 | F34: =I34-I83 -> 0 | H34: 21090.02 | I34: 0 | K34: 1835.5 | L34: 0.0028748513 | M34: =O34-O84 -> 0 | N34: =P34-P85 -> 0 | O34: 9506 | P34: 0
A35: Platform Works | C35: 6003782 | D35: 0.18143329 | E35: =H35-H85 -> 84562.57 | F35: =I35-I84 -> 0 | G35: 0 | H35: 371500.3 | I35: 0 | K35: 68964.6 | L35: 0.10801578 | M35: =O35-O86 -> 238 | N35: =P35-P86 -> 0 | O35: 2336 | P35: 0
A36: Platform Substructure | C36: 5037344 | D36: 0.15222769 | E36: =H36-H85 -> 84562.57 | F36: =I36-I85 -> 0 | G36: 0 | H36: 371500.3 | I36: 0 | K36: 47410.5 | L36: 0.074256681 | M36: =O36-O87 -> 2336 | N36: =P36-P87 -> 0 | O36: 2336 | P36: 0
A37: Finishes & Architectural Works | C37: 966437 | D37: 0.029205564 | E37: =H37-H87 -> 0 | F37: =I37-I86 -> 0 | H37: 0 | I37: 0 | K37: 21151.7 | L37: 0.033128844 | M37: =O37-O88 -> 0 | N37: =P37-P88 -> 0 | O37: 0 | P37: 0
A38: Platform Electrical Works | C38: 0 | D38: 0 | H38: 0 | I38: 0 | K38: 402.4 | L38: 0.00063025888 | O38: 0 | P38: 0
A39: Canopy works | C39: 3863605 | D39: 0.1167575 | H39: 22585.02 | I39: 0 | K39: 33380.9 | L39: 0.052282825 | O39: 348 | P39: 0
A40: Civil and Architectural Works | C40: 166440 | D40: 0.0050297889 | H40: 11200.01 | I40: 0 | K40: 1830.7 | L40: 0.0028673333 | O40: 228 | P40: 0
A41: Metals | C41: 3697165 | D41: 0.11172771 | H41: 11385.01 | I41: 0 | K41: 31550.3 | L41: 0.049415648 | O41: 120 | P41: 0
A42: Electrical Works | C42: 700343 | D42: 0.021164248 | H42: 0 | I42: 0 | K42: 28894.3 | L42: 0.045255689 | O42: 0 | P42: 0
A43: Low-Voltage Electrical Power Conductors and Cables | C43: 36000 | D43: 0.001087914 | H43: 0 | I43: 0 | K43: 675.6 | L43: 0.0010581583 | O43: 0 | P43: 0
A44: Ondoor Lighting Points | C44: 62010 | D44: 0.0018739318 | H44: 0 | I44: 0 | K44: 389.5 | L44: 0.00061005426 | O44: 0 | P44: 0
A45: Outdoor Lighting Fixtures | C45: 152490 | D45: 0.0046082222 | H45: 0 | I45: 0 | K45: 16411.4 | L45: 0.02570435 | O45: 0 | P45: 0
A46: CCTV | C46: 327218 | D46: 0.0098884731 | H46: 0 | I46: 0 | K46: 4075.8 | L46: 0.0063837205 | O46: 0 | P46: 0
A47: Voice Evacuation System | C47: 122624 | D47: 0.0037056767 | H47: 0 | I47: 0 | K47: 7341.9 | L47: 0.011499249 | O47: 0 | P47: 0
A48: Testing and Comissioning | C48: 0 | D48: 0 | H48: 0 | I48: 0 | K48: 12737.5 | L48: 0.019950106 | O48: 0 | P48: 0
A49: Close Out | C49: 0 | D49: 0 | H49: 0 | I49: 0 | K49: 6416.6 | L49: 0.010049998 | O49: 0 | P49: 0
A52: Total | C52: 33090825 | D52: =D9+D10+D11+D48+D49 -> 1 | E52: =E9+E10+E11+E36 -> 795259.98 | F52: =F9+F10+F11+F36 -> 214091.03 | G52: =G9+G10+G11+G37+G38+G36 -> 0 | H52: =H9+H10+H11+H48+H49 -> 6301807.5 | I52: =I9+I10+I11+I48+I49 -> 7095542 | K52: =K8+K9+K10+K11+K48+K49 -> 638467.8 | L52: =L8+L9+L10+L11+L48+L49 -> 1 | M52: =M9+M10+M11+M48+M49 -> 11686 | N52: =N9+N10+N11+N36 -> 8072 | O52: =O8+O9+O10+O11+O49+O48 -> 242979 | P52: =P8+P9+P10+P11+P49+P48 -> 166508
H53: =H52/C52 -> 0.19043972 | I53: =I52/C52 -> 0.21442627 | O53: =O52/K52 -> 0.38056579 | P53: =P52/K52 -> 0.2607931
H57: PW Planned | I57: PW Actuals | O57: PW Planned | P57: PW Actuals
G58: Mobilization | H58: 0 | I58: 0 | M58: Mobilization | O58: 19793 | P58: 19793
G59: Engineering | H59: 0 | I59: 0 | M59: Engineering | O59: 32988 | P59: 31339
G60: Procurement | H60: 0 | I60: 0 | M60: Procurement | O60: 65213 | P60: 12488
G61: Construction | H61: 5591110 | I61: 6881451 | M61: Construction | O61: 113299 | P61: 94816
G62: Package-1 | H62: 5272900.5 | I62: 6881451 | M62: Package-1 | O62: 101519 | P62: 94816
G63: ROAD WORKS 1 | H63: 4852207 | I63: 6388750.9 | M63: ROAD WORKS 1 | O63: 71328 | P63: 78348
G64: ROAD - 01 | H64: 2875132.8 | I64: 4028243.6 | M64: ROAD - 01 | O64: 57682 | P64: 62103
G65: ROAD - 02 | H65: 1977074.3 | I65: 2360507.3 | M65: ROAD - 02 | O65: 13646 | P65: 16245
G66: ELECTRICAL WORKS | H66: 184577.23 | I66: 18969.58 | M66: ELECTRICAL WORKS | O66: 15603 | P66: 1323
G67: MV Network | H67: 18273.39 | I67: 0 | M67: MV Network | O67: 542 | P67: 0
G68: Earthing System | H68: 0 | I68: 0 | M68: Earthing System | O68: 0 | P68: 0
G69: Street Lighting Network | H69: 115723 | I69: 6382.5 | M69: Street Lighting Network | O69: 11722 | P69: 515
... G99: Close Out | H99: 0 | I99: 0 | M99: Close Out | O99: 0 | P99: 0

Sheet Weekly Photos
B1: WEEKLY PROGRESS PHOTOS | V1: ='[36]General Information'!K1 -> Data Date | W1: ='General Information'!L1 -> 46314
B2: Asphalt base course first layer 8 cm at Road 1 | L2: Asphalt base course first layer 8 cm at Road 1
B40: Aggregate Base course layer at Road 1 | L40: Aggregate Base course layer at Road 1
B59: Grading for second layer of subgrade at Road no.1 From st 00+650 to 00+950 | L59: Grading for second layer of subgrade at Road no.1 From st 00+650 to 00+950

Sheet Quality-Stat
A1: Quality -Stat
A2: Quality Reports
A3: Item | C3: Issued | D3: Closed | E3: Pending | F3: Avg. Closing (Days) | G3: Pending
G4: 0-10 Days | H4: 11-20 Days | I4: 21-30 Days | J4: 31-60 Days | K4: > 60 Days
A6: Non Conforomance Report (NCR) | C6: 4 | D6: 4 | E6: =C6-D6 -> 0 | H6: - | I6: - | J6: - | K6: -
A7: Site Instruction (SI) | C7: 0 | D7: 0 | E7: =C7-D7 -> 0 | G7: - | H7: 0 | I7: 0 | J7: 0 | K7: 0
A8: Material Inspection Report (MIR) | C8: 15 | D8: 15 | E8: =C8-D8 -> 0 | G8: =C8-D8 -> 0 | H8: 0 | I8: 0 | J8: 0 | K8: 0
A9: Field Inspection Request (FIR) | C9: 152 | D9: 143 | E9: =C9-D9 -> 9 | G9: =C9-D9 -> 9 | H9: 0 | I9: 0 | J9: 0 | K9: 0
A11: Shop Drawings
A12: Item Per WBS | D12: Total | E12: Total Drawings Submitted | J12: Remaining Drawings | K12: Pending | L12: Total Submittals
E13: A | F13: B | G13: C | H13: D | I13: Processed(A+B+C+D) | J13: with Designer | K13: Submittals With Consultant
A14: Road work | D14: 90 | E14: 80 | F14: 10 | G14: 0 | H14: 0 | I14: =E14+F14+G14+H14 -> 90 | J14: 0 | K14: 0 | L14: =I14 -> 90
A15: wet network(sewer,potable,Storm) | D15: 47 | E15: 13 | F15: 34 | G15: 0 | H15: 0 | I15: =E15+F15+G15+H15 -> 47 | J15: =D15-I15 -> 0 | K15: 0 | L15: =I15 -> 47
A16: Telecom | D16: 15 | E16: 8 | F16: 7 | G16: 0 | H16: 0 | I16: =E16+F16+G16+H16 -> 15 | J16: 0 | K16: 0 | L16: =I16 -> 15
A17: Lighting | C17: Mechanical | D17: 28 | E17: 8 | F17: 20 | G17: 0 | H17: 0 | I17: =E17+F17+G17+H17 -> 28 | J17: 0 | K17: 0 | L17: =I17 -> 28
A18: Electrical | C18: Electrical | D18: 24 | E18: 5 | F18: 19 | G18: 0 | H18: 0 | I18: =E18+F18+G18+H18 -> 24 | J18: 0 | K18: 0 | L18: =I18 -> 24
A19: TOTAL | D19: =SUM(D14:D18) -> 204 | E19: =SUM(E14:E18) -> 114 | F19: =SUM(F14:F18) -> 90 | G19: =SUM(G14:G18) -> 0 | H19: =SUM(H14:H18) -> 0 | I19: =SUM(I14:I18) -> 204 | J19: =SUM(J14:J18) -> 0 | K19: =SUM(K14:K18) -> 0 | L19: =SUM(L14:L18) -> 204
A22: Material Approval
A23: Item Per WBS | D23: Total | E23: Total Materials Submitted | J23: Remaining to approve | K23: Pending | L23: Total Submittals
E24: A | F24: B | G24: C | H24: D | I24: Processed(A+B+C+D) | J24: with Designer | K24: Submittals With Consultant
A25: Civil /Structural /Architectural | D25: 20 | E25: 0 | F25: 18 | G25: 1 | H25: 0 | I25: =E25+F25+G25+H25 -> 19 | J25: 0 | K25: 1 | L25: =I25+J25+K25 -> 20
A26: Electrical | C26: Mechanical | D26: 16 | E26: 1 | F26: 13 | G26: 2 | H26: 0 | I26: 16 | J26: 0 | K26: 0 | L26: =I26+J26+K26 -> 16
A27: Mechanical/STR | C27: Electrical | D27: 7 | E27: 0 | F27: 7 | G27: 0 | H27: 0 | I27: =E27+F27+G27+H27 -> 7 | J27: =D27-I27 -> 0 | K27: 0 | L27: =I27+J27+K27 -> 7
A28: TOTAL | D28: =SUM(D23:D27) -> 43 | E28: =SUM(E25:E27) -> 1 | F28: =SUM(F25:F27) -> 38 | G28: =SUM(G25:G27) -> 3 | H28: =SUM(H25:H27) -> 0 | I28: =SUM(I25:I27) -> 42 | J28: 0 | K28: =SUM(K25:K27) -> 1 | L28: =SUM(L25:L27) -> 43
A30: Procurement Summary
A31: Item Per WBS | D31: Total Materials | E31: Total Number of P.O. | F31: Actual P.O. To Date | G31: Remaining P.O | H31: Actual Material on Site | I31: Remaining Materials | J31: Material Delivery Completion (Date)
E32: A | F32: B | G32: C | H32: D | I32: Processed
A33: Civil /Structural /Architectural | D33: 3 | E33: 2 | F33: 2 | G33: 1 | H33: 0 | I33: =D33-H33 -> 3 | J33: -
A34: Electrical | C34: Electrical | D34: 18 | E34: 15 | F34: 15 | G34: 3 | H34: 6 | I34: 6 | J34: -
A35: Mechanical | C35: Electrical | D35: 6 | E35: 5 | F35: 5 | G35: 1 | H35: 3 | I35: 3 | J35: -
A36: TOTAL | D36: =SUM(D33:D35) -> 27 | E36: =SUM(E33:E35) -> 22 | F36: =SUM(F33:F35) -> 22 | G36: =SUM(G33:G35) -> 5 | H36: =SUM(H33:H35) -> 9 | I36: =SUM(I33:I35) -> 12
A38: Consultant Quality Inspections / Observations (Weekly Basis) | I38: Overall Average | J38: - | L38: Average Closing | M38: -
A39: Week Number | B39: Date of Audit | C39: Date Issued | D39: Numbers Of Comments | E39: Quality Score | F39: Date Closed | G39: Closure Duration | I39: This Week Score | J39: - | L39: Average Number of Comments Per Audit | M39: -

Sheet Quality.
B2: QC OBSERVATIONS CHECKLIST
BB4: 45377
B6: Project No. | E6: SUD1-05-018 | K6: OBS No. | U6: Inspection Day: | X6: ='General Information'!L1 -> 46314
B8: Project | E8: Construction of Passenger Station for SAR Railway Sudair Industrial City | O8: Contractor: Consultant: | U8: Technical Development Company Egis Engineering cunsultancy
B10: 4 | D10: Excellent | G10: Quality Management System is being practiced and applies to MODON System | Z10: 90 - 100 | AB10: QC Overall Score | AC10: =Q49 -> 0.88724138 | AN10: =SUM(Z10:Z13) -> 0 | AO10: 100 | AP10: 0.22883295
B11: 3 | D11: Good | G11: Evidence of compliance with plans and procedures. | Z11: 80 - 89 | AN11: =SUM(Y10:Y14) -> 0 | AO11: 89 | AP11: 0.20366133
B12: 2 | D12: Average | G12: Indication level of compliance with standards but there is room for improvement | Z12: 70 - 79 | AO12: 79 | AP12: 0.18077803
B13: 1 | D13: Improve | G13: Quality and Control is NOT being managed effectively. Needs Improvement | Z13: ≤ 69 | AO13: 69 | AP13: 0.15789474
B14: 0 | D14: N/A | G14: Item was not applicable or this item was not reviewed during the inspection. | Z14: Zero | AO14: 100 | AP14: 0.22883295
B16: No. | C16: Topic | K16: E (4) | L16: G (3) | M16: A (2) | N16: I (1) | O16: N/A (0) | Q16: No. | R16: Topic | Z16: E (4) | AA16: G (3) | AB16: A (2) | AC16: I (1) | AD16: N/A (0) | AO16: =SUM(AO10:AO15) -> 437
K17: 1 | L17: 0.89 | M17: 0.79 | N17: 0.69 | O17: 1 | Z17: 1 | AA17: 0.89 | AB17: 0.79 | AC17: 0.69 | AD17: 1 | AF17: =SUM(AF18:AG46)/COUNT(AF18:AG46) -> 0.88724138
B18: 1 | C18: Control of Access to Site/Office | L18: 1 | Q18: 30 | R18: QC of Excavation | Z18: 0 | AA18: 1 | AD18: 0 | AF18: =SUMPRODUCT($K$17:$O$17,K18:O18) -> 0.89 | AG18: =SUMPRODUCT($Z$17:$AD$17,Z18:AD18) -> 0.89 | AV18: Item Count | AW18: Score | AX18: Distributtion
B19: 2 | C19: Document Control Administration | L19: 1 | Q19: 31 | R19: QC of Roads/Round about | AA19: 1 | AB19: 0 | AF19: =SUMPRODUCT($K$17:$O$17,K19:O19) -> 0.89 | AG19: =SUMPRODUCT($Z$17:$AD$17,Z19:AD19) -> 0.89 | AX19: Overall | AY19: Relevant
B20: 3 | C20: Project Documents and Progress | L20: 1 | Q20: 32 | R20: QC of Interlock & Curbstone | AA20: 1 | AB20: 0 | AF20: =SUMPRODUCT($K$17:$O$17,K20:O20) -> 0.89 | AG20: =SUMPRODUCT($Z$17:$AD$17,Z20:AD20) -> 0.89 | AM20: 4 | AN20: =58 -> 58 | AO20: counts | AQ20: 4 | AR20: Excellent | AV20: =SUM(Z18:Z46,K18:K46) -> 1 | AW20: =AQ20*AV20 -> 4 | AX20: =AV20/$AV$25 -> 0.01754386 | AY20: =AV20/SUM($AV$20:$AV$23) -> 0.028571429
B21: 4 | C21: Contractor's Quality Plan/CM (Updated and Reviewed) | K21: 0 | L21: 1 | Q21: 33 | R21: Layers/Backfilling Sampling | Z21: 0 | AA21: 1 | AB21: 0 | AD21: 0 | AF21: =SUMPRODUCT($K$17:$O$17,K21:O21) -> 0.89 | AG21: =SUMPRODUCT($Z$17:$AD$17,Z21:AD21) -> 0.89 | AM21: 3 | AN21: =58 -> 58 | AO21: counts | AQ21: 3 | AR21: Good | AV21: =SUM(L18:L46,AA18:AA46) -> 23 | AW21: =AQ21*AV21 -> 69 | AX21: =AV21/$AV$25 -> 0.40350877 | AY21: =AV21/SUM($AV$20:$AV$23) -> 0.65714286
B22: 5 | C22: MS Log and Paperwork | L22: 1 | M22: 0 | Q22: 34 | R22: Pump Stations Units | AC22: 0 | AD22: 1 | AF22: =SUMPRODUCT($K$17:$O$17,K22:O22) -> 0.89 | AG22: =SUMPRODUCT($Z$17:$AD$17,Z22:AD22) -> 1 | AM22: 2 | AN22: =58 -> 58 | AO22: counts | AQ22: 2 | AR22: Average | AV22: =SUM(M18:M46,AB18:AB46) -> 4 | AW22: =AQ22*AV22 -> 8 | AX22: =AV22/$AV$25 -> 0.070175439 | AY22: =AV22/SUM($AV$20:$AV$23) -> 0.11428571
B23: 6 | C23: RFI, FIR, & MIR Procedure | L23: 1 | Q23: 35 | R23: Quality of Form Work | AA23: 0 | AC23: 0 | AD23: 0 | AF23: =SUMPRODUCT($K$17:$O$17,K23:O23) -> 0.89 | AG23: =SUMPRODUCT($Z$17:$AD$17,Z23:AD23) -> 0 | AM23: 1 | AN23: =58 -> 58 | AO23: counts | AQ23: 1 | AR23: Improve | AV23: =SUM(N18:N46,AC18:AC46) -> 7 | AW23: =AQ23*AV23 -> 7 | AX23: =AV23/$AV$25 -> 0.12280702 | AY23: =AV23/SUM($AV$20:$AV$23) -> 0.2
B24: 7 | C24: RFI, FIR, & MIR Inventory system | L24: 1 | Q24: 36 | R24: Design Change List | AD24: 1 | AF24: =SUMPRODUCT($K$17:$O$17,K24:O24) -> 0.89 | AG24: =SUMPRODUCT($Z$17:$AD$17,Z24:AD24) -> 1 | AM24: 0 | AN24: =58 -> 58 | AO24: counts | AQ24: 0 | AR24: N/A | AV24: =SUM(O18:O46,AD18:AD46) -> 22 | AW24: =AQ24*AV24 -> 0 | AX24: =AV24/$AV$25 -> 0.38596491 | AY24: -
B25: 8 | C25: NCRs Control & Procedure | L25: 1 | M25: 0 | Q25: 37 | R25: Quality of Concrete Placing | AA25: 0 | AB25: 0 | AC25: 0 | AD25: 1 | AF25: =SUMPRODUCT($K$17:$O$17,K25:O25) -> 0.89 | AG25: =SUMPRODUCT($Z$17:$AD$17,Z25:AD25) -> 1 | AR25: Total | AV25: =SUM(AV20:AV24) -> 57 | AW25: =SUM(AW20:AW24) -> 88 | AX25: =SUM(AX20:AX24) -> 1 | AY25: =SUM(AY20:AY24) -> 1
B26: 9 | C26: NCR Log | L26: 1 | Q26: 38 | R26: Concrete Surface Finishing | AA26: 0 | AB26: 0 | AC26: 0 | AD26: 1 | AF26: =SUMPRODUCT($K$17:$O$17,K26:O26) -> 0.89 | AG26: =SUMPRODUCT($Z$17:$AD$17,Z26:AD26) -> 1
B27: 10 | C27: MODON Standard* | K27: 0 | M27: 1 | Q27: 39 | R27: Pedestals/Columns/Beams Alignment | AA27: 0 | AD27: 1 | AF27: =SUMPRODUCT($K$17:$O$17,K27:O27) -> 0.79 | AG27: =SUMPRODUCT($Z$17:$AD$17,Z27:AD27) -> 1 | AV27: Maz Score Available: | AW27: =SUM(AV20:AV23)*AQ20 -> 140 | AX27: <- Excludes N/A items
B28: 11 | C28: Project Risk Plan/Management* | M28: 0 | N28: 1 | Q28: 40 | R28: Siporex Lifting & Unloading | AD28: 1 | AF28: =SUMPRODUCT($K$17:$O$17,K28:O28) -> 0.69 | AG28: =SUMPRODUCT($Z$17:$AD$17,Z28:AD28) -> 1
B29: 12 | C29: Monthly Quality Reports* | L29: 0 | M29: 0 | N29: 1 | O29: 0 | Q29: 41 | R29: Siporex Quality Pre-installation | AD29: 1 | AF29: =SUMPRODUCT($K$17:$O$17,K29:O29) -> 0.69 | AG29: =SUMPRODUCT($Z$17:$AD$17,Z29:AD29) -> 1
B30: 13 | C30: ITP | L30: 0 | M30: 1 | O30: 0 | Q30: 42 | R30: Siporex Finishing Quality | AD30: 1 | AF30: =SUMPRODUCT($K$17:$O$17,K30:O30) -> 0.79 | AG30: =SUMPRODUCT($Z$17:$AD$17,Z30:AD30) -> 1 | AR30: Total Score | AW30: Percentage (%)
B31: 14 | C31: MODON Weekly Report | L31: 0 | N31: 1 | Q31: 43 | R31: Roads / Parking Markings | AA31: 1 | AD31: 0 | AF31: =SUMPRODUCT($K$17:$O$17,K31:O31) -> 0.69 | AG31: =SUMPRODUCT($Z$17:$AD$17,Z31:AD31) -> 0.89 | AN31: =MAX(AN20:AN24) -> 58 | AR31: =AW25 -> 88 | AW31: =SUM(100/AR33*AR31) -> 62.857143 | AY31: %
B32: 15 | C32: Design Change Official Paperwork* | N32: 0 | O32: 1 | Q32: 44 | R32: QC of Finishing Outdoors | AC32: 0 | AD32: 1 | AF32: =SUMPRODUCT($K$17:$O$17,K32:O32) -> 1 | AG32: =SUMPRODUCT($Z$17:$AD$17,Z32:AD32) -> 1 | AR32: Max Score Available | BP32: 31
B33: 16 | C33: Design Change was Applied* | O33: 1 | Q33: 45 | R33: Quality of Finishing Indoors | AD33: 1 | AF33: =SUMPRODUCT($K$17:$O$17,K33:O33) -> 1 | AG33: =SUMPRODUCT($Z$17:$AD$17,Z33:AD33) -> 1 | AR33: =AW27 -> 140 | BP33: 32
B34: 17 | C34: Material List | K34: 0 | L34: 1 | O34: 0 | Q34: 46 | R34: Stairs Quality | AD34: 1 | AF34: =SUMPRODUCT($K$17:$O$17,K34:O34) -> 0.89 | AG34: =SUMPRODUCT($Z$17:$AD$17,Z34:AD34) -> 1 | BP34: 33
B35: 18 | C35: Pending Material Status | L35: 1 | O35: 0 | Q35: 47 | R35: Tanks Method Statement Work | AB35: 0 | AC35: 0 | AD35: 1 | AF35: =SUMPRODUCT($K$17:$O$17,K35:O35) -> 0.89 | AG35: =SUMPRODUCT($Z$17:$AD$17,Z35:AD35) -> 1 | BP35: 34
B36: 19 | C36: Lifting Plan* | K36: 0 | L36: 0 | N36: 1 | O36: 0 | Q36: 48 | R36: Electric Rooms | AD36: 1 | AF36: =SUMPRODUCT($K$17:$O$17,K36:O36) -> 0.69 | AG36: =SUMPRODUCT($Z$17:$AD$17,Z36:AD36) -> 1 | BP36: 35
B37: 20 | C37: DWG Log | M37: 0 | N37: 1 | Q37: 49 | R37: QC of MCC/ATS Plant Units | AD37: 1 | AF37: =SUMPRODUCT($K$17:$O$17,K37:O37) -> 0.69 | AG37: =SUMPRODUCT($Z$17:$AD$17,Z37:AD37) -> 1 | BP37: 36
B38: 21 | C38: Invoice Status | K38: 0 | L38: 0 | N38: 1 | Q38: 50 | R38: Qualified Subcontractor | AA38: 1 | AD38: 0 | AF38: =SUMPRODUCT($K$17:$O$17,K38:O38) -> 0.69 | AG38: =SUMPRODUCT($Z$17:$AD$17,Z38:AD38) -> 0.89 | BP38: 37
B39: 22 | C39: Site Handover Letter | K39: 1 | O39: 0 | Q39: 51 | R39: Scaffold/Ladders/Slope/Bridge Compliance | AD39: 1 | AF39: =SUMPRODUCT($K$17:$O$17,K39:O39) -> 1 | AG39: =SUMPRODUCT($Z$17:$AD$17,Z39:AD39) -> 1 | BP39: 38
B40: 23 | C40: Material Testing Results & Certification | L40: 0 | N40: 1 | Q40: 52 | R40: Protection Applied to Completed Work | AA40: 0 | AC40: 0 | AD40: 1 | AF40: =SUMPRODUCT($K$17:$O$17,K40:O40) -> 0.69 | AG40: =SUMPRODUCT($Z$17:$AD$17,Z40:AD40) -> 1
B41: 24 | C41: As Build Drawings Status* | N41: 0 | O41: 1 | Q41: 53 | R41: Storage Management in/out Control | AA41: 0 | AD41: 1 | AF41: =SUMPRODUCT($K$17:$O$17,K41:O41) -> 1 | AG41: =SUMPRODUCT($Z$17:$AD$17,Z41:AD41) -> 1
B42: 25 | C42: Calibrated Lab Tools & Equipment | L42: 1 | O42: 0 | Q42: 54 | R42: Material Control | AA42: 1 | AD42: 0 | AF42: =SUMPRODUCT($K$17:$O$17,K42:O42) -> 0.89 | AG42: =SUMPRODUCT($Z$17:$AD$17,Z42:AD42) -> 0.89
B43: 26 | C43: Storage Inventory System | L43: 1 | O43: 0 | Q43: 55 | R43: Manholes Storing and Quality | AD43: 1 | AF43: =SUMPRODUCT($K$17:$O$17,K43:O43) -> 0.89 | AG43: =SUMPRODUCT($Z$17:$AD$17,Z43:AD43) -> 1
B44: 27 | C44: Logistics Plan | L44: 1 | O44: 0 | Q44: 56 | R44: Reinforced Steel Quality | AB44: 0 | AC44: 0 | AD44: 1 | AF44: =SUMPRODUCT($K$17:$O$17,K44:O44) -> 0.89 | AG44: =SUMPRODUCT($Z$17:$AD$17,Z44:AD44) -> 1
B45: 28 | C45: Project Progress Planview | M45: 1 | O45: 0 | Q45: 57 | R45: Safety Overview | Z45: 0 | AA45: 1 | AF45: =SUMPRODUCT($K$17:$O$17,K45:O45) -> 0.79 | AG45: =SUMPRODUCT($Z$17:$AD$17,Z45:AD45) -> 0.89
B46: 29 | C46: Sufficient Number of QC Inspectors | L46: 0 | M46: 1 | O46: 0 | Q46: 58 | R46: Waste Management Control | Z46: 0 | AA46: 1 | AB46: 0 | AD46: 0 | AF46: =SUMPRODUCT($K$17:$O$17,K46:O46) -> 0.79 | AG46: =SUMPRODUCT($Z$17:$AD$17,Z46:AD46) -> 0.89
O47: 0
I48: Score
M49: *QC % | Q49: =AF17 -> 0.88724138
B51: Prepared by: | G51: Sarvar Ahmad | Q51: Issued to PM: | V51: Engr.Zyad Al Shabat
B53: *QC Observations refer only to the practices and documentation observed at time of inspection. The responsibility of the CM and Contractor is to ensure that aspects of Quality are suitably managed. *Scores are a reflection of the general site conditions based upon the findings at the time of the walk through *If Applicable

Sheet HSE-Stat
A1: Safety Statistics
A3: Category | B3: Item | D3: This Week | E3: This Month | F3: Year to Date | G3: Cumulative
A4: Category | B4: Total Hours Worked | D4: 4280 | E4: 9540 | F4: 77050 | G4: 77050
B5: Safe Hours Worked | D5: 4280 | E5: 9540 | F5: 77050 | G5: 77050
B6: No.of Internal Training | D6: 1 | E6: 3 | F6: 22 | G6: 22
B7: No.of Internal Audit
B8: No. of Toolbox Talks | D8: 1 | E8: 3 | F8: 20 | G8: 20
B9: Safety Awards/Incentives
I10: Category | J10: Item | L10: This Week | M10: This Month | N10: Year to Date | O10: Cumulative
A12: Consultant Safety Inspection (Weekly Basis) | I12: Overall Average | J12: 0.8333
A13: Week Number | B13: Date of Audit | C13: Date Issued | D13: Numbers Of Comments | E13: Overall Score | F13: Date Closed | G13: Closure Duration | I13: This Week Score | J13: =E30 -> 0.83333333
A14: Week-1 | D14: 0 | E14: 0.76 | G14: 0
A15: Week-2 | D15: 0 | E15: 0.76 | G15: 0
A16: Week-3 | D16: 0 | E16: =HSE.!AE6 -> 0.83333333 | G16: 0
A17: Week-4 | D17: 0 | E17: 0.77 | G17: 0
A18: Week-5 | D18: 0 | E18: =HSE.!AE6 -> 0.83333333 | G18: 0
A19: Week-6 | D19: 0 | E19: =HSE.!AE6 -> 0.83333333 | G19: 0
A20: Week-7 | D20: 0 | E20: =E19 -> 0.83333333 | G20: 0
A21: Week-8 | D21: 0 | E21: =E20 -> 0.83333333 | G21: 0
A22: Week-9 | D22: 0 | E22: =E21 -> 0.83333333 | G22: 0
A23: Week-10 | B23: 46251 | C23: 46251 | D23: 0 | E23: =E22 -> 0.83333333 | F23: 46251 | G23: 0
A24: Week-11 | B24: 46258 | C24: 46258 | D24: 0 | E24: =E23 -> 0.83333333 | F24: 46258 | G24: 0
A25: Week-12 | B25: 46265 | C25: 46265 | D25: 0 | E25: =E24 -> 0.83333333 | F25: 46265 | G25: 0
A26: Week-13 | B26: 46272 | C26: 46272 | D26: 0 | E26: =E25 -> 0.83333333 | F26: 46272 | G26: 0
A27: Week-14 | B27: 46279 | C27: 46279 | D27: 0 | E27: =E26 -> 0.83333333 | F27: 46279 | G27: 0
A28: Week-15 | B28: 46286 | C28: 46286 | D28: 0 | E28: =E27 -> 0.83333333 | F28: 46286 | G28: 0
A29: Week-16 | B29: 46293 | C29: 46293 | D29: 0 | E29: =E28 -> 0.83333333 | F29: 46293 | G29: 0
A30: Week-17 | B30: 46300 | C30: 46300 | D30: 0 | E30: =E29 -> 0.83333333 | F30: 46300 | G30: 0
A31: Week-18 | B31: 46307 | C31: 46307 | D31: 0 | E31: 0.83 | F31: 46307 | G31: 0
A32: Week-19 | B32: 46314 | C32: 46314 | D32: 0 | E32: 0.83 | F32: 46314 | G32: 0
A33: Week-20 | D33: 0 | E33: 0 | G33: 0
A34: Week-21 | D34: 0 | E34: 0 | G34: 0
A35: Week-22 | D35: 0 | E35: 0 | G35: 0
A36: Week-23 | D36: 0 | E36: 0 | G36: 0
A37: Week-24 | D37: 0 | E37: 0 | G37: 0
A38: Week-25 | D38: 0 | E38: 0 | G38: 0
A39: Week-26 | D39: 0 | E39: 0 | G39: 0
A40: Week-27 | D40: 0 | E40: 0 | G40: 0
A41: Week-28 | D41: 0 | E41: 0 | G41: 0
A42: Week-29 | D42: 0 | E42: 0 | G42: 0

Sheet HSE.
B1: MODON HSE Site Inspection Report
B2: Date | E2: ='General Information'!L1 -> 46314 | L2: Inspected By: | T2: Engr Ayman Sabry
B4: Project ID. | E4: SUD1-02-011 | L4: Report No. | W4: MODON PM Name | Y4: Engr.Ziyad Al Shabbat
B6: Project Name: | E6: Construction of Passenger Station for SAR Railway Sudair Industrial City | L6: Contractor: | R6: TECHNICAL DEVELOPMENT CONTRACTING CO. | X6: Safety Performance | AA6: =IF(W29>0,3,IF(L29>6,2,IF(D29>0,2,1)*1)*1) -> 2 | AE6: =(((COUNTIF(L13:Q25,"1")+COUNTIF(AC13:AH25,"1"))*AR13)+(COUNTIF(L13:Q25,"2")+COUNTIF(AC13:AH25,"2"))*AR14+(COUNTIF(L13:Q25,"3")+COUNTIF(AC13:AH25,"3"))*AR15)/((COUNT(L13:Q25)+COUNT(AC13:AH25))*100) -> 0.83333333
B8: Inspections are a snapshot in time and refer only to the practices and documentation observed at the time of the Inspection. It remains the responsibility of the Consultant and Contractor to ensure that all aspects of Health & Safety are suitably managed.
B9: 1 | D9: Good Practice | H9: 2 | I9: Need Improvement | T9: 3 | U9: Fail (Life Threatening Activity) / Comliance with Plan & Procedures | X9: N/A | Y9: Atcitty Not Applicable for this Site Inspection Report
B11: No. | C11: Topic | K11: Wt. | L11: HSE Compliance | S11: No. | T11: Topic | AB11: Wt. | AC11: HSE Compliance
B13: 1 | C13: Access and Egress - (General access to site, segregated from vehicles, / Overhead protection, while entering into the building /Adequate lighting provided when dark or overnight work) | K13: 0.05 | L13: 2 | S13: 14 | T13: Work at Height - (PPE/Fall Protection(Same level, above and blow) / Training / Fall restraint / competency /Safe access & egress to and from work at height / Ladders / Openings (floor/shafts/Provision of emergency rescue) | AB13: 0.05 | AC13: N/A | AP13: 1 | AR13: 100 | AU13: 1
B14: 2 | C14: Traffic Management - (Loading/unloading/sheeting/temp. routes/speed/parking/competence) | K14: 0.03 | L14: 2 | S14: 15 | T14: Scaffolding - (Temp. Scaffolding Work-platform (All types) - qualified scaffolder / Inspection / Tagged / Safe Access/egress / PTW/Falsework & Formwork) | AB14: 0.04 | AC14: N/A | AP14: 2 | AR14: 75 | AU14: 2
B15: 3 | C15: Site Signage - (Project Notice Board & General Signage) | K15: 0.02 | L15: 2 | S15: 16 | T15: Mobile Elevated Work platform (MEWP) - (PTW/competence requirements/conditions/inspections/tagged/training/Full-body harness) | AB15: 0.04 | AC15: N/A | AP15: 3 | AR15: 0 | AU15: 3
B16: 4 | C16: PPE Compliance - (Use, storage, stock, handling & checks - Head, Foot, Eye, Hearing) | K16: 0.05 | L16: 2 | S16: 17 | T16: Excavation & Trenches - (PTW/Edge protection/buffer zone/Slope/Benching/Shoring/Geo-tech report/Atmospheric hazards/Acess&egress/Emergency management / MS&RA/H.E) | AB16: 0.03 | AC16: 2 | AU16: N/A
B17: 5 | C17: Housekeeping - (Material correctly stored/Rubbish cleaned & removed daily/slips & trips hazards) | K17: 0.03 | L17: 2 | S17: 18 | T17: Confined Space - (PTW/Training/competence/Emergency Management/MS & RA/Safe access/egress) | AB17: 0.05 | AC17: N/A
B18: 6 | C18: Storage of Materials - (Transporting, storage, training and use - Combustible / Flammable / Hazardous substances (COSHH) | L18: 1 | S18: 19 | T18: Fire Protection - (Flammable/Oxy. LPG /Combustible separated/FE's/Flashback arrestor/Sparks & slags/Smoking area/PTW/Generators/MS & RA/Emergency Management) | AC18: 1 | AL18: Red | AM18: Serious injury or death (immediately)
B19: 7 | C19: Site Waste Management - (Hazardous waste /Combustible waste / Human waste / Construction waste - asphalt, cable, timber, paving roof sheeting tiles, plastic & bricks) | L19: 1 | S19: 20 | T19: Health & Welfare - (Adequate drinking water/shaded - eating & rest area/washing & sanitary facilities/Certified FA/FA Box & Stock/adequate toilets/Ambulance) | AC19: 2 | AL19: Yellow | AM19: Minor or near miss (3 days to comply)
B20: 8 | C20: Health Surveillance - (Expose to excessive noise/vibration/dust/silica/CO/cement/radiation/extreme weather condition) | K20: 0.03 | L20: 2 | S20: 21 | T20: Environmental Incident Measures - (Spill/ Leakage / Concrete wash / vehicle & eqpts. wash / waste disposal/Sewers and drains/emissions/Emergency Management/Training/site run-off water) | AB20: 0.05 | AC20: 2 | AL20: Green | AM20: No issues
B21: 9 | C21: Electrical Safety - (Electrical qualified /RCD/GFCI/Industrial Cocket/LOTO/Cable-overhung or buried/Cords in good condition/current inspection tag) | K21: 0.05 | L21: 2 | S21: 22 | T21: HSE Communications & Meetings - (Schedule HSE Meetings/Safety Committee meetings/Alerts / Lesson learned/Safety Bulletin contains latest HSE KPI) | AB21: 0.05 | AC21: 2
B22: 10 | C22: Tools & Equipment - (Includes, powered, hydraulic & pneumatic/Guards in place/Properly stored/RCD Protection/Earthed/Good condition & tagged) | K22: 0.03 | L22: 1 | S22: 23 | T22: HSE Plan & Associated Procedures - (Approved updated HSE Plan/ CEMP/HAZComm/Procedures/Standards/Project Safety Risk Register) | AB22: 0.03 | AC22: 1 | AL22: 26 points > 4 minors then is it’s a serious issue
B23: 11 | C23: Manual Handling - (Lifting/loading/pulling/pushing/twisting/awkward posture/repetitive task/frequent and prolong physical effort/Reasonable practicable use of mechanical aid) | K23: 0.03 | L23: 2 | S23: 24 | T23: Health, Safety & Environment Incident reporting - (Review of HSE Statistics, Reporting of Unsafe Act & Conditions/ Reporting of Near Miss incident/Reporting of FA cases/Record MT cases) | AB23: 0.03 | AC23: 1
B24: 12 | C24: Vehicle and mobile equipment / Plant - (dumpers; excavators, cranes, piling rigs, grader, roller, loaders/condition/KSA License/certification) | K24: 0.05 | L24: 2 | S24: 25 | T24: HSE Awareness, Training & Competence - (Policy /Objective & targets/Information, training/Climatic condition awareness/Reponses in emergency situation/ Safety Behavior Observation) | AB24: 0.04 | AC24: 2
B25: 13 | C25: Lifting Operations & Rigging - (Lifting Plan/Lifting devices & gears/PTW/Condition/3rd party certification/bank-man/rigger/slingers/man-basket/inspection record/tagged) | L25: N/A | S25: 26 | T25: Project Leadership Site Tours - (Provide evidence of proactive safety performance/Deficient discovered discussed/Positive feedback/Workers resolving safety issues) | AC25: 1
B27: Prepared by: | G27: Abdul kalim | S27: Sent to MODON PM: | X27: Engr.Ziyad Al Shabbat
B28: Safety Results
B29: 1 | D29: =COUNTIF(L13:Q26,"1")+COUNTIF(AB13:AG26,"1") -> 7 | I29: 2 | L29: =COUNTIF(L13:Q26,"2")+COUNTIF(AB13:AG26,"2") -> 14 | U29: 3 | W29: =COUNTIF(L13:Q26,"3")+COUNTIF(AB13:AG26,"3") -> 0

Sheet Major Quantities
A1: MAJOR QUANTITIES
A2: BOQ Number | B2: Description of Item | C2: Total Quantity | D2: Unit of Measurement | E2: Plan To Date | F2: Actual To Date | G2: Excecuted on site | H2: Remaining Total | I2: Variance
A3: B1.32 11 13.01 | B3: Subgrade | C3: 20530 | D3: m3 | F3: 15000 | G3: 15000 | H3: =C3-F3 -> 5530
A4: B1.32 11 23.01 | B4: Aggregate base course | C4: 16375.94 | D4: m3 | F4: 9875.94 | G4: 4625 | H4: =C4-F4 -> 6500
A5: B4.33 31 23.01 | B5: HDPE pipe | C5: 5808 | D5: m | F5: 5808 | H5: =C5-F5 -> 0 | I5: =E5-H5 -> 0
A6: B1.32 12 16.01 | B6: Asphalt | C6: 13360 | D6: m3 | F6: 573 | G6: 573 | H6: =C6-F6 -> 12787
A7: B1.32 14 13.13.01 | B7: Interlock | C7: 27900 | D7: m2 | F7: 0 | H7: =C7-F7 -> 27900
A8: B1.32 16 13.23.01 | B8: Curbstone | C8: 20555 | D8: m2 | F8: 0 | H8: =C8-F8 -> 20555
A9: B2.31 23 00.01 | B9: Medium Voltage cables | C9: 7120 | D9: m | F9: 0 | H9: =C9-F9 -> 7120
A10: B2.33 71 00 02.01 | B10: Low Voltage Cables, Copper & Aluminum, | C10: 7500 | D10: m | F10: 7500 | H10: =C10-F10 -> 0
A11: 31 00 00 | B11: Canopy | C11: 4000 | D11: m | F11: 0 | H11: =C11-F11 -> 4000
A12: 03 00 00 | B12: Platform | C12: 4000 | D12: m2 | F12: 0 | H12: =C12-F12 -> 4000
A13: B4.05 52 00.01 | B13: Metal Handrail | C13: 440 | D13: m | F13: 0 | H13: =C13-F13 -> 440
A14: B2.26 56 19.01 | B14: Lighting Luminaire | C14: 116 | D14: Unit | F14: 0 | H14: =C14-F14 -> 116

Sheet Invoice Log
B1: Weekly Progress Report - Invoice Log | AK1: Y
B2: Project Value | L2: Payment Status | T2: Invoices Summary | AD2: Average Invoices durations | AK2: N
B3: Original Contract Value | F3: 33090825 | H3: O&M Value | J3: 0 | L3: Advance Payment % | N3: 0 | P3: Advance Payment (SAR) | R3: =F3*N3 -> 0 | T3: No of Submitted Invoices | V3: =MAX($C$9:$C$39) -> 2 | X3: Submitted Invoices (SAR) | Z3: =SUM(F9:F39) -> 3048399.3 | AB3: Submiited Invoice Peroid | AD3: CM / PgM Average Approval duration | AF3: 0 | AH3: Average Invoice Value | AI3: 0
B4: Revised Contract Value | F4: 0 | H4: Revised O&M Value | J4: 0 | L4: Retention % | N4: 0 | P4: Retention (SAR) | R4: =F3*N4 -> 0 | T4: No of Approved Invoices (CM) | V4: =COUNTIF($O$9:$O$52,"Y") -> 0 | X4: Approved Invoices (CM) (SAR) | Z4: =SUMIF($O$9:$O$39,"Y",$K$9:$K$39) -> 0 | AD4: MODON PM & Accounts Average Approval duration | AF4: 0
B5: Estimate At Completion Value | F5: 33090825 | H5: Submitted Invoices (Gross Value) | J5: =SUM(F9:F51) -> 3048399.3 | L5: Penalties and deduction % | N5: =J6/F3 -> -6.0439714e-05 | P5: AP Recovery (SAR) | R5: =SUM(G9:G51) -> 0 | T5: No of Approved Invoices (PM) | V5: =COUNTIF($S$9:$S$52,"Y") -> 0 | X5: Approved Invoices (PM) (SAR) | Z5: =SUMIF($S$9:$S$39,"Y",$K$9:$K$39) -> 0 | AB5: Invoice Submitted Compared to Contract Value | AC5: =Z3/F4 -> #DIV/0! | AD5: Payments Average Duration | AF5: 0
B6: Potential Changes | F6: 0 | H6: Total Deduction | J6: =J9+G9 -> -2000 | L6: Penalties and deduction (SAR) | N6: =SUM(J9:J51) -> -2000 | P6: Retention Cumulative (SAR) | R6: =SUM(H9:H51) -> 0 | T6: No of Paid Invoices | V6: =COUNTA(Y9:Y52) -> 0 | X6: Paid Invoices (SAR) | Z6: =SUM(Z9:Z39) -> 0 | AD6: Invoices Average total Duration | AF6: =IFERROR(AVERAGE(AD9:AD52),"")
B7: Invoice Reference | F7: Invoice Value | K7: Period Covered | N7: CM / PgM Approval Timeline | R7: Modon PM & Accounts Approval | Y7: Payment Status | AD7: Total Invoice Duration | AE7: Remarks
B8: # | C8: Invoice No. | D8: Doc Control reference | E8: Submittal Rev. # | F8: Gross Value | G8: AP Recovery | H8: Retention | I8: VAT 5%/15% | J8: Deduction / Penalties | K8: Amount (net) | L8: Start Date | M8: End Date | N8: Date to CM / PgM | O8: CM / PgM Approval (Yes/No) | P8: CM / PgM Reply Date | Q8: Days Elapsed | R8: Date to PM | S8: PM Approval (Yes/No) | T8: PM Reply Date | U8: Date to Accounts | V8: Accounts Approval (Yes/No) | W8: Accounts Approval Date | X8: Days Elapsed | Y8: Date Paid | Z8: Amount Paid | AA8: Paid % | AB8: Payment Period (d) | AC8: Amount Pending
B9: 1 | C9: 1 | D9: SUD1-05-018-TDC-TS9-1-IPC-0001-00 | E9: 0 | F9: 2573925.6 | G9: =IF(ISBLANK(F9),"",-F9*$N$3) -> 0 | I9: 386088.84 | J9: -2000 | K9: =IF(ISBLANK(F9),"",SUM(F9:J9)) -> 2958014.4 | L9: 46119 | M9: 46221 | Z9: =IF(ISBLANK(Y9),"",K9) | AA9: =IF(ISBLANK(Y9),"",Z9/K9) | AB9: =IF(ISBLANK(W9),"",Y9-W9) | AC9: =IF(ISBLANK(Y9),"",(K9-Z9)) | AD9: =IF(ISBLANK(Y9),"",Y9-N9)
B10: 9 | C10: 2 | D10: SUD1-05-018-TDC-TS9-1-IPC-0002-00 | F10: 474473.73 | I10: 71171.06 | J10: 0 | K10: =IF(ISBLANK(F10),"",SUM(F10:J10)) -> 545644.79 | L10: 46222 | M10: 46264 | Q10: =IF(ISBLANK(P10),"",P10-N10) | X10: =IF(ISBLANK(W10),"",W10-R10) | Z10: =IF(ISBLANK(Y10),"",K10) | AA10: =IF(ISBLANK(Y10),"",Z10/K10) | AB10: =IF(ISBLANK(W10),"",Y10-W10) | AC10: =IF(ISBLANK(Y10),"",(K10-Z10)) | AD10: =IF(ISBLANK(Y10),"",Y10-N10)
B11: 10 | K11: =IF(ISBLANK(F11),"",SUM(F11:J11)) | Q11: =IF(ISBLANK(P11),"",P11-N11) | X11: =IF(ISBLANK(W11),"",W11-R11) | Z11: =IF(ISBLANK(Y11),"",K11) | AA11: =IF(ISBLANK(Y11),"",Z11/K11) | AB11: =IF(ISBLANK(W11),"",Y11-W11) | AC11: =IF(ISBLANK(Y11),"",(K11-Z11)) | AD11: =IF(ISBLANK(Y11),"",Y11-N11)
B12: 11 | K12: =IF(ISBLANK(F12),"",SUM(F12:J12)) | Q12: =IF(ISBLANK(P12),"",P12-N12) | X12: =IF(ISBLANK(W12),"",W12-R12) | Z12: =IF(ISBLANK(Y12),"",K12) | AA12: =IF(ISBLANK(Y12),"",Z12/K12) | AB12: =IF(ISBLANK(W12),"",Y12-W12) | AC12: =IF(ISBLANK(Y12),"",(K12-Z12)) | AD12: =IF(ISBLANK(Y12),"",Y12-N12)
B13: 12 | K13: =IF(ISBLANK(F13),"",SUM(F13:J13)) | Q13: =IF(ISBLANK(P13),"",P13-N13) | X13: =IF(ISBLANK(W13),"",W13-R13) | Z13: =IF(ISBLANK(Y13),"",K13) | AA13: =IF(ISBLANK(Y13),"",Z13/K13) | AB13: =IF(ISBLANK(W13),"",Y13-W13) | AC13: =IF(ISBLANK(Y13),"",(K13-Z13)) | AD13: =IF(ISBLANK(Y13),"",Y13-N13)
B14: 13 | K14: =IF(ISBLANK(F14),"",SUM(F14:J14)) | Q14: =IF(ISBLANK(P14),"",P14-N14) | X14: =IF(ISBLANK(W14),"",W14-R14) | Z14: =IF(ISBLANK(Y14),"",K14) | AA14: =IF(ISBLANK(Y14),"",Z14/K14) | AB14: =IF(ISBLANK(W14),"",Y14-W14) | AC14: =IF(ISBLANK(Y14),"",(K14-Z14)) | AD14: =IF(ISBLANK(Y14),"",Y14-N14)
B15: 14 | K15: =IF(ISBLANK(F15),"",SUM(F15:J15)) | Q15: =IF(ISBLANK(P15),"",P15-N15) | X15: =IF(ISBLANK(W15),"",W15-R15) | Z15: =IF(ISBLANK(Y15),"",K15) | AA15: =IF(ISBLANK(Y15),"",Z15/K15) | AB15: =IF(ISBLANK(W15),"",Y15-W15) | AC15: =IF(ISBLANK(Y15),"",(K15-Z15)) | AD15: =IF(ISBLANK(Y15),"",Y15-N15)
B16: 15 | K16: =IF(ISBLANK(F16),"",SUM(F16:J16)) | Q16: =IF(ISBLANK(P16),"",P16-N16) | X16: =IF(ISBLANK(W16),"",W16-R16) | Z16: =IF(ISBLANK(Y16),"",K16) | AA16: =IF(ISBLANK(Y16),"",Z16/K16) | AB16: =IF(ISBLANK(W16),"",Y16-W16) | AC16: =IF(ISBLANK(Y16),"",(K16-Z16)) | AD16: =IF(ISBLANK(Y16),"",Y16-N16)
B17: 16 | K17: =IF(ISBLANK(F17),"",SUM(F17:J17)) | Q17: =IF(ISBLANK(P17),"",P17-N17) | X17: =IF(ISBLANK(W17),"",W17-R17) | Z17: =IF(ISBLANK(Y17),"",K17) | AA17: =IF(ISBLANK(Y17),"",Z17/K17) | AB17: =IF(ISBLANK(W17),"",Y17-W17) | AC17: =IF(ISBLANK(Y17),"",(K17-Z17)) | AD17: =IF(ISBLANK(Y17),"",Y17-N17)
B18: 17 | K18: =IF(ISBLANK(F18),"",SUM(F18:J18)) | Q18: =IF(ISBLANK(P18),"",P18-N18) | X18: =IF(ISBLANK(W18),"",W18-R18) | Z18: =IF(ISBLANK(Y18),"",K18) | AA18: =IF(ISBLANK(Y18),"",Z18/K18) | AB18: =IF(ISBLANK(W18),"",Y18-W18) | AC18: =IF(ISBLANK(Y18),"",(K18-Z18)) | AD18: =IF(ISBLANK(Y18),"",Y18-N18)
B19: 18 | K19: =IF(ISBLANK(F19),"",SUM(F19:J19)) | Q19: =IF(ISBLANK(P19),"",P19-N19) | X19: =IF(ISBLANK(W19),"",W19-R19) | Z19: =IF(ISBLANK(Y19),"",K19) | AA19: =IF(ISBLANK(Y19),"",Z19/K19) | AB19: =IF(ISBLANK(W19),"",Y19-W19) | AC19: =IF(ISBLANK(Y19),"",(K19-Z19)) | AD19: =IF(ISBLANK(Y19),"",Y19-N19)
B20: 19 | K20: =IF(ISBLANK(F20),"",SUM(F20:J20)) | Q20: =IF(ISBLANK(P20),"",P20-N20) | X20: =IF(ISBLANK(W20),"",W20-R20) | Z20: =IF(ISBLANK(Y20),"",K20) | AA20: =IF(ISBLANK(Y20),"",Z20/K20) | AB20: =IF(ISBLANK(W20),"",Y20-W20) | AC20: =IF(ISBLANK(Y20),"",(K20-Z20))
B21: 20 | G21: =IF(ISBLANK(F21),"",-F21*$N$3) | H21: =IF(ISBLANK(F21),"",-F21*$N$4) | K21: =IF(ISBLANK(F21),"",SUM(F21:J21)) | Q21: =IF(ISBLANK(P21),"",P21-N21) | X21: =IF(ISBLANK(W21),"",W21-R21) | Z21: =IF(ISBLANK(Y21),"",K21) | AA21: =IF(ISBLANK(Y21),"",Z21/K21) | AB21: =IF(ISBLANK(W21),"",Y21-W21) | AC21: =IF(ISBLANK(Y21),"",(K21-Z21)) | AD21: =IF(ISBLANK(Y21),"",Y21-N21)
B22: 21 | G22: =IF(ISBLANK(F22),"",-F22*$N$3) | H22: =IF(ISBLANK(F22),"",-F22*$N$4) | K22: =IF(ISBLANK(F22),"",SUM(F22:J22)) | Q22: =IF(ISBLANK(P22),"",P22-N22) | X22: =IF(ISBLANK(W22),"",W22-R22) | Z22: =IF(ISBLANK(Y22),"",K22) | AA22: =IF(ISBLANK(Y22),"",Z22/K22) | AB22: =IF(ISBLANK(W22),"",Y22-W22) | AC22: =IF(ISBLANK(Y22),"",(K22-Z22)) | AD22: =IF(ISBLANK(Y22),"",Y22-N22)
B23: 22 | G23: =IF(ISBLANK(F23),"",-F23*$N$3) | H23: =IF(ISBLANK(F23),"",-F23*$N$4) | K23: =IF(ISBLANK(F23),"",SUM(F23:J23)) | Q23: =IF(ISBLANK(P23),"",P23-N23) | X23: =IF(ISBLANK(W23),"",W23-R23) | Z23: =IF(ISBLANK(Y23),"",K23) | AA23: =IF(ISBLANK(Y23),"",Z23/K23) | AB23: =IF(ISBLANK(W23),"",Y23-W23) | AC23: =IF(ISBLANK(Y23),"",(K23-Z23)) | AD23: =IF(ISBLANK(Y23),"",Y23-N23)
B24: 23 | G24: =IF(ISBLANK(F24),"",-F24*$N$3) | H24: =IF(ISBLANK(F24),"",-F24*$N$4) | K24: =IF(ISBLANK(F24),"",SUM(F24:J24)) | Q24: =IF(ISBLANK(P24),"",P24-N24) | X24: =IF(ISBLANK(W24),"",W24-R24) | Z24: =IF(ISBLANK(Y24),"",K24) | AA24: =IF(ISBLANK(Y24),"",Z24/K24) | AB24: =IF(ISBLANK(W24),"",Y24-W24) | AC24: =IF(ISBLANK(Y24),"",(K24-Z24)) | AD24: =IF(ISBLANK(Y24),"",Y24-N24)
B25: 24 | G25: =IF(ISBLANK(F25),"",-F25*$N$3) | H25: =IF(ISBLANK(F25),"",-F25*$N$4) | K25: =IF(ISBLANK(F25),"",SUM(F25:J25)) | Q25: =IF(ISBLANK(P25),"",P25-N25) | X25: =IF(ISBLANK(W25),"",W25-R25) | Z25: =IF(ISBLANK(Y25),"",K25) | AA25: =IF(ISBLANK(Y25),"",Z25/K25) | AB25: =IF(ISBLANK(W25),"",Y25-W25) | AC25: =IF(ISBLANK(Y25),"",(K25-Z25)) | AD25: =IF(ISBLANK(Y25),"",Y25-N25)
B26: 25 | G26: =IF(ISBLANK(F26),"",-F26*$N$3) | H26: =IF(ISBLANK(F26),"",-F26*$N$4) | K26: =IF(ISBLANK(F26),"",SUM(F26:J26)) | Q26: =IF(ISBLANK(P26),"",P26-N26) | X26: =IF(ISBLANK(W26),"",W26-R26) | Z26: =IF(ISBLANK(Y26),"",K26) | AA26: =IF(ISBLANK(Y26),"",Z26/K26) | AB26: =IF(ISBLANK(W26),"",Y26-W26) | AC26: =IF(ISBLANK(Y26),"",(K26-Z26)) | AD26: =IF(ISBLANK(Y26),"",Y26-N26)
B27: 26 | G27: =IF(ISBLANK(F27),"",-F27*$N$3) | H27: =IF(ISBLANK(F27),"",-F27*$N$4) | K27: =IF(ISBLANK(F27),"",SUM(F27:J27)) | Q27: =IF(ISBLANK(P27),"",P27-N27) | X27: =IF(ISBLANK(W27),"",W27-R27) | Z27: =IF(ISBLANK(Y27),"",K27) | AA27: =IF(ISBLANK(Y27),"",Z27/K27) | AB27: =IF(ISBLANK(W27),"",Y27-W27) | AC27: =IF(ISBLANK(Y27),"",(K27-Z27)) | AD27: =IF(ISBLANK(Y27),"",Y27-N27)
B28: 27 | G28: =IF(ISBLANK(F28),"",-F28*$N$3) | H28: =IF(ISBLANK(F28),"",-F28*$N$4) | K28: =IF(ISBLANK(F28),"",SUM(F28:J28)) | Q28: =IF(ISBLANK(P28),"",P28-N28) | X28: =IF(ISBLANK(W28),"",W28-R28) | Z28: =IF(ISBLANK(Y28),"",K28) | AA28: =IF(ISBLANK(Y28),"",Z28/K28) | AB28: =IF(ISBLANK(W28),"",Y28-W28) | AC28: =IF(ISBLANK(Y28),"",(K28-Z28)) | AD28: =IF(ISBLANK(Y28),"",Y28-N28)
B29: 28 | G29: =IF(ISBLANK(F29),"",-F29*$N$3) | H29: =IF(ISBLANK(F29),"",-F29*$N$4) | K29: =IF(ISBLANK(F29),"",SUM(F29:J29)) | Q29: =IF(ISBLANK(P29),"",P29-N29) | X29: =IF(ISBLANK(W29),"",W29-R29) | Z29: =IF(ISBLANK(Y29),"",K29) | AA29: =IF(ISBLANK(Y29),"",Z29/K29) | AB29: =IF(ISBLANK(W29),"",Y29-W29) | AC29: =IF(ISBLANK(Y29),"",(K29-Z29)) | AD29: =IF(ISBLANK(Y29),"",Y29-N29)
B30: 29 | G30: =IF(ISBLANK(F30),"",-F30*$N$3) | H30: =IF(ISBLANK(F30),"",-F30*$N$4) | K30: =IF(ISBLANK(F30),"",SUM(F30:J30)) | Q30: =IF(ISBLANK(P30),"",P30-N30) | X30: =IF(ISBLANK(W30),"",W30-R30) | Z30: =IF(ISBLANK(Y30),"",K30) | AA30: =IF(ISBLANK(Y30),"",Z30/K30) | AB30: =IF(ISBLANK(W30),"",Y30-W30) | AC30: =IF(ISBLANK(Y30),"",(K30-Z30)) | AD30: =IF(ISBLANK(Y30),"",Y30-N30)
B31: 30 | G31: =IF(ISBLANK(F31),"",-F31*$N$3) | H31: =IF(ISBLANK(F31),"",-F31*$N$4) | K31: =IF(ISBLANK(F31),"",SUM(F31:J31)) | Q31: =IF(ISBLANK(P31),"",P31-N31) | X31: =IF(ISBLANK(W31),"",W31-R31) | Z31: =IF(ISBLANK(Y31),"",K31) | AA31: =IF(ISBLANK(Y31),"",Z31/K31) | AB31: =IF(ISBLANK(W31),"",Y31-W31) | AC31: =IF(ISBLANK(Y31),"",(K31-Z31)) | AD31: =IF(ISBLANK(Y31),"",Y31-N31)
B32: 31 | G32: =IF(ISBLANK(F32),"",-F32*$N$3) | H32: =IF(ISBLANK(F32),"",-F32*$N$4) | K32: =IF(ISBLANK(F32),"",SUM(F32:J32)) | Q32: =IF(ISBLANK(P32),"",P32-N32) | X32: =IF(ISBLANK(W32),"",W32-R32) | Z32: =IF(ISBLANK(Y32),"",K32) | AA32: =IF(ISBLANK(Y32),"",Z32/K32) | AB32: =IF(ISBLANK(W32),"",Y32-W32) | AC32: =IF(ISBLANK(Y32),"",(K32-Z32)) | AD32: =IF(ISBLANK(Y32),"",Y32-N32)
... B39: 38 | G39: =IF(ISBLANK(F39),"",-F39*$N$3) | H39: =IF(ISBLANK(F39),"",-F39*$N$4) | K39: =IF(ISBLANK(F39),"",SUM(F39:J39)) | Q39: =IF(ISBLANK(P39),"",P39-N39) | X39: =IF(ISBLANK(W39),"",W39-R39) | Z39: =IF(ISBLANK(Y39),"",K39) | AA39: =IF(ISBLANK(Y39),"",Z39/K39) | AB39: =IF(ISBLANK(W39),"",Y39-W39) | AC39: =IF(ISBLANK(Y39),"",(K39-Z39)) | AD39: =IF(ISBLANK(Y39),"",Y39-N39)
B40: 39 | G40: =IF(ISBLANK(F40),"",-F40*$N$3) | H40: =IF(ISBLANK(F40),"",-F40*$N$4) | Z40: =IF(ISBLANK(Y40),"",K40) | AA40: =IF(ISBLANK(Y40),"",Z40/K40) | AB40: =IF(ISBLANK(W40),"",Y40-W40) | AC40: =IF(ISBLANK(Y40),"",(K40-Z40))
B41: 40 | G41: =IF(ISBLANK(F41),"",-F41*$N$3) | H41: =IF(ISBLANK(F41),"",-F41*$N$4) | Z41: =IF(ISBLANK(Y41),"",K41) | AA41: =IF(ISBLANK(Y41),"",Z41/K41) | AB41: =IF(ISBLANK(W41),"",Y41-W41) | AC41: =IF(ISBLANK(Y41),"",(K41-Z41))
B42: 41 | G42: =IF(ISBLANK(F42),"",-F42*$N$3) | H42: =IF(ISBLANK(F42),"",-F42*$N$4) | Z42: =IF(ISBLANK(Y42),"",K42) | AA42: =IF(ISBLANK(Y42),"",Z42/K42) | AB42: =IF(ISBLANK(W42),"",Y42-W42) | AC42: =IF(ISBLANK(Y42),"",(K42-Z42))
B43: 42 | G43: =IF(ISBLANK(F43),"",-F43*$N$3) | H43: =IF(ISBLANK(F43),"",-F43*$N$4) | Z43: =IF(ISBLANK(Y43),"",K43) | AA43: =IF(ISBLANK(Y43),"",Z43/K43) | AB43: =IF(ISBLANK(W43),"",Y43-W43) | AC43: =IF(ISBLANK(Y43),"",(K43-Z43))
B44: 43 | G44: =IF(ISBLANK(F44),"",-F44*$N$3) | H44: =IF(ISBLANK(F44),"",-F44*$N$4) | Z44: =IF(ISBLANK(Y44),"",K44) | AA44: =IF(ISBLANK(Y44),"",Z44/K44) | AB44: =IF(ISBLANK(W44),"",Y44-W44) | AC44: =IF(ISBLANK(Y44),"",(K44-Z44))
B45: 44 | G45: =IF(ISBLANK(F45),"",-F45*$N$3) | H45: =IF(ISBLANK(F45),"",-F45*$N$4) | Z45: =IF(ISBLANK(Y45),"",K45) | AA45: =IF(ISBLANK(Y45),"",Z45/K45) | AB45: =IF(ISBLANK(W45),"",Y45-W45) | AC45: =IF(ISBLANK(Y45),"",(K45-Z45))
B46: 45 | G46: =IF(ISBLANK(F46),"",-F46*$N$3) | H46: =IF(ISBLANK(F46),"",-F46*$N$4) | Z46: =IF(ISBLANK(Y46),"",K46) | AA46: =IF(ISBLANK(Y46),"",Z46/K46) | AB46: =IF(ISBLANK(W46),"",Y46-W46) | AC46: =IF(ISBLANK(Y46),"",(K46-Z46))
B47: 46 | G47: =IF(ISBLANK(F47),"",-F47*$N$3) | H47: =IF(ISBLANK(F47),"",-F47*$N$4) | Z47: =IF(ISBLANK(Y47),"",K47) | AA47: =IF(ISBLANK(Y47),"",Z47/K47) | AB47: =IF(ISBLANK(W47),"",Y47-W47) | AC47: =IF(ISBLANK(Y47),"",(K47-Z47))
B48: 47 | G48: =IF(ISBLANK(F48),"",-F48*$N$3) | H48: =IF(ISBLANK(F48),"",-F48*$N$4) | Z48: =IF(ISBLANK(Y48),"",K48) | AA48: =IF(ISBLANK(Y48),"",Z48/K48) | AB48: =IF(ISBLANK(W48),"",Y48-W48) | AC48: =IF(ISBLANK(Y48),"",(K48-Z48))
B49: 48 | G49: =IF(ISBLANK(F49),"",-F49*$N$3) | H49: =IF(ISBLANK(F49),"",-F49*$N$4) | Z49: =IF(ISBLANK(Y49),"",K49) | AA49: =IF(ISBLANK(Y49),"",Z49/K49) | AB49: =IF(ISBLANK(W49),"",Y49-W49) | AC49: =IF(ISBLANK(Y49),"",(K49-Z49))
B50: 49 | G50: =IF(ISBLANK(F50),"",-F50*$N$3) | H50: =IF(ISBLANK(F50),"",-F50*$N$4) | Z50: =IF(ISBLANK(Y50),"",K50) | AA50: =IF(ISBLANK(Y50),"",Z50/K50) | AB50: =IF(ISBLANK(W50),"",Y50-W50) | AC50: =IF(ISBLANK(Y50),"",(K50-Z50))
B51: 50 | G51: =IF(ISBLANK(F51),"",-F51*$N$3) | H51: =IF(ISBLANK(F51),"",-F51*$N$4) | Z51: =IF(ISBLANK(Y51),"",K51) | AA51: =IF(ISBLANK(Y51),"",Z51/K51) | AB51: =IF(ISBLANK(W51),"",Y51-W51) | AC51: =IF(ISBLANK(Y51),"",(K51-Z51))
E52: TOTAL | F52: =SUM(F9:F51) -> 3048399.3 | G52: =SUM(G9:G51) -> 0 | H52: =SUM(H9:H51) -> 0 | J52: =SUM(J9:J51) -> -2000 | K52: =SUM(K9:K51) -> 3503659.2 | Q52: =IF(ISBLANK(P52),"",P52-N52) | X52: =IF(ISBLANK(W52),"",W52-R52) | Z52: =SUM(Z9:Z51) -> 0 | AB52: =IF(ISBLANK(Y52),"",Y52-W52) | AC52: =SUM(AC9:AC51) -> 0 | AD52: =IF(ISBLANK(Y52),"",Y52-N52)

Sheet Invoice Amount FIR
A1: INVOICE AMOUNT FIR | E1: 33090825
A2: SL. | B2: date of FIR | C2: TOTAL AMOUNT | D2: Total Amount % (as per FIR)
A3: 1 | B3: 46225 | C3: 2573925.6 | D3: =C3/$E$1 -> 0.077783664
A4: 2 | B4: 46264 | C4: 474473.73 | D4: =C4/$E$1 -> 0.014338528
A5: 3
A6: 4
A7: 5
A8: 6
A9: 7
A10: 8
A11: 9
A12: 10
A13: 11
A14: 12
A15: 13
A16: 14
... A21: 19

Sheet FIR Summary
B2: Project Name | D2: Construction of Passenger Station for SAR Railway Sudair Industrial City
B3: Project ID | D3: SUD1-02-011 | F3: Project Budget | G3: ='Invoice Log'!F3 -> 33090825
B4: Date Pariod | D4: Start Date | E4: 46119 | F4: To | G4: Data Date | H4: ='General Information'!L1 -> 46314
A6: SL NO | B6: BOQ Item # | C6: BOQ Description | D6: Date | E6: FIR # | F6: FIR Description | G6: Unit Rate | H6: Current Pariod Quantity | I6: % Claim | J6: Unite rate as per claim | K6: Total (SR)
C7: Description | K7: =SUM(K8:K87) -> 3646338.7
A8: 1 | B8: B1 .31 23 23.01 | C8: Earth works & Embankment | D8: 46188 | E8: SUD1-05-018-TDC-TS9-1-ROD-FIR-0014-01 | F8: Check Coordinates level and Compaction F.D.T for Embankment 1st Layer for Station Road RD-01 , STA: 1+350 to STA: 1+700 | G8: 24 | H8: 5835.38 | I8: 1 | J8: =I8*G8 -> 24 | K8: =J8*H8 -> 140049.12
A9: 2 | B9: B1 .31 23 23.01 | C9: Earth works & Embankment | D9: 46214 | E9: SUD1-05-018-TDC-TS9-1-ROD-FIR-0015-00 | F9: Check Coordinates level and Compaction F.D.T for Embankment 5th layer for Station Road RD-01, STA: 0+850 to STA: 1+000 (Bottom subgrade) | G9: 24 | H9: 1733.54 | I9: 1 | J9: =I9*G9 -> 24 | K9: =J9*H9 -> 41604.96
A10: 3 | B10: B1 .31 23 23.01 | C10: Earth works & Embankment | D10: 46189 | E10: SUD1-05-018-TDC-TS9-1-ROD-FIR-0016-01 | F10: Check Coordinates level and Compaction F.D.T for Embankment 1st Layer for Station Road RD-01 , STA: 0+120 to STA: 0+500 | G10: 24 | H10: 5229.11 | I10: 1 | J10: =I10*G10 -> 24 | K10: =J10*H10 -> 125498.64
A11: 4 | B11: B1 .31 23 23.01 | C11: Earth works & Embankment | D11: 46188 | E11: SUD1-05-018-TDC-TS9-1-ROD-FIR-0018-00 | F11: Check Coordinates level and Compaction F.D.T for Embankment 1st Layer for Station Road RD-01 , STA: 0+500 to STA: 1+000 | G11: 24 | H11: 6588.4 | I11: 1 | J11: =I11*G11 -> 24 | K11: =J11*H11 -> 158121.6 | Z11: 0.08
A12: 5 | B12: B1 .31 23 23.01 | C12: Earth works & Embankment | D12: 46188 | E12: SUD1-05-018-TDC-TS9-1-ROD-FIR-0021-00 | F12: Check Coordinates level and Compaction F.D.T for Embankment 1st layer for Station Road RD-02, STA: 1+000 to STA:1+239.64 | G12: 24 | H12: 3557.97 | I12: 1 | J12: =I12*G12 -> 24 | K12: =J12*H12 -> 85391.28
A13: 6 | B13: B1 .31 23 23.01 | C13: Earth works & Embankment | D13: 46188 | E13: SUD1-05-018-TDC-TS9-1-ROD-FIR-0022-00 | F13: Check Coordinates level and Compaction F.D.T for Embankment 1st layer for Station Road RD-01, STA: 1+000 to STA:1+350 | G13: 24 | H13: 6159.64 | I13: 1 | J13: =I13*G13 -> 24 | K13: =J13*H13 -> 147831.36
A14: 7 | B14: B1.312323.01 | C14: Earth works & Embankment | D14: 46189 | E14: SUD1-05-018-TDC-TS9-1-ROD-FIR-0023-00 | F14: Check Coordinates level and Compaction F.D.T for Embankment 2nd layer for Station Road RD-01, STA: 1+350 to STA:1+530 | G14: 24 | H14: 2536.83 | I14: 1 | J14: =I14*G14 -> 24 | K14: =J14*H14 -> 60883.92
A15: 8 | B15: B1 .31 23 23.01 | C15: Earth works & Embankment | D15: 46190 | E15: SUD1-05-018-TDC-TS9-1-ROD-FIR-0026-00 | F15: Check Coordinates level and Compaction F.D.T for Embankment 2nd layer for Station Road RD-01, STA: 0+120 to STA:0+300 | G15: 24 | H15: 3205.93 | I15: 1 | J15: =I15*G15 -> 24 | K15: =J15*H15 -> 76942.32
A16: 9 | B16: B1 .31 23 23.01 | C16: Earth works & Embankment | D16: 46193 | E16: SUD1-05-018-TDC-TS9-1-ROD-FIR-0027-01 | F16: Check Coordinates level and Compaction F.D.T for Embankment 1st layer for Station Road RD-02, STA: 0+840 to STA:1+000 | G16: 24 | H16: 2713.88 | I16: 1 | J16: =I16*G16 -> 24 | K16: =J16*H16 -> 65133.12
A17: 10 | B17: B1 .31 23 23.01 | C17: Earth works & Embankment | D17: 46193 | E17: SUD1-05-018-TDC-TS9-1-ROD-FIR-0028-00 | F17: Check Coordinates level and Compaction F.D.T for Embankment 2nd layer for Station Road RD-01, STA: 1+200 to STA:1+350 | G17: 24 | H17: 2471.63 | I17: 1 | J17: =I17*G17 -> 24 | K17: =J17*H17 -> 59319.12
A18: 11 | B18: B1.31 23.23.01 | C18: Earth works & Embankment | D18: 46194 | E18: SUD1-05-018-TDC-TS9-1-ROD-FIR-0029-00 | F18: Check Coordinates level and Compaction F.D.T for Embankment 2nd Layer for Station Road RD-01, STA: 0+300 to STA:0+500 | G18: 24 | H18: 3412.82 | I18: 1 | J18: =I18*G18 -> 24 | K18: =J18*H18 -> 81907.68
A19: 12 | B19: B1 .31 23 23.01 | C19: Earth works & Embankment | D19: 46194 | E19: SUD1-05-018-TDC-TS9-1-ROD-FIR-0030-00 | F19: Check Coordinates level and Compaction F.D.T for Embankment 2nd Layer for Station Road RD-01, STA: 0+500 to STA:0+700 | G19: 24 | H19: 3411.28 | I19: 1 | J19: =I19*G19 -> 24 | K19: =J19*H19 -> 81870.72
A20: 13 | B20: B1 .31 23 23.01 | C20: Earth works & Embankment | D20: 46194 | E20: SUD1-05-018-TDC-TS9-1-ROD-FIR-0031-00 | F20: Check Coordinates level and Compaction F.D.T for Embankment 2nd layer for Station Road RD-01, STA: 1+000 to STA:1+200 | G20: 24 | H20: 3279.64 | I20: 1 | J20: =I20*G20 -> 24 | K20: =J20*H20 -> 78711.36
A21: 14 | B21: B1 .31 23 23.01 | C21: Earth works & Embankment | D21: 46224 | E21: SUD1-05-018-TDC-TS9-1-ROD-FIR-0032-00 | F21: Check Coordinates level and Compaction F.D.T for Embankment 3rd layer for Station Road RD-02, STA: 0+600 to STA:0+700 | G21: 24 | H21: 1118.04 | I21: 1 | J21: =I21*G21 -> 24 | K21: =J21*H21 -> 26832.96
A22: 15 | B22: B1 .31 23 23.01 | C22: Earth works & Embankment | D22: 46196 | E22: SUD1-05-018-TDC-TS9-1-ROD-FIR-0033-00 | F22: Check Coordinates level and Compaction F.D.T for Embankment 2nd layer for Station Road RD-02, STA: 0+860 to STA:1+000 | G22: 24 | H22: 1963.02 | I22: 1 | J22: =I22*G22 -> 24 | K22: =J22*H22 -> 47112.48
A23: 16 | B23: B1 .31 23 23.01 | C23: Earth works & Embankment | D23: 46195 | E23: SUD1-05-018-TDC-TS9-1-ROD-FIR-0034-00 | F23: Check Coordinates level and Compaction F.D.T for Embankment 2nd layer for Station Road RD-01, STA: 0+700 to STA:0+850 | G23: 24 | H23: 2675.56 | I23: 1 | J23: =I23*G23 -> 24 | K23: =J23*H23 -> 64213.44
... A107: 100 | B107: B1.32 11 26.01 | C107: BITUMINOUS BASE COURSE | D107: 46312 | E107: SUD1-05-018-TDC-TS9-1-ROD-FIR-0151-00 | F107: Check Coordinates, level, thickness, Compaction and Testing for Bituminous base course 1st layer (80mm) on Road /Carriageway from STA:0+170 to STA: 0+550 at Road #RD-01 | G107: 533 | H107: 266 | I107: 0.1 | J107: =I107*G107 -> 53.3 | K107: =J107*H107 -> 14177.8
K108: =SUM(K8:K107) -> 3887955.9

Sheet CCO
A1: CONTRACT CHANGE ORDER (CCO)
A2: CCO No. | B2: Date Added | C2: Description of Change | D2: Status | E2: SR | F2: Sch Impact (Months) | G2: Date Approved | H2: Duration (days)
A3: - | B3: - | C3: - | D3: - | E3: - | F3: - | G3: - | H3: -

Sheet Procurement
A1: PROCUREMENT
A2: Sr. NO. | B2: Project ID | C2: ACT#inP6 | D2: Item Description | E2: Discipline | F2: (Long \Short) Lead Items | G2: BOQ. No. | H2: Unit | I2: Quantity | J2: Proc. Qty | K2: Required P.O Date | L2: Date of Pur. Order Issued | M2: Purchase Order No. | N2: Supplier | O2: Supplier Phone | P2: Method of Shipping | Q2: Required on Job | R2: E.D.A. to Site | S2: A.D.A. to Site | T2: Lead Time | U2: Approval Status | V2: The Impact (BOQ Cost) | W2: Completion Rate | X2: Remarks
A3: 1 | B3: SUD1-05-018 | C3: SDR-ST-PRO-S-1010 | D3: Waterproofing (Thermal & moisture Protection) | E3: Civil | F3: Short Lead Items | G3: 07 00 00 | H3: m2 | I3: 910 | J3: 910 | K3: 46244 | L3: - | M3: - | N3: - | P3: Local trancport | Q3: Civil | R3: 46269 | S3: 46330 | T3: =R3-K3 -> 25 | U3: Approved | V3: - | W3: -
A4: 2 | B4: SUD1-05-018 | C4: SDR-ST-PRO-S-1030 | D4: Interlock | E4: Civil | F4: Short Lead Items | G4: 33 42 16 | H4: m2 | I4: 27900 | J4: 27900 | K4: 46267 | L4: - | M4: - | N4: - | P4: Local trancport | Q4: Civil | R4: 46293 | S4: 46345 | T4: =R4-K4 -> 26 | U4: Approved | V4: - | W4: - | X4: on going
A5: 3 | B5: SUD1-05-018 | C5: SDR-ST-PRO-S-1060 | D5: Kerbstone | E5: Civil | F5: Short Lead Items | G5: 32 11 26 | H5: m | I5: 20555 | J5: 20555 | K5: 46268 | L5: - | M5: - | N5: - | P5: Local trancport | Q5: Civil | R5: 46282 | S5: 46343 | T5: =R5-K5 -> 14 | U5: Approved | V5: - | W5: - | X5: on going
A6: 4 | B6: SUD1-05-018 | C6: SDR-ST-PRO-S-1260 | D6: Steel Bars | E6: Civil | F6: Short Lead Items | G6: 05 12 00 | H6: Unit | I6: 1 | J6: 1 | K6: 46174 | L6: - | M6: - | N6: - | P6: Local trancport | Q6: Civil | R6: 46225 | S6: 46285 | T6: =R6-K6 -> 51 | U6: Approved | V6: - | W6: 0.9 | X6: on going
A7: 5 | B7: SUD1-05-018 | C7: SDR-ST-PRO-S-1270 | D7: Asphalt | E7: Civil | F7: Short Lead Items | G7: 32 12 16 | H7: m3 | I7: 3420 | J7: 3420 | K7: 46322 | L7: - | M7: - | N7: - | P7: Local trancport | Q7: Civil | R7: 46336 | S7: 46427 | T7: =R7-K7 -> 14 | U7: Approved | V7: - | W7: 0.043 | X7: on going
A8: 6 | B8: SUD1-05-018 | C8: SDR-ST-PRO-S-1140 | D8: LOW VOLTAGE CABLES | E8: Electrical | F8: Short Lead Items | G8: 33 71 00 02 | H8: m | I8: 695 | J8: 695 | K8: 46265 | L8: 46191 | M8: PO 12507 | N8: - | P8: Local trancport | Q8: Civil | R8: 46276 | S8: 46306 | T8: =R8-K8 -> 11 | U8: Approved | V8: - | W8: 1 | X8: Delivered
A9: 7 | B9: SUD1-05-018 | C9: SDR-ST-PRO-S-1150 | D9: LOW VOLTAGE DISTRIBUTION Panel | E9: Electrical | F9: Short Lead Items | G9: 33 71 26 | H9: Unit | I9: 1 | J9: 1 | K9: 46262 | L9: - | M9: - | N9: - | P9: Local trancport | Q9: Civil | R9: 46283 | S9: 46344 | T9: 32 | U9: Approved | V9: - | W9: - | X9: on going
A10: 8 | B10: SUD1-05-018 | C10: SDR-ST-PRO-S-1160 | D10: STREET LIGHTING FEEDER Panel | E10: Electrical | F10: Short Lead Items | G10: 33 71 26 03 | H10: Unit | I10: 2 | J10: 2 | K10: 46272 | L10: - | M10: - | N10: - | P10: Local trancport | Q10: Civil | R10: 46286 | S10: 46327 | T10: =R10-K10 -> 14 | U10: Approved | V10: - | W10: - | X10: on going
A11: 9 | B11: SUD1-05-018 | C11: SDR-ST-PRO-S-1170 | D11: STREET LIGHTING CABLES | E11: Electrical | F11: Short Lead Items | G11: 33 71 00 01 | H11: Unit | I11: 6800 | J11: 6800 | K11: 46265 | L11: - | M11: - | N11: - | P11: Local trancport | Q11: Civil | R11: 46279 | S11: 46340 | T11: =R11-K11 -> 14 | U11: Approved | V11: - | W11: 1 | X11: Delivered
A12: 10 | B12: SUD1-05-018 | C12: SDR-ST-PRO-S-1200 | D12: ROAD CROSSING DUCTS Ø110mm | E12: Electrical | F12: Short Lead Items | G12: 33 81 26 | H12: Unit | I12: 104 | J12: 104 | K12: 46252 | L12: - | M12: - | N12: - | P12: Local trancport | Q12: Civil | R12: 46293 | S12: 46328 | T12: 19 | U12: Approved | V12: - | W12: 1 | X12: Delivered
A13: 12 | B13: SUD1-05-018 | C13: SDR-ST-PRO-S-1230 | D13: CCTV :5MP IP PoE Bullet Camera | E13: Electrical | F13: Short Lead Items | G13: B2.28.20.00.01 | H13: unit | I13: 16 | J13: 16 | K13: 46266 | L13: - | M13: - | N13: - | P13: Local trancport | Q13: Electrical | R13: 46282 | S13: 46323 | T13: =R13-K13 -> 16 | U13: Approved | V13: - | W13: - | X13: on going
A14: 13 | B14: SUD1-05-018 | C14: SDR-ST-PRO-S-1240 | D14: CCTV :Pole mounted Filed Equipment cabinet (FE | E14: Electrical | F14: Short Lead Items | G14: B2.28.20.00.02 | H14: unit | I14: 4 | J14: 4 | K14: 46321 | L14: - | M14: - | N14: - | P14: Local trancport | Q14: Electrical | R14: 46332 | S14: 46392 | T14: =R14-K14 -> 11 | U14: Approved | V14: - | W14: - | X14: on going
A15: 14 | B15: SUD1-05-018 | C15: SDR-ST-PRO-S-1250 | D15: VOICE EVACUATION SYSTEM | E15: Electrical | F15: Short Lead Items | G15: 27 40 00 | H15: Unit | I15: 32 | J15: 32 | K15: 46324 | L15: - | M15: - | N15: - | P15: Local trancport | Q15: Electrical | R15: 46337 | S15: 46397 | T15: =R15-K15 -> 13 | U15: Approved | V15: - | W15: - | X15: on going
A16: 15 | B16: SUD1-05-018 | C16: SDR-ST-PRO-S-1040 | D16: HDPE PIPES & FITTINGS | E16: Mechanical | F16: Short Lead Items | G16: 33 31 23 | H16: m | I16: 2946 | J16: 2946 | K16: 46258 | L16: 46188 | M16: PO 12272 | P16: Local trancport | Q16: Electrical | R16: 46283 | S16: 46344 | T16: =R16-K16 -> 25 | U16: Approved | V16: - | W16: 1 | X16: Delivered
A17: 16 | B17: SUD1-05-018 | C17: SDR-ST-PRO-S-1050 | D17: CONCRETE PIPES AND FITTINGS | E17: Mechanical | F17: Short Lead Items | G17: 33 42 13 | H17: m | I17: 230 | J17: 230 | K17: 46272 | P17: Local trancport | Q17: Electrical | R17: 46283 | S17: 46363 | T17: =R17-K17 -> 11 | U17: Approved | V17: - | W17: 1 | X17: Delivered
A18: 19 | B18: SUD1-05-018 | C18: SDR-ST-PRO-S-1090 | D18: MANHOLE, CATCH BASIN & VALVE BOX COVER | E18: Mechanical | F18: Short Lead Items | G18: 33 81 26 | H18: Unit | I18: 16 | J18: 16 | K18: 46279 | L18: - | P18: Local trancport | Q18: Electrical | R18: 46293 | S18: 46363 | T18: =R18-K18 -> 14 | U18: Approved | V18: - | W18: -
A19: 20 | B19: SUD1-05-018 | C19: SDR-ST-PRO-S-1000 | D19: Metal railing for platform | E19: Civil | F19: Long Lead Items | G19: 05 52 00 | H19: m | I19: 440 | J19: 440 | K19: 46259 | L19: - | P19: Local trancport | Q19: Electrical | R19: 46323 | S19: 46420 | T19: =R19-K19 -> 64 | U19: Not submitted | V19: - | W19: -
A20: 21 | B20: SUD1-05-018 | C20: SDR-ST-PRO-S-1020 | D20: Canopy | E20: Civil | F20: Long Lead Items | G20: 03 30 00/03 53 00 | H20: 560 | I20: m2 | J20: m2 | K20: 46345 | L20: - | P20: Local trancport | Q20: Mechanical | R20: 46378 | S20: 46485 | T20: =R20-K20 -> 33 | U20: Not submitted | V20: - | W20: -
A21: 22 | B21: SUD1-05-018 | C21: SDR-ST-PRO-S-1110 | D21: MEDIUM VOLTAGE CABLES DUCT BANKS | E21: Electrical | F21: Long Lead Items | G21: 33 71 00 | H21: m | I21: 105 | J21: 105 | K21: 46307 | L21: - | P21: Local trancport | Q21: Mechanical | R21: 46324 | S21: 46432 | T21: =R21-K21 -> 17 | U21: Not submitted | V21: - | W21: -
A22: 23 | B22: SUD1-05-018 | C22: SDR-ST-PRO-S-1120 | D22: MEDIUM VOLTAGE CABLES | E22: Electrical | F22: Long Lead Items | G22: 33 71 49.23 | H22: Unit | I22: 7120 | J22: 7120 | K22: 46307 | L22: - | P22: Local trancport | Q22: Mechanical | R22: 46325 | S22: 46433 | T22: =R22-K22 -> 18 | U22: Not submitted | V22: - | W22: -
A23: 24 | B23: SUD1-05-018 | C23: SDR-ST-PRO-S-1130 | D23: SUB-STATION | E23: Electrical | F23: Long Lead Items | G23: 33 73 00 | H23: unit | I23: 2 | J23: 2 | K23: 46314 | L23: - | P23: Local trancport | Q23: Mechanical | R23: 46359 | S23: 46450 | T23: =R23-K23 -> 45 | U23: Not submitted | V23: - | W23: -
A24: 25 | B24: SUD1-05-018 | C24: SDR-ST-PRO-S-1180 | D24: LIGHTING POLES | E24: Electrical | F24: Long Lead Items | G24: 33 71 16 | H24: m | I24: 143 | J24: 143 | K24: 46314 | L24: 46204 | M24: PO 12725 | N24: - | P24: Local trancport | Q24: Mechanical | R24: 46331 | S24: 46445 | T24: =R24-K24 -> 17 | U24: Not submitted | V24: - | W24: -
A25: 26 | B25: SUD1-05-018 | C25: SDR-ST-PRO-S-1190 | D25: STREET LIGHTING LUMINAIRE | E25: Electrical | F25: Long Lead Items | G25: 26 56 19 | H25: Unit | I25: 276 | J25: 276 | K25: 46336 | L25: - | N25: - | P25: Local trancport | Q25: Civil | R25: 46374 | S25: 46471 | T25: =R25-K25 -> 38 | U25: Not submitted | V25: - | W25: -
A26: 27 | B26: SUD1-05-018 | C26: SDR-ST-PRO-S-1220 | D26: Outdoor Lighting Fixtures | E26: Electrical | F26: Long Lead Items | G26: 26 56 00 | H26: Unit | I26: 390 | J26: 390 | K26: 46349 | L26: - | N26: - | P26: Local trancport | Q26: Civil | R26: 46366 | S26: 46488 | T26: =R26-K26 -> 17 | U26: Not submitted | V26: - | W26: -
A27: 28 | B27: SUD1-05-018 | C27: SDR-ST-PRO-S-1100 | D27: WASHOUT & AIR VALVE, GATE VALVE, BUTTERFLY VALVE | E27: Mechanical | F27: Long Lead Items | G27: 33 14 19 | H27: Unit | I27: 5 | J27: 5 | K27: 46321 | L27: - | N27: - | P27: Local trancport | Q27: Electrical | R27: 46364 | S27: 46471 | T27: =R27-K27 -> 43 | U27: Approved | V27: - | W27: - | X27: on going
W29: 0.15 | X29: Under delivery
W35: 1
R64351: =+#REF!+25 -> #REF!
A1048526: Y

Sheet Manpower
A1: Head-Count ( Non Manual)
A2: MONTHS | B2: 46119 | C2: =EOMONTH(B2,1) -> 46173 | D2: =EOMONTH(C2,1) -> 46203 | E2: =EOMONTH(D2,1) -> 46234 | F2: =EOMONTH(E2,1) -> 46265 | G2: =EOMONTH(F2,1) -> 46295 | H2: =EOMONTH(G2,1) -> 46326 | I2: =EOMONTH(H2,1) -> 46356 | J2: =EOMONTH(I2,1) -> 46387 | ... R2: =EOMONTH(Q2,1) -> 46630
A3: Plan - Monthly | B3: 12 | C3: 16 | D3: 20 | E3: 29 | F3: 30 | G3: 30 | H3: 32 | I3: 32 | J3: 32 | K3: 30 | L3: 28 | M3: 24 | N3: 21 | O3: 20 | P3: 19 | Q3: 21 | R3: 15
A4: Planned - Cumulative | B4: =B3 -> 12 | C4: =B4+B3 -> 24 | D4: =C4+C3 -> 40 | E4: =D4+D3 -> 60 | F4: =E4+E3 -> 89 | G4: =F4+F3 -> 119 | H4: =G4+G3 -> 149 | I4: =H4+H3 -> 181 | J4: =I4+I3 -> 213 | ... R4: =Q4+Q3 -> 408
A5: Actual - Monthly | B5: 12 | C5: 16 | D5: 16 | E5: 16 | F5: =B20 -> 22 | G5: 16 | H5: 22
A6: Actual Cumulative | B6: =B5 -> 12 | C6: =B6+C5 -> 28 | D6: =C6+D5 -> 44 | E6: =D6+E5 -> 60 | F6: =E6+F5 -> 82 | G6: =F6+G5 -> 98 | H6: =G6+H5 -> 120
A7: Forecast - Monthly
A8: Saudi Monthly - Actual
A9: Head-Count (Manual)
A10: MONTHS | B10: 46119 | C10: =EOMONTH(B10,1) -> 46173 | D10: =EOMONTH(C10,1) -> 46203 | E10: =EOMONTH(D10,1) -> 46234 | F10: =EOMONTH(E10,1) -> 46265 | G10: =EOMONTH(F10,1) -> 46295 | H10: =EOMONTH(G10,1) -> 46326 | I10: =EOMONTH(H10,1) -> 46356 | J10: =EOMONTH(I10,1) -> 46387 | ... R10: =EOMONTH(Q10,1) -> 46630
A11: Plan - Monthly | B11: 18 | C11: 30 | D11: 36 | E11: 41 | F11: 47 | G11: 123 | H11: 185 | I11: 200 | J11: 230.9885 | K11: 226.42712 | L11: 218.56131 | M11: 203.83462 | N11: 202.603 | O11: 135.98915 | P11: 137.28477 | Q11: 105.60912 | R11: 6.7546154
A12: Planned - Cumulative | B12: =B11 -> 18 | C12: =B12+C11 -> 48 | D12: =C12+D11 -> 84 | E12: =D12+E11 -> 125 | F12: =E12+F11 -> 172 | G12: =F12+G11 -> 295 | H12: =G12+H11 -> 480 | I12: =H12+I11 -> 680 | J12: =I12+J11 -> 910.9885 | ... R12: =Q12+R11 -> 2148.0522
A13: Actual - Monthly | B13: 41 | C13: 48 | D13: 62 | E13: =B24 -> 65 | F13: 31 | G13: 31 | H13: 65 | AQ13: =W2-V2 -> 0
A14: Actual Cumulative | B14: =B13 -> 41 | C14: =B14+C13 -> 89 | D14: =C14+D13 -> 151 | E14: =D14+E13 -> 216 | F14: =E14+F13 -> 247 | G14: =F14+G13 -> 278 | H14: =G14+H13 -> 343
A15: Forecast - Monthly
A16: Saudi - Actual
A18: Head-Count (Non-Manual) | AG18: Month | AI18: =EOMONTH('General Information'!$L$1,0) -> 46326 | AM18: =EOMONTH(AI18,1) -> 46356
A19: Planned | B19: Actual | D19: Variance | F19: Forecast Next Month | H19: Saudi Staff
A20: 20 | B20: 22 | D20: =B20-A20 -> 2 | F20: =HLOOKUP($AM$18,$B$2:$AL$8,6,FALSE) -> 0 | H20: 3
A22: Head-Count (Manual) | L22: Man Power by Trade
A23: Planned | B23: Actual | D23: Variance | F23: Forecast Next Month | H23: Saudi Staff | L23: Key Trade | N23: Engineer | P23: Doc. Controller | R23: Proc. Team | T23: Foreman | V23: Draftman | X23: Driver | Z23: UnSkilled Labor | AB23: Skiled labour | AD23: Others | AF23: Total
A24: 40 | B24: 65 | D24: =B24-A24 -> 25 | F24: =HLOOKUP($AM$18,$B$10:$AL$16,6,FALSE) -> 0 | H24: 0 | L24: Plan | N24: 2 | P24: 1 | R24: 1 | T24: 2 | V24: 1 | X24: 5 | Z24: 15 | AB24: 8 | AD24: 5 | AF24: =SUM(N24:AE24) -> 40
L25: Actual | N25: 10 | P25: 1 | R25: 1 | T25: 3 | V25: 1 | X25: 31 | Z25: 20 | AB25: 10 | AD25: 10 | AF25: =SUM(N25:AE25) -> 87
A32: Equipment
A33: MONTHS | B33: 46119 | C33: =EOMONTH(B33,1) -> 46173 | D33: =EOMONTH(C33,1) -> 46203 | E33: =EOMONTH(D33,1) -> 46234 | F33: =EOMONTH(E33,1) -> 46265 | G33: =EOMONTH(F33,1) -> 46295 | H33: =EOMONTH(G33,1) -> 46326 | I33: =EOMONTH(H33,1) -> 46356 | J33: =EOMONTH(I33,1) -> 46387 | ... R33: =EOMONTH(Q33,1) -> 46630
A34: Plan - Monthly | B34: 0 | C34: 6.3076923 | D34: 6.2421538 | E34: 22.275808 | F34: 28.846923 | G34: 47.771 | H34: 56.644346 | I34: 61.630269 | J34: 46.214885 | K34: 31.332923 | L34: 14.952 | M34: 13.857269 | N34: 10.074731 | O34: 8.9238462 | P34: 8 | Q34: 0 | R34: 0
A35: Planned - Cumulative | B35: =B34 -> 0 | C35: =B35+C34 -> 6.3076923 | D35: =C35+C34 -> 12.615385 | E35: =D35+D34 -> 18.857538 | F35: =E35+E34 -> 41.133346 | G35: =F35+F34 -> 69.980269 | H35: =G35+G34 -> 117.75127 | I35: =H35+H34 -> 174.39562 | J35: =I35+I34 -> 236.02588 | K35: =J35+J34 -> 282.24077 | ... R35: =Q35+Q34 -> 369.38154
A36: Actual - Monthly | B36: 0 | C36: 6 | D36: 14 | E36: 17 | F36: =B43 -> 32 | G36: 18 | H36: 32
A37: Actual Cumulative | B37: 0 | C37: =B37+C36 -> 6 | D37: =C37+D36 -> 20 | E37: =D37+E36 -> 37 | F37: =E37+F36 -> 69 | G37: =F37+G36 -> 87 | H37: =G37+H36 -> 119
A38: Forecast - Monthly
A41: Equipment Count
A42: Planned | B42: Actual | D42: Idle | F42: Variance | H42: Forecast Next Month
A43: =F34 -> 28.846923 | B43: 32 | C43: =HLOOKUP($AI$18,$B$33:$AL$38,2,FALSE) -> 56.644346 | D43: =AH52 -> 0 | F43: =B43-A43 -> 3.1530769 | H43: =HLOOKUP($AM$18,$B$33:$AL$38,6,FALSE) -> 0
A49: Type | B49: Pick Up/Car | C49: Fork lift | D49: Bus | E49: Dumper | F49: Dump Truck | G49: Grader | H49: Boom Truck | J49: Generator | L49: CRANE | N49: Showel | P49: Grader | R49: Truck | T49: Water Tank | V49: Finisher | X49: Bobcat | Z49: Forklift | AB49: JCB | AD49: Loader | AF49: Boom Truck | AG49: Road Marker | AH49: Total
A50: Plan | B50: 1 | D50: 1 | F50: 10 | H50: 0 | J50: 1 | L50: 0 | N50: 0 | P50: 6 | R50: 0 | T50: 0 | V50: 0 | X50: 0 | Z50: 0 | AB50: 0 | AD50: 1 | AF50: 2 | AG50: 0 | AH50: =SUM(B50:AG50) -> 22
A51: Actual | B51: 2 | D51: 1 | F51: 10 | H51: 0 | J51: 1 | L51: 1 | N51: 1 | P51: 5 | R51: 0 | T51: 2 | V51: 0 | X51: 0 | Z51: 0 | AB51: 0 | AD51: 0 | AF51: 0 | AG51: 0 | AH51: =SUM(B51:AG51) -> 23
A52: Idle | AH52: =SUM(B52:AG52) -> 0

Sheet Issues
M3: ='General Information'!L1 -> 46314 | N3: Status | O3: Responsibility
N4: Open | O4: Contractor
N5: Closed | O5: Consultant
O6: Modon
O7: Third Party
O8: Other
A9: Issue Log
A12: Issue ID | B12: Parent Project ID | C12: Contract / Project ID | D12: Project Name | E12: City | F12: Region | G12: Fund Source | H12: Phase | I12: PM / Owner | J12: Contractor / Designer | K12: Current Status | L12: Value (SAR) | M12: Category | N12: Issue Title | O12: Description | P12: Evidence / Data | Q12: Severity (1-5) | R12: Urgency (1-5) | S12: Priority Score | T12: Priority | U12: Action Required | V12: Date Raised | W12: Status | X12: Duration Elapsed | Y12: Expected/Actual Closure | Z12: Target Date
A13: 3120-1 | B13: 3120 | C13: 3196 | D13: Construction of Passenger Station for SAR Railway Sudair Industrial City | E13: Sudair | F13: Riyadh Region | G13: Government Funded | H13: Construction / Access & Permits | I13: Egis / MODON | J13: Technical Development Company for Contracting | K13: Close | O13: Noticed a signboard that is fallen and improperly positioned on the ground | T13: Contractor | U13: Assess the damage: Evaluate whether the sign can be repaired and reinstalled, or if it needs a complete replacement.Inspect the mounting hardware: Determine why it fell. Check for rusted bolts, rotted wood, cracked concrete bases, or loose brackets.Reinstall securely: Remount the sign using upgraded, weather-resistant hardware (such as heavy-duty anchor bolts or reinforced brackets) that can withstand local wind loads and environmental conditions. | V13: 46267 | W13: Closed | X13: 1 | Y13: 2 | Z13: 46267
A14: 3120-2 | B14: 3120 | C14: 3196 | D14: Construction of Passenger Station for SAR Railway Sudair Industrial City | E14: Sudair | F14: Riyadh Region | G14: Government Funded | H14: Design / Engineering | I14: Egis / MODON | J14: Technical Development Company for Contracting | K14: Close | O14: Waste plastic bottles were scattered on-site, resulting in poor housekeeping. | T14: Contractor | U14: Informed the workgroup about the concern to clean up the area immediately, set up proper disposal bins, and run a short safety reminder for the crew. | V14: 46269 | W14: Closed | X14: 1 | Y14: 2 | Z14: 46269
A15: 3120-3 | B15: 3120 | C15: 3196 | D15: Construction of Passenger Station for SAR Railway Sudair Industrial City | E15: Sudair | F15: Riyadh Region | G15: Government Funded | H15: Construction / Civil Works | I15: Egis / MODON | J15: Technical Development Company for Contracting | K15: Close | O15: A new water filter was installed to ensure clean drinking water. | T15: Contractor | U15: GOOD PRACTICE | V15: 46271 | W15: Closed | X15: 1 | Y15: 2 | Z15: 46271
A16: 3120-4 | B16: 3120 | C16: 3196 | D16: Construction of Passenger Station for SAR Railway Sudair Industrial City | E16: Sudair | F16: Riyadh Region | G16: Government Funded | H16: Construction / Civil Works | I16: Egis / MODON | J16: Technical Development Company for Contracting | K16: Close | O16: It was observed that the subcontractor was carrying out pipe-shifting activities using a wheel loader. | T16: Contractor | U16: Stop Work: Issue an immediate Stop Work Order to halt the pipe-shifting activity safely.Secure the Area: Ensure the load is safely lowered to the ground and the area is barricaded if necessary.Conduct a Safety Stand-Down: Brief the supervisor and workers involved on the specific hazards of using unauthorized machinery for lifting. Review Risk Assessment & Method Statement (RAMS): Verify if the approved RAMS specified a wheel loader. If not, enforce compliance; if it did, revise the RAMS immediately to reflect proper lifting equipment.Verify Operator Competency: Check the operator's license and verify if they have undergone specific training for material handling.Enforce Proper Equipment: Mandate the use of appropriate lifting equipment, such as a crane, boom truck, or an excavator fitted with an approved lifting hook and certified slings/shackles | V16: 46273 | W16: Closed | X16: 1 | Y16: 2 | Z16: 46273
A17: 3120-5 | B17: 3120 | C17: 3196 | D17: Construction of Passenger Station for SAR Railway Sudair Industrial City | E17: Sudair | F17: Riyadh Region | G17: Government Funded | H17: Construction / Civil Works | I17: Egis / MODON | J17: Technical Development Company for Contracting | K17: Close | O17: Concrete barriers were misplaced in the area | T17: Contractor/HSE Team | U17: Use appropriate heavy lifting equipment (such as a Boomtruck) to move the concrete barriers back to a safe distance—away from the excavation edge. | V17: 46274 | W17: Closed | X17: 1 | Y17: 2 | Z17: 46274
A18: 3120-6 | B18: 3120 | C18: 3196 | D18: Construction of Passenger Station for SAR Railway Sudair Industrial City | E18: Sudair | F18: Riyadh Region | G18: Government Funded | H18: Construction / Civil Works | I18: Egis / MODON | J18: Technical Development Company for Contracting | K18: Close | O18: Dust created by vehicles moving on project routes | T18: Contractor | U18: Water spraying on vehiceles routes on regular basis | V18: 46285 | W18: Closed | X18: 1 | Y18: 2 | Z18: 46285
A19: 3120-7 | B19: 3120 | C19: 3196 | D19: Construction of Passenger Station for SAR Railway Sudair Industrial City | E19: Sudair | F19: Riyadh Region | G19: Government Funded | H19: Construction / Civil Works | I19: Egis / MODON | J19: Technical Development Company for Contracting | K19: Close | O19: Unaviailibilty of shaded cold water station | T19: Contractor/HSE Team | U19: Provision of shaded cold water station to the site workers. | V19: 46285 | W19: Closed | X19: 1 | Y19: 2 | Z19: 46285
A20: 3120-8 | B20: 3120 | C20: 3196 | D20: Construction of Passenger Station for SAR Railway Sudair Industrial City | E20: Sudair | F20: Riyadh Region | G20: Government Funded | H20: Construction / Civil Works | I20: Egis / MODON | J20: Technical Development Company for Contracting | K20: Close | O20: Shallow excavation found without safety and warning signages | T20: Contractor/HSE Team | U20: posting warning and safety signages to increase the visibility and awareness about riks. | V20: 46289 | W20: Closed | X20: 1 | Y20: 2 | Z20: 46289
A21: 3120-9 | B21: 3120 | C21: 3196 | D21: Construction of Passenger Station for SAR Railway Sudair Industrial City | E21: Sudair | F21: Riyadh Region | G21: Government Funded | H21: Construction / Civil Works | I21: Egis / MODON | J21: Technical Development Company for Contracting | K21: Close | O21: Workers found in equipment working zone | T21: Contractor/HSE Team | U21: Stop movement in man machine/ equioment interface and segrete equipment and man working areas. | V21: 46289 | W21: Closed | X21: 1 | Y21: 2 | Z21: 46289
A22: 3120-10 | B22: 3120 | C22: 3196 | D22: Construction of Passenger Station for SAR Railway Sudair Industrial City | E22: Sudair | F22: Riyadh Region | G22: Government Funded | H22: Construction / Civil Works | I22: Egis / MODON | J22: Technical Development Company for Contracting | K22: Close | O22: Directional signages along with concrete jersey barriers and warning signages and tape were found missing | P22: Contractor HSE team | Q22: Directional signages along with concrete jersey barriers and warning tape with rope have been provided – New Diversion Road,to ensure safe traffic movement and to guide site vehicles / heavy equipment. | T22: Contractor HSE team | U22: Directional signages along with concrete jersey barriers and warning tape with rope have been provided – New Diversion Road,to ensure safe traffic movement and to guide site vehicles / heavy equipment. | V22: 46298 | W22: Closed | X22: 1 | Y22: 2 | Z22: 46298
A23: 3120-11 | B23: 3120 | C23: 3196 | D23: Construction of Passenger Station for SAR Railway Sudair Industrial City | E23: Sudair | F23: Riyadh Region | G23: Government Funded | H23: Construction / Civil Works | I23: Egis / MODON | J23: Technical Development Company for Contracting | K23: Close | O23: Equipment operator found working zone with Non-compalince to site mandatory PPE. | P23: Contractor consruction /HSE Team | Q23: it was ensure to wear the mandatory PPE all the time when present on site | T23: Contractor consruction /HSE Team | U23: it was ensure to wear the mandatory PPE all the time when present on site | V23: 46298 | W23: Closed | X23: 1 | Y23: 2 | Z23: 46298
A24: 3120-12 | B24: 3120 | C24: 3196 | D24: Construction of Passenger Station for SAR Railway Sudair Industrial City | E24: Sudair | F24: Riyadh Region | G24: Government Funded | H24: Construction / Civil Works | I24: Egis / MODON | J24: Technical Development Company for Contracting | K24: Close | O24: Observe Hot Work activity without proper control measure Fire safety | T24: Contractor HSE team | U24: Provide Fire Extinguisher and other requirements as per Hot work requirements. | V24: 46305 | W24: Closed | X24: 1 | Y24: 2 | Z24: 46305
A25: 3120-13 | B25: 3120 | C25: 3196 | D25: Construction of Passenger Station for SAR Railway Sudair Industrial City | E25: Sudair | F25: Riyadh Region | G25: Government Funded | H25: Construction / Civil Works | I25: Egis / MODON | J25: Technical Development Company for Contracting | K25: Close | O25: Observe site without mandatory PPE complaince | T25: Contractor consruction /HSE Team | U25: Wear the mandatory PPE all the time when present on site | V25: 46306 | W25: Closed | X25: 1 | Y25: 2 | Z25: 46306
A26: 3120-14 | B26: 3120 | C26: 3196 | D26: Construction of Passenger Station for SAR Railway Sudair Industrial City | E26: Sudair | F26: Riyadh Region | G26: Government Funded | H26: Construction / Civil Works | I26: Egis / MODON | J26: Technical Development Company for Contracting | K26: Close | O26: Observe dust created at temporary vehicles roads due insuffient dust control measures. | T26: Contractor HSE team | U26: Ensure dust control by regular spraying of water on vehicles routes | V26: 46313 | W26: Closed | X26: 1 | Y26: 2 | Z26: 46313
A27: 3120-15 | B27: 3120 | C27: 3196 | D27: Construction of Passenger Station for SAR Railway Sudair Industrial City | E27: Sudair | F27: Riyadh Region | G27: Government Funded | H27: Construction / Civil Works | I27: Egis / MODON | J27: Technical Development Company for Contracting | K27: Close | O27: Observe non complaince of mandatory PPE by equipment operators | T27: Contractor consruction /HSE Team | U27: Wear the mandatory PPE all the time by equipment operators when present on site | V27: 46312 | W27: Closed | X27: 1 | Y27: 2 | Z27: 46312

Sheet Risk Register
A1: Risk Log
A4: Risk ID | B4: Parent Project ID | C4: Contract / Project ID | D4: Project Name | E4: City | F4: Region | G4: Fund Source | H4: Phase | I4: PM / Owner | J4: Contractor / Designer | K4: Current Status | L4: Value (SAR) | M4: Category | N4: Risk Title | O4: Description | P4: Evidence / Data | Q4: Probability (1-5) | R4: Impact (1-5) | S4: Score | T4: Rating | U4: Response | V4: Mitigation Plan | W4: Date Identified | X4: Status | Y4: Target Date | Z4: Notes / Updates | AA4: Source
A5: 3120-1 | B5: 3120 | C5: 3196 | D5: Construction of Passenger Station for SAR Railway Sudair Industrial City | E5: Sudair | F5: Riyadh Region | G5: Government Funded | H5: Construction / Access & Permits | I5: Egis / MODON | J5: Technical Development Company for Contracting | K5: Open | M5: Permits/Stakeholder | N5: Pending SAR Fence Permission Affecting Platform and Canopy Works | O5: The required SAR/fence permission to commence the works inside the designated platform area is still pending. As a result, the Contractor is unable to commence the platform and associated canopy works. Continued delay in obtaining the required permission is affecting the planned sequence of works and may directly impact the project completion date. | P5: Canopy and platform design/details not received from Client; related shop drawings cannot be finalized; associated procurement and construction activities are dependent on the required design information; Client design information remains outstanding. | Q5: 5 | R5: 5 | S5: 25 | T5: Very High | U5: Mitigate | V5: Expedite the SAR/fence permission through the Client and relevant authorities. Escalate the matter to project management for immediate resolution. Arrange regular follow-up with the responsible parties and obtain a firm approval/permission date. Prepare manpower, materials, equipment and work fronts in advance so that platform and canopy works can commence immediately once permission is received. Review the programme and implement recovery/acceleration measures if required. | W5: 16/9/2026 | X5: Open | Z5: SAR/fence permission remains outstanding. Platform and canopy works cannot commence until the required permission is obtained. Continued delay may affect the planned construction sequence and project completion date. | AA5: SAR/Fence Permission Correspondence, Client Instructions, RFI/Approval Register, Site Records, Project Scheduledule
A6: 3120-2 | B6: 3120 | C6: 3196 | D6: Construction of Passenger Station for SAR Railway Sudair Industrial City | E6: Sudair | F6: Riyadh Region | G6: Government Funded | H6: Design / Engineering | I6: Egis / MODON | J6: Technical Development Company for Contracting | K6: Open | L6: 9867379 | M6: Design/Technical | N6: Outstanding Canopy and Platform Design Affecting Shop Drawing, Procurement and Construction | O6: The required design/details for the canopy and platform have not yet been provided by the Client. The outstanding design information is preventing the Contractor from finalizing the related shop drawings and progressing associated construction and procurement activities. Continued non-availability of the design information may result in delay to the affected works and potentially impact the overall project completion milestone. | P6: Canopy and platform design/details not received from Client; related shop drawings cannot be finalized; associated procurement and construction activities are dependent on the required design information; Client design information remains outstanding. | Q6: 5 | R6: 5 | S6: 25 | T6: Very High | U6: Mitigate | V6: Immediately escalate the outstanding design requirement to the Client/Consultant and request formal issuance of the canopy and platform design. Conduct dedicated coordination meetings to close the outstanding information. Prepare all possible shop-drawing activities in parallel and identify procurement requirements in advance. Once the design is received, prioritize shop-drawing preparation, review/approval, procurement and construction. Assess the schedule impact and develop recovery measures if required. Maintain formal records of all requests and correspondence to protect the Contractor's contractual position. | W6: 16/9/2026 | X6: Open | Z6: Project is currently ahead of schedule; however, the Client's outstanding canopy and platform design is affecting the finalization of shop drawings and may hold associated procurement and construction activities. Continued delay in receiving the design information may consume available float and potentially impact the overall project completion/handover milestone. | AA6: Client/Consultant Correspondence, RFI, Design/Submittal Register, Shop Drawing Register, Procurement Log, Project Schedule
A7: 3120-3 | B7: 3120 | C7: 3196 | D7: Construction of Passenger Station for SAR Railway Sudair Industrial City | E7: Sudair | F7: Riyadh Region | G7: Government Funded | H7: Construction / Civil Works | I7: Egis / MODON | J7: Technical Development Company for Contracting | K7: Open | M7: Interface/Utilities | N7: Delay in Client Approval for MV Duct Crossings Affecting MV Cable Installation | O7: Client approval is required for the proposed MV duct crossings. If approval is not obtained within the required timeframe, the execution of the MV duct crossings may be delayed, which could subsequently affect MV cable installation and the planned sequence of electrical works. | P7: MV duct crossing proposal/submission pending Client approval; MV cable installation is dependent on completion/availability of the required duct crossings; project is currently ahead of schedule. | Q7: 4 | R7: 4 | S7: 16 | T7: High | U7: Mitigate | V7: Expedite Client review and approval of the MV duct crossing proposal. Conduct regular follow-up with the Client/Consultant and obtain formal approval at the earliest. Coordinate the crossing works with civil and electrical teams and prepare resources/materials in advance so that construction can commence immediately after approval. Monitor the activity against the MV cable installation schedule to prevent loss of available float. | W7: 16/9/2026 | X7: Open | Z7: Project is currently ahead of schedule. However, pending Client approval for MV duct crossings may affect the planned execution of the crossing works and subsequently impact MV cable installation if approval is not received within the required timeframe. | AA7: MV Duct Crossing Proposal / Client Correspondence / RFI or Technical Submittal / Project Schedule
A8: 3120-4 | B8: 3120 | C8: 3196 | D8: Construction of Passenger Station for SAR Railway Sudair Industrial City | E8: Sudair | F8: Riyadh Region | G8: Government Funded | H8: Construction / Civil Works | I8: Egis / MODON | J8: Technical Development Company for Contracting | K8: Open | M8: Authorities / Permits | N8: Delay is recevieng SAR Permit | O8: Affecting Geo technical Report ,Shop Drawing and Backfilling work | P8: Delay in completion date | Q8: 4 | R8: 4 | S8: 16 | T8: High | W8: 46147 | X8: Close | Y8: 46178 | AC8: Post Treatment
A9: 3120-5 | B9: 3120 | C9: 3196 | D9: Construction of Passenger Station for SAR Railway Sudair Industrial City | E9: Sudair | F9: Riyadh Region | G9: Government Funded | H9: Construction / Civil Works | I9: Egis / MODON | J9: Technical Development Company for Contracting | K9: Open | M9: Authorities / Permits | N9: Delay is recevieng Tender drawing for platform | O9: Structure Drawing for Platform | P9: Delay in completion date | Q9: 3 | R9: 3 | S9: 12 | T9: M12 | W9: 46147 | X9: Close | Y9: 46178
A10: 3120-6 | B10: 3120 | C10: 3196 | D10: Construction of Passenger Station for SAR Railway Sudair Industrial City | E10: Sudair | F10: Riyadh Region | G10: Government Funded | H10: Construction / Civil Works | I10: Egis / MODON | J10: Technical Development Company for Contracting | K10: Close | M10: Safety / Quality | N10: Visibility is low due to strong winds and dust. | O10: Vehicle and machinery collisions, falls from high places, and breathing problems. | P10: Severe site hazards, including vehicle and machinery collisions, respiratory damage from inhaled particles, and structural instability from high wind load | Q10: 3 | R10: 3 | S10: 12 | T10: M12 | W10: 46238 | X10: Close | Y10: 46238 | Z10: Suspending high-risk tasks, controlling vehicle movement, and protecting workers.
A11: 3120-7 | B11: 3120 | C11: 3196 | D11: Construction of Passenger Station for SAR Railway Sudair Industrial City | E11: Sudair | F11: Riyadh Region | G11: Government Funded | H11: Construction / Civil Works | I11: Egis / MODON | J11: Technical Development Company for Contracting | K11: Close | M11: Safety / Quality | N11: Found a damaged fire extinguisher in the site office area. | O11: May fail during a fire, can leak harmful chemicals or gas, and it can burst or fly apart. | P11: Complete equipment failure during a fire, sudden rupture or explosion of the pressurized metal container, and delayed evacuation or severe personal injury | Q11: 2 | R11: 2 | S11: 10 | T11: L4 | W11: 46239 | X11: Close | Y11: 46239 | Z11: Finding a damaged fire extinguisher requires immediate removal, clear tagging, and professional servicing
A12: 3120-8 | B12: 3120 | C12: 3196 | D12: Construction of Passenger Station for SAR Railway Sudair Industrial City | E12: Sudair | F12: Riyadh Region | G12: Government Funded | H12: Construction / Civil Works | I12: Egis / MODON | J12: Technical Development Company for Contracting | K12: Close | M12: Safety / Quality | N12: It was observed that diesel is being stored in plastic containers. | O12: Chemical Breakdown and Leaks, Fuel Contamination, Environmental Spills and Exposure. Fire hazard | P12: Health Risks, Equipment Failure | Q12: 2 | R12: 2 | S12: 10 | T12: L4 | W12: 46273 | X12: Close | Y12: 46273 | Z12: Immediate transfer of the diesel into approved containers and the systematic neutralization of microbial risks
A13: 3120-9 | B13: 3120 | C13: 3196 | D13: Construction of Passenger Station for SAR Railway Sudair Industrial City | E13: Sudair | F13: Riyadh Region | G13: Government Funded | H13: Construction / Civil Works | I13: Egis / MODON | J13: Technical Development Company for Contracting | K13: Close | M13: Safety / Quality | N13: Due to sand storm dust accumulated and poor visibility on site | O13: Visibility & Safety Hazards, Acute Health Risks, Equipment & Asset Damage | P13: Immediate On-Site Consequences (Due to Poor Visibility), Physical Consequences (Due to Accumulated Dust, Health Hazards for Site Personnel, | Q13: 2 | R13: 2 | S13: 10 | T13: L4 | W13: 46274 | X13: Close | Y13: 46274 | Z13: Halt All Mobile Operations: Order an immediate stop to all heavy equipment operation, crane lifting, and vehicle transit. Poor visibility makes navigating the site blind and exponentially increases the risk of collisions or structural strikes. Mandatory Shelter-in-Place: Move all personnel immediately away from open areas. Issue High-Efficiency PPE
A14: 3120-10 | B14: 3120 | C14: 3196 | D14: Construction of Passenger Station for SAR Railway Sudair Industrial City | E14: Sudair | F14: Riyadh Region | G14: Government Funded | H14: Construction / Civil Works | I14: Egis / MODON | J14: Technical Development Company for Contracting | K14: Close | M14: Safety / Quality | N14: Dust created by vehicles moving on project routes | O14: Visibility & Safety Hazards, Acute Health Risks, Equipment & Asset Damage | P14: Health Issues (repiratory), Equipment collsion due low visibility | Q14: 3 | R14: 3 | S14: 12 | T14: M8 | W14: 46285 | X14: Close | Y14: 46285 | Z14: Regular water spraying on vehicle routes
A15: 3120-11 | B15: 3120 | C15: 3196 | D15: Construction of Passenger Station for SAR Railway Sudair Industrial City | E15: Sudair | F15: Riyadh Region | G15: Government Funded | H15: Construction / Civil Works | I15: Egis / MODON | J15: Technical Development Company for Contracting | K15: Close | M15: Safety / Quality | N15: Shade not available for drinking water | O15: Heat Stress to workers on site due improper arrangement of cold water stations. | P15: Heat stress and heat stroke to workers as workers | Q15: 3 | R15: 3 | S15: 12 | T15: M8 | W15: 46285 | X15: Close | Y15: 46285 | Z15: Shaded water station so that water remains cold for long duration for site workers.
A16: 3120-12 | B16: 3120 | C16: 3196 | D16: Construction of Passenger Station for SAR Railway Sudair Industrial City | E16: Sudair | F16: Riyadh Region | G16: Government Funded | H16: Construction / Civil Works | I16: Egis / MODON | J16: Technical Development Company for Contracting | K16: Close | M16: Safety / Quality | N16: Shallow excavation found without safety and warning signages | O16: Visibility & Safety Hazards which could lead in workers and equipment fall in to excavation. | P16: Peronsal injuries and equipment damages | Q16: 4 | R16: 4 | S16: 25 | T16: Very High | W16: 46289 | X16: Close | Y16: 46289 | Z16: posting warning and safety signages to increase the visibility and awareness about riks.
A17: 3120-13 | B17: 3120 | C17: 3196 | D17: Construction of Passenger Station for SAR Railway Sudair Industrial City | E17: Sudair | F17: Riyadh Region | G17: Government Funded | H17: Construction / Civil Works | I17: Egis / MODON | J17: Technical Development Company for Contracting | K17: Close | M17: Safety / Quality | N17: Workers found in equipment working zone | O17: Workers working in machine /equipment working zone are exposed to hit/ struck by the moving machine/ equipment. | P17: Peronal injuries from minor to critical injuries and fatalities | Q17: 5 | R17: 5 | S17: 25 | T17: Very High | W17: 46289 | X17: Close | Y17: 46289 | Z17: Stop movement in man machine/ equioment interface and segrete equipment and man working areas.
A18: 3120-14 | B18: 3120 | C18: 3196 | D18: Construction of Passenger Station for SAR Railway Sudair Industrial City | E18: Sudair | F18: Riyadh Region | G18: Government Funded | H18: Construction / Civil Works | I18: Egis / MODON | J18: Technical Development Company for Contracting | K18: Close | M18: Safety / Quality | N18: directional signages along with concrete jersey barriers and warning signages and tape were missing | O18: Information signages inncrease Visibility & absence expose workers and equipment to Safety Hazards which could lead in workers and equipment collsion and fall to trenches | P18: Information signages inncrease Visibility & absence expose workers and equipment to Safety Hazards which could lead in workers and equipment collsion and fall to trenches | Q18: 5 | R18: 5 | S18: 25 | T18: Very High | W18: 46298 | X18: Close | Y18: 46298 | Z18: Directional signages along with concrete jersey barriers and warning tape with rope have been provided – New Diversion Road,to ensure safe traffic movement and to guide site vehicles / heavy equipment.
A19: 3120-15 | B19: 3120 | C19: 3196 | D19: Construction of Passenger Station for SAR Railway Sudair Industrial City | E19: Sudair | F19: Riyadh Region | G19: Government Funded | H19: Construction / Civil Works | I19: Egis / MODON | J19: Technical Development Company for Contracting | K19: Close | M19: Safety / Quality | N19: Found equipment operators without PPE complaince | O19: Mandatory PPE non complaince could to several injuries from minor to major. | P19: Mandatory PPE non complaince could to several injuries from minor to major. | Q19: 3 | R19: 3 | S19: 12 | T19: M12 | W19: 46298 | X19: Close | Y19: 46298 | Z19: Wear the mandatory PPE all the time when present on site
A20: 3120-16 | B20: 3120 | C20: 3196 | D20: Construction of Passenger Station for SAR Railway Sudair Industrial City | E20: Sudair | F20: Riyadh Region | G20: Government Funded | H20: Construction / Civil Works | I20: Egis / MODON | J20: Technical Development Company for Contracting | K20: Close | M20: Safety / Quality | N20: Observe Hot Work activity without proper control measure Fire safety | O20: High risk of uncontrolled fire resulted from unavialablity of fire extinguisher | P20: Peronsal injuries and equipment damages | Q20: 5 | R20: 5 | S20: 25 | T20: Very High | W20: 46305 | X20: Close | Y20: 46305 | Z20: Peronsal injuries and equipment damages
A21: 3120-17 | B21: 3120 | C21: 3196 | D21: Construction of Passenger Station for SAR Railway Sudair Industrial City | E21: Sudair | F21: Riyadh Region | G21: Government Funded | H21: Construction / Civil Works | I21: Egis / MODON | J21: Technical Development Company for Contracting | K21: Close | M21: Safety / Quality | N21: Observe site without mandatory PPE complaince | O21: Mandatory PPE non complaince could to several injuries from minor to major. | P21: minor and major injuries | Q21: 3 | R21: 3 | S21: 12 | T21: M12 | W21: 46306 | X21: Close | Y21: 46306 | Z21: minor and major injuries
... A23: 3120-19 | B23: 3120 | C23: 3196 | D23: Construction of Passenger Station for SAR Railway Sudair Industrial City | E23: Sudair | F23: Riyadh Region | G23: Government Funded | H23: Construction / Civil Works | I23: Egis / MODON | J23: Technical Development Company for Contracting | K23: Close | M23: Safety / Quality | N23: Observe site without mandatory PPE complaince by equipment operator | O23: Mandatory PPE non complaince could to several injuries from minor to major. | P23: minor and major injuries | Q23: 5 | R23: 5 | S23: 25 | T23: Very High | W23: 46312 | X23: Close | Y23: 46312 | Z23: minor and major injuries

Sheet Milestones
A1: Project Name
A2: Item No. | B2: Milestones | C2: Original (Baseline) | D2: Latest | E2: Forecast | G2: Days Change
B3: ="Contract Duration Current Contract Weeks : "&TEXT(I3, "0")&" of "&TEXT(L3, "0") -> Contract Duration Current Contract Weeks : 28 of 69 | D3: =(D13-D4)/7 -> 69.428571 | E3: =(E13-E4)/7 -> 69.428571 | G3: =(D3-E3)*7 -> 0 | I3: =('General Information'!L1-C4)/7 -> 27.857143 | L3: =D3 -> 69.428571
A4: 1 | B4: Project Start Milstone | C4: 46119 | D4: 46119 | E4: 46119 | F4: Finish | G4: =D4-E4 -> 0
A5: 2 | B5: Mobilization Finish Milestone | C5: 46148 | D5: 46148 | E5: 46148 | F5: Finish | G5: =D5-E5 -> 0
A6: 3 | B6: Work Plan and Timeline Milestone | C6: 46148 | D6: 46148 | E6: 46250 | F6: UP | G6: =D6-E6 -> -102
A7: 4 | B7: Completion of MV Work | C7: 46519 | D7: 46529 | E7: 46512 | F7: UP | G7: =D7-E7 -> 17
A8: 5 | B8: Completion of road and paving works Milestone | C8: 46362 | D8: 46362 | E8: 46387 | F8: UP | G8: =D8-E8 -> -25
A9: 6 | B9: Completion of site and platform work Milestone | C9: 46588 | D9: 46588 | E9: 46604 | F9: UP | G9: =D9-E9 -> -16
A10: 7 | B10: Completion of finishing works and general site works | C10: 46588 | D10: 46588 | E10: 46605 | F10: UP | G10: =D10-E10 -> -17
A11: 8 | B11: Engineering Phase Finish Milestone | C11: 46148 | D11: 46148 | E11: 46286 | F11: UP | G11: =D11-E11 -> -138
A12: 9 | B12: Procurment Phase Finish Milestone | C12: 46492 | D12: 46492 | E12: 46547 | F12: UP | G12: =D12-E12 -> -55
A13: 10 | B13: Project Finish Milstone | C13: 46605 | D13: 46605 | E13: 46605 | F13: - | G13: =D13-E13 -> 0

Sheet Schedule
A1: Primavera P6 Schedule Status | P1: ='General Information'!$K$1 -> Data Date | Q1: ='General Information'!$L$1 -> 46314
A2: Project Activities Overview
A3: Schedule Statistics | F3: Active Schedule Activities
A4: Total Act. | B4: Not Started | C4: In Progress | D4: Completed | E4: % | F4: Active | G4: Ahead | H4: On | I4: Behind | J4: Flag
A5: 855 | B5: 586 | C5: 46 | D5: 223 | E5: =D5/A5 -> 0.26081871 | F5: 10 | G5: 15 | H5: 0 | I5: 22 | J5: =+G5+H5-I5 -> -7
A6: Critical Path Activities | D6: Free Float Management (Total) | H6: Failed Start Activities
D7: Greater Than 14 Days | F7: Less Than 14 Days
A8: Last Week | B8: This Week | C8: Diff | D8: Last Week | E8: This Week | F8: Last Week | G8: This Week | H8: Last Week | I8: This Week | J8: Flag
A9: 0 | B9: 0 | C9: =A9-B9 -> 0 | D9: 53 | E9: 172 | F9: 598 | G9: 570 | H9: 0 | I9: 2 | J9: =H9-I9 -> -2

Sheet EV-Chart Data
B2: Baseline Plan | E2: Revised / Recovery Plan | H2: Earned Value | K2: Gross Paid Value | N2: Forecast | Q2: Actual/Fcst vs Plan
A3: Month | B3: Monthly | C3: Cum | D3: % | E3: Monthly | F3: Cum | G3: % | H3: Monthly | I3: Cum | J3: % | K3: Monthly | L3: Cum | M3: % | N3: Monthly | O3: C um | Q3: Month | R3: Cum
A4: 46138 | B4: ` | C4: 0 | D4: =C4/$C$20 -> 0 | H4: =I4 -> 0 | I4: 0 | J4: =I4/$C$20 -> 0 | K4: 0 | L4: =K4 -> 0 | M4: 0 | N4: =O4 -> 0 | O4: 0 | R4: =Q4 -> 0 | T4: Actuals thru previous month
A5: 46168 | B5: 2034 | C5: =B5 -> 2034 | D5: =C5/$C$20 -> 6.1467137e-05 | H5: =I5-I4 -> 397090 | I5: 397090 | J5: =I5/$C$20 -> 0.011999993 | K5: 0 | L5: =L4+K5 -> 0 | M5: 0 | N5: =O5-O4 -> 397090 | O5: 397090 | Q5: =N5-B5 -> 395056 | R5: =Q5 -> 395056
A6: 46199 | B6: 4767 | C6: =B6+C5 -> 6801 | D6: =C6/$C$20 -> 0.00020552507 | H6: =I6-I5 -> 980202 | I6: 1377292 | J6: =I6/$C$20 -> 0.041621532 | K6: 0 | L6: =L5+K6 -> 0 | M6: 0 | N6: =O6-O5 -> 980202 | O6: 1377292 | Q6: =N6-B6 -> 975435 | R6: =Q6 -> 975435
A7: 46229 | B7: 36612 | C7: =B7+C6 -> 43413 | D7: =C7/$C$20 -> 0.0013119335 | H7: =I7-I6 -> 1192785 | I7: 2570077 | J7: =I7/$C$20 -> 0.077667294 | K7: 0 | L7: =K7+L6 -> 0 | M7: 0 | N7: =O7-O6 -> 1192785 | O7: 2570077 | Q7: =N7-B7 -> 1156173 | R7: =Q7 -> 1156173
A8: 46260 | B8: 3025382 | C8: =B8+C7 -> 3068795 | D8: =C8/$C$20 -> 0.092738468 | H8: =I8-I7 -> 2859151.8 | I8: 5429228.8 | J8: =I8/$C$20 -> 0.16407038 | K8: 0 | L8: =K8+L7 -> 0 | M8: 0 | N8: =O8-O7 -> 2859151.8 | O8: 5429228.8 | Q8: =N8-B8 -> -166230.21 | R8: =Q8 -> -166230.21 | T8: Forecast current and future months
A9: 46291 | B9: 7642106 | C9: =B9+C8 -> 10710901 | D9: =C9/$C$20 -> 0.32368162 | H9: =I9-I8 -> 482348.68 | I9: 5911577.5 | J9: =I9/$C$20 -> 0.17864687 | K9: 0 | L9: =K9+L8 -> 0 | M9: 0 | N9: =O9-O8 -> 482348.68 | O9: 5911577.5 | Q9: =N9-B9 -> -7159757.3 | R9: =Q9 -> -7159757.3
A10: 46321 | B10: 4071913 | C10: =B10+C9 -> 14782814 | D10: =C10/$C$20 -> 0.44673415 | H10: =I10-I9 -> 1183964.6 | I10: 7095542 | J10: =I10/$C$20 -> 0.21442608 | K10: 0 | L10: =K10+L9 -> 0 | M10: 0 | N10: =O10-O9 -> 1183964.6 | O10: 7095542 | P10: =O10/C20 -> 0.21442608 | Q10: =N10-B10 -> -2887948.4 | R10: =Q10 -> -2887948.4
A11: 46352 | B11: 2368425 | C11: =B11+C10 -> 17151239 | D11: =C11/$C$20 -> 0.51830755 | H11: 0 | K11: 0 | L11: =K11+L10 -> 0 | M11: 0 | N11: =O11-O10 -> 6427021.6 | O11: 13522564 | P11: =O11/C20 -> 0.40864959 | Q11: =N11-B11 -> 4058596.6 | R11: =Q11 -> 4058596.6
A12: 46382 | B12: 3761619 | C12: =B12+C11 -> 20912858 | D12: =C12/$C$20 -> 0.63198304 | H12: 0 | K12: 0 | L12: =K12+L11 -> 0 | M12: 0 | N12: =O12-O11 -> 7390294.4 | O12: 20912858 | P12: =O12/$O$20 -> 0.63198304 | Q12: =N12-B12 -> 3628675.4 | R12: =Q12 -> 3628675.4
A13: 46413 | B13: 2141463 | C13: =B13+C12 -> 23054321 | D13: =C13/$C$20 -> 0.69669769 | H13: 0 | N13: =O13-O12 -> 2141463 | O13: 23054321 | P13: =O13/$O$20 -> 0.69669769 | Q13: =N13-B13 -> 0 | R13: =Q13 -> 0
A14: 46444 | B14: 1637344 | C14: =B14+C13 -> 24691665 | D14: =C14/$C$20 -> 0.74617795 | H14: 0 | N14: =O14-O13 -> 1637344 | O14: 24691665 | P14: =O14/$O$20 -> 0.74617795 | Q14: =N14-B14 -> 0 | R14: =Q14 -> 0
A15: 46472 | B15: 2104692 | C15: =B15+C14 -> 26796357 | D15: =C15/$C$20 -> 0.80978139 | H15: 0 | N15: =O15-O14 -> 2104692 | O15: 26796357 | P15: =O15/$O$20 -> 0.80978139 | Q15: =N15-B15 -> 0 | R15: =Q15 -> 0
A16: 46503 | B16: 1246419 | C16: =B16+C15 -> 28042776 | D16: =C16/$C$20 -> 0.84744796 | H16: 0 | N16: =O16-O15 -> 1246419 | O16: 28042776 | P16: =O16/$O$20 -> 0.84744796 | Q16: =N16-B16 -> 0 | R16: =Q16 -> 0
A17: 46533 | B17: 955808 | C17: =B17+C16 -> 28998584 | D17: =C17/$C$20 -> 0.87633232 | H17: 0 | N17: =O17-O16 -> 955808 | O17: 28998584 | P17: =O17/$O$20 -> 0.87633232 | Q17: =N17-B17 -> 0 | R17: =Q17 -> 0
A18: 46564 | B18: 1588983 | C18: =B18+C17 -> 30587567 | D18: =C18/$C$20 -> 0.92435112 | H18: 0 | N18: =O18-O17 -> 1588983 | O18: 30587567 | P18: =O18/$O$20 -> 0.92435112 | Q18: =N18-B18 -> 0 | R18: =Q18 -> 0
A19: 46594 | B19: 2381575 | C19: =B19+C18 -> 32969142 | D19: =C19/$C$20 -> 0.99632191 | H19: 0 | N19: =O19-O18 -> 2381575 | O19: 32969142 | P19: =O19/$O$20 -> 0.99632191 | Q19: =N19-B19 -> 0 | R19: =Q19 -> 0
A20: 46625 | B20: 121711 | C20: =B20+C19 -> 33090853 | D20: =C20/$C$20 -> 1 | H20: 0 | N20: =O20-O19 -> 121711 | O20: 33090853 | P20: =O20/$O$20 -> 1 | Q20: =N20-B20 -> 0 | R20: =Q20 -> 0
B21: UPDATE ONLY YELLOW PORTION FROM PRIMAVERA EXPORT, IF NEEDED, EXTEND YELLOW PORTION BASED ON SCHEDULE.
O23: =C20-O20 -> 0 | P23: 12303404 | Q23: =P23+O23 -> 12303404
I24: 3309683
O25: =N9+O23 -> 482348.68
I26: 0
I27: 397090
I28: 1377292 | O28: =O23+O12 -> 20912858
I29: 2570077
C30: 6881451 | D30: 158436 | I30: 5429228.8 | L30: 4070077 | O30: 0
I31: 5911577.5 | O31: 397090
O32: 1377292
O33: 2570077
C34: 7095542 | D34: 166508 | O34: 5429228.8
O35: 5911577.5
O36: 11154139
O37: 13522564
O38: 20912858
O39: 23054321
O40: 24691665
D41: 5622620.3 | E41: 146227 | O41: 26796357
O42: 28042776
O43: 28998584
O44: 30587567
O45: 32969142
O46: 33090853

Sheet Physical-Chart Data
B2: Baseline Plan | E2: Revised / Recovery Plan | H2: Earned Effort % | K2: Forecast | N2: Achieved/Fcst vs Plan
A3: Week | B3: Monthly Effort | C3: Cum Effort | D3: Plan Wt.% | E3: MonthlyEffort | F3: Cum Effort | G3: Plan Wt.% | H3: Monthly Wt. | I3: Cum Wt. | J3: Achieved Wt.% | K3: Monthly Wt. | L3: Cum Wt. | M3: Wt.% | N3: Monthly Wt. | O3: Cum Wt.
A4: 46138 | B4: 36221.3 | C4: =B4 -> 36221.3 | D4: =C4/$C$20 -> 0.056731591 | H4: 22574 | I4: 22574 | J4: 0.042400292 | K4: =L4 -> 22574 | L4: 22574 | N4: =K4-B4 -> -13647.3 | O4: =N4 -> -13647.3 | Q4: Actuals thru previous month
A5: 46168 | B5: 10471.3 | C5: =C4+B5 -> 46692.6 | D5: =C5/$C$20 -> 0.073132259 | H5: 11000 | I5: =H5+I4 -> 33574 | J5: 0.081740865 | K5: =L5-L4 -> 11000 | L5: 33574 | N5: =K5-B5 -> 528.7 | O5: =O4+N5 -> -13118.6
A6: 46199 | B6: 14207.6 | C6: =C5+B6 -> 60900.2 | D6: =C6/$C$20 -> 0.095384905 | H6: 27880 | I6: =H6+I5 -> 61454 | J6: =I6/C$20 -> 0.096252294 | K6: =L6-L5 -> 27880 | L6: 61454 | N6: =K6-B6 -> 13672.4 | O6: =O5+N6 -> 553.8
A7: 46229 | B7: 16820.8 | C7: =C6+B7 -> 77721 | D7: =C7/$C$20 -> 0.12173047 | H7: 20650 | I7: =H7+I6 -> 82104 | J7: =I7/C$20 -> 0.12859535 | K7: =L7-L6 -> 20650 | L7: 82104 | N7: =K7-B7 -> 3829.2 | O7: =O6+N7 -> 4383
A8: 46260 | B8: 62842.3 | C8: =C7+B8 -> 140563.3 | D8: =C8/$C$20 -> 0.22015719 | H8: =I8-I7 -> 44752 | I8: 126856 | J8: =I8/C$20 -> 0.19868814 | K8: =L8-L7 -> 44752 | L8: 126856 | N8: =K8-B8 -> -18090.3 | O8: =O7+N8 -> -13707.3 | Q8: Forecast current and future months
A9: 46291 | B9: 54898.5 | C9: =C8+B9 -> 195461.8 | D9: =C9/$C$20 -> 0.30614194 | H9: =I9-I8 -> 21939 | I9: 148795 | J9: =I9/C$20 -> 0.23305009 | K9: =L9-L8 -> 21939 | L9: 148795 | N9: =K9-B9 -> -32959.5 | O9: =O8+N9 -> -46666.8
A10: 46321 | B10: 49442.2 | C10: =C9+B10 -> 244904 | D10: =C10/$C$20 -> 0.38358076 | H10: =I10-I9 -> 17713 | I10: 166508 | J10: =I10/C$20 -> 0.26079306 | K10: =L10-L9 -> 17713 | L10: 166508 | M10: =L10/$L$20 -> 0.26079306 | N10: =K10-B10 -> -31729.2 | O10: =O9+N10 -> -78396
A11: 46352 | B11: 40627.8 | C11: =C10+B11 -> 285531.8 | D11: =C11/$C$20 -> 0.44721403 | H11: 0 | K11: =L11-L10 -> 119023.8 | L11: 285531.8 | M11: =L11/$L$20 -> 0.44721403 | N11: =K11-B11 -> 78396 | O11: =O10+N11 -> 0
A12: 46382 | B12: 49100.4 | C12: =C11+B12 -> 334632.2 | D12: =C12/$C$20 -> 0.5241175 | H12: 0 | K12: =L12-L11 -> 49100.4 | L12: 334632.2 | M12: =L12/$L$20 -> 0.5241175 | N12: =K12-B12 -> 0 | O12: =O11+N12 -> 0
A13: 46413 | B13: 29292.3 | C13: =C12+B13 -> 363924.5 | D13: =C13/$C$20 -> 0.56999655 | H13: 0 | K13: =L13-L12 -> 29292.3 | L13: 363924.5 | M13: =L13/$L$20 -> 0.56999655 | N13: =K13-B13 -> 0 | O13: =O12+N13 -> 0
A14: 46444 | B14: 23424.4 | C14: =C13+B14 -> 387348.9 | D14: =C14/$C$20 -> 0.606685 | K14: =L14-L13 -> 23424.4 | L14: 387348.9 | M14: =L14/$L$20 -> 0.606685 | N14: =K14-B14 -> 0 | O14: =O13+N14 -> 0
A15: 46472 | B15: 56271.1 | C15: =C14+B15 -> 443620 | D15: =C15/$C$20 -> 0.69481958 | K15: =L15-L14 -> 56271.1 | L15: 443620 | M15: =L15/$L$20 -> 0.69481958 | N15: =K15-B15 -> 0 | O15: =O14+N15 -> 0
A16: 46503 | B16: 56367.4 | C16: =C15+B16 -> 499987.4 | D16: =C16/$C$20 -> 0.78310499 | K16: =L16-L15 -> 56367.4 | L16: 499987.4 | M16: =L16/$L$20 -> 0.78310499 | N16: =K16-B16 -> 0 | O16: =O15+N16 -> 0
A17: 46533 | B17: 38590.1 | C17: =C16+B17 -> 538577.5 | D17: =C17/$C$20 -> 0.84354672 | K17: =L17-L16 -> 38590.1 | L17: 538577.5 | M17: =L17/$L$20 -> 0.84354672 | N17: =K17-B17 -> 0 | O17: =O16+N17 -> 0
A18: 46564 | B18: 54478.7 | C18: =C17+B18 -> 593056.2 | D18: =C18/$C$20 -> 0.92887395 | K18: =L18-L17 -> 54478.7 | L18: 593056.2 | M18: =L18/$L$20 -> 0.92887395 | N18: =K18-B18 -> 0 | O18: =O17+N18 -> 0
A19: 46594 | B19: 44013.6 | C19: =C18+B19 -> 637069.8 | D19: =C19/$C$20 -> 0.99781023 | K19: =L19-L18 -> 44013.6 | L19: 637069.8 | M19: =L19/$L$20 -> 0.99781023 | N19: =K19-B19 -> 0 | O19: =O18+N19 -> 0
A20: 46625 | B20: 1398.1 | C20: =C19+B20 -> 638467.9 | D20: =C20/$C$20 -> 1 | K20: =L20-L19 -> 1398.1 | L20: 638467.9 | M20: =L20/$L$20 -> 1 | N20: =K20-B20 -> -2.3192115e-11 | O20: =O19+N20 -> -2.3192115e-11
B21: UPDATE ONLY YELLOW PORTION FROM PRIMAVERA EXPORT, IF NEEDED, EXTEND YELLOW PORTION BASED ON SCHEDULE.
G26: =B9-K9 -> 32959.5 | M26: =C20-L20 -> 0
L27: =M26+L10 -> 166508
F28: 156010 | M28: 201563.6 | N28: =M28+L29 -> 201563.6
L29: =C20-L20 -> 0
F30: 158436 | L30: =K9+L29 -> 21939
H31: 3309683 | I31: 103933.2
L32: 22574 | M32: =L30/2 -> 10969.5
L33: 33574 | P33: =K9+20000 -> 41939
L34: 61454
L35: 82104
L36: 126856
L37: 148795
L38: 244904
L39: 285531.8
L40: 334632.2
L41: 363924.5
L42: 387348.9
L43: 443620
L44: 499987.4
L45: 538577.5
... L48: 638467.9

Sheet Testing
A1: Testing and Commissioning
A2: Item | B2: Planned Start Date | C2: Planned Finish Date | D2: Forecast Start Date | E2: Forecast Finish Date | F2: Actual Start Date | G2: Actual Finish Date | H2: % Completed | I2: Open Comments | J2: Closed Comments
A3: Package 1 | B3: =B4 -> 46406 | C3: =C4 -> 46605 | D3: =D4 -> 46412 | E3: =E4 -> 46595 | H3: 0 | I3: 0 | J3: 0
A4: Testing and Comissioning | B4: 46406 | C4: 46605 | D4: 46412 | E4: 46595 | H4: 0 | I4: 0 | J4: 0
A5: Civil Works | B5: 46516 | C5: 46538 | D5: 46544 | E5: 46561 | H5: 0 | I5: 0 | J5: 0
A6: Storm Water Drainage Network | B6: 46406 | C6: 46424 | D6: 46464 | E6: 46482 | H6: 0 | I6: 0 | J6: 0
A7: Sewerage Network | B7: 46460 | C7: 46477 | D7: 46412 | E7: 46431 | H7: 0 | I7: 0 | J7: 0
A8: Portable Water | B8: 46468 | C8: 46485 | D8: 46474 | E8: 46491 | H8: 0 | I8: 0 | J8: 0
A9: Electrical Works | B9: 46586 | C9: 46602 | D9: 46576 | E9: 46594 | H9: 0 | I9: 0 | J9: 0
A10: CCTV Works | B10: 46590 | C10: 46605 | D10: 46580 | E10: 46595 | H10: 0 | I10: 0 | J10: 0
A11: Package 3 | B11: =B12 -> 46406 | C11: =C12 -> 46605 | D11: =D12 -> 46412 | E11: =E12 -> 46595 | H11: 0 | I11: 0 | J11: 0
A12: Testing and Comissioning | B12: 46406 | C12: 46605 | D12: 46412 | E12: 46595 | H12: 0 | I12: 0 | J12: 0
A13: Civil Works | B13: 46516 | C13: 46538 | D13: 46544 | E13: 46561 | H13: 0 | I13: 0 | J13: 0
A14: Storm Water Drainage Network | B14: 46406 | C14: 46424 | D14: 46464 | E14: 46482 | H14: 0 | I14: 0 | J14: 0
A15: Sewerage Network | B15: 46460 | C15: 46477 | D15: 46412 | E15: 46431 | H15: 0 | I15: 0 | J15: 0
A16: Portable Water | B16: 46468 | C16: 46485 | D16: 46474 | E16: 46491 | H16: 0 | I16: 0 | J16: 0
A17: Electrical Works | B17: 46586 | C17: 46602 | D17: 46576 | E17: 46594 | H17: 0 | I17: 0 | J17: 0
A18: CCTV Works | B18: 46590 | C18: 46605 | D18: 46580 | E18: 46595 | H18: 0 | I18: 0 | J18: 0
A19: Total | H19: =AVERAGE(H12:H18) -> 0 | I19: =AVERAGE(I12:I18) -> 0 | J19: =AVERAGE(J12:J18) -> 0

Sheet Conclusion
A1: تقدم سير مشروع تطوير شبكات البنية التحتية في مدينة سدير للصناعة والأعمال – المرحلة الثانية – الجزء الثاني
A2: معلومات المشروع | F2: نطاق المشروع | L2: موقع المشروع
A3: المقاول | B3: شركة تطوير التقنية للمقاولات | C3: الاستشاري | D3: شركة ايجيس السعودية للاستشارات | F3: البند | G3: الكمية الكلية | H3: الكمية المنفذة | I3: الكمية المتبقية | J3: نسبة المنفذ
A4: تاريخ استلام الموقع | B4: 06-01-2026 م | C4: مدة التنفيذ | D4: 18 شهرًا ميلاديًا | F4: أعمال الطرق والرصف (ROD) | G4: 18,252 م | H4: 0 | I4: 0 | J4: -
A5: بداية العقد | B5: من تاريخ استلام الموقع | C5: قيمة العقد (شامل ضريبة القيمة المضافة) | D5: 193,923,948.00 ريال | F5: أعمال شبكة مياة الشرب (WAT) | G5: 18,021 م | H5: 0 | I5: 0 | J5: -
A6: نسبة الإنجاز المخطط له | B6: 0 | C6: نسبة الإنجاز الفعلي | D6: 0.0003 | F6: أعمال شبكة المياه المعالجة (TSE) | G6: 16,141 م | H6: 0 | I6: 0 | J6: -
C7: =C10+C11+C12+C13+C14+C15+C16+C17 -> 1.6862952e+08 | F7: أعمال شبكة الصرف الصحي (SEW) | G7: 13,040 م | H7: 0 | I7: 0 | J7: -
A8: ملخص جدول الكميات | F8: أعمال شبكة صرف مياه الأمطار (STR) | G8: 13,600 م | H8: 0 | I8: 0 | J8: -
A9: مكونات المشروع | C9: التكلفة (غير شامل ضريبة القيمة المضافة) | D9: النسبة الاجمالية | F9: أعمال شبكة الري والمناظر الطبيعية (IRR) | G9: 29,570 م | H9: 0 | I9: 0 | J9: -
A10: أعمال الطرق | C10: 88002863 | D10: =C10/$C$7 -> 0.52187104 | F10: أعمال الشبكة الكهربائية (ELE) | G10: 51,500 م | H10: 0 | I10: 0 | J10: -
A11: شبكة تصريف مياه الأمطار | C11: 25408257 | D11: =C11/$C$7 -> 0.15067502 | F11: أعمال المراقبة بالكاميرات (CCTV) | G11: 125 كاميرا | H11: 0 | I11: 0 | J11: -
A12: شبكة الصرف الصحي | C12: 7071026.5 | D12: =C12/$C$7 -> 0.041932317 | F12: ملخص التوريدات | L12: تقدم أعمال layout
A13: شبكة المياه المعالجة (TSE) | C13: 4148179.8 | D13: =C13/$C$7 -> 0.024599369 | F13: البند | G13: الكمية الكلية | H13: الكمية المورده | I13: الكمية المتبقية | J13: نسبة التوريد
A14: شبكة مياه الشرب | C14: 7780464.9 | D14: =C14/$C$7 -> 0.0461394
A15: الأعمال الكهربائية | C15: 20085705 | D15: =C15/$C$7 -> 0.11911144
A16: أعمال تنسيق الموقع والري | C16: 6827173.9 | D16: =C16/$C$7 -> 0.040486232
A17: أعمال كاميرات المراقبة (CCTV) | C17: 9305849.7 | D17: =C17/$C$7 -> 0.055185175
A18: معالم البرنامج الزمني
A19: البند | C19: التاريخ حسب الجدول الزمني | D19: ملاحظة
A20: Mobilization Finish Milestone | C20: 46058 | D20: Finish
A21: Baseline Submission Finish Milestone | C21: 46058 | D21: UG | F21: التحديات والعوائق
A22: Technical Submittals Finish Milestone | C22: 46086 | D22: UG | F22: 1-
A23: Quality Lap Finish Milestone | C23: 46058 | D23: Finish | F23: 2-
A24: RBF Finish Milestone | C24: 46058 | D24: Finish | F24: 3-
A25: All Works Finish Milestone | C25: 46573 | D25: UG | F25: 4-
F26: 5-
F27: 6-
F28: 7-
